Workbook

Sheet Home
A1: THIS DOCUMENT WILL BE DEPRECATED BY THE END OF APRIL 2025 If you need support please submit a ticket via zendesk.
F5: RESULTS | I5: Share this document: https://bit.ly/FundedProjectsReporting
C6: Date Launched | D6: 1st Funding | E6: Launch Guide | F6: Official Results (PDF) | G6: Sheets Output (excel)
B7: Fund1 (pilot) | C7: Aug 2020 | D7: n/a | E7: n/a | F7: https://drive.google.com/file/d/1UmAGBRxWbQtpWjrNnvGuybgLiWs2zFMS/view | G7: n/a
B8: Fund2 | C8: Sep 2020 | D8: Jan 2021 | E8: n/a | F8: https://static.iohk.io/docs/catalyst/catalyst-voting-results-fund2.pdf | G8: n/a
B9: Fund3 | C9: Jan 2021 | D9: Apr 2021 | E9: n/a | F9: https://drive.google.com/file/d/1X6BnuFBvNO8yF2DeUgBqA3yyYSvqeKvg/view | G9: https://docs.google.com/spreadsheets/d/1ibl-9qpLRQiFhJQfcvIeSdfJr9LjGpU6WqHce6VIUnE/edit#gid=1538672709
B10: Fund4 | C10: Feb 2021 | D10: July 2021 | E10: n/a | F10: https://drive.google.com/file/d/19VMTYn_sv5Xsp2mC5VUN_-z_aXYHL_Dd/view | G10: https://docs.google.com/spreadsheets/d/13NC6SZ5MzQsYb-ufbuQHakxvLvPtZWv_02Aq17PFErI/edit#gid=1538672709
B11: Fund5 | C11: Mar 2021 | D11: Aug 2021 | E11: n/a | F11: https://drive.google.com/file/d/1HKmqyPebE87BUrPtE4AT5E2V4_yIZtT-/view | G11: https://docs.google.com/spreadsheets/d/156SdqPYOBkC5iQQeOOZc9yXSYoNHb-J-wJrem-xax78/edit#gid=1848314097
B12: Fund6 | C12: Aug 2020 | D12: Nov 2021 | E12: https://drive.google.com/file/d/1-8rQ4KBVJmCuS4MYLevryZFHicip97sH/view | F12: https://drive.google.com/file/d/13h5JFtwqyylMUNMoRGXQZ-FJEM4bznOJ/view?usp=sharing | G12: https://docs.google.com/spreadsheets/d/1y-7U88FRvsEEzm98KbEswUGuy4q-eTeoFTV3EFrc6b4/edit#gid=1183771745
B13: Fund7 | C13: Nov 2021 | D13: Feb 2022 | E13: https://drive.google.com/file/d/1E47HUA9Xikla1v9bvgxw-pR3_4kSnTye/view | F13: https://bit.ly/3HJNhuX | G13: https://docs.google.com/spreadsheets/d/19_TEovS_Gemwvz2qlc6jGPizqAY8ZeDrzbH3DSeXyto/edit#gid=309291557
B14: Fund8 | C14: Feb 2022 | D14: May 2022 | E14: https://bit.ly/3LDYNuk | F14: https://drive.google.com/file/d/1s3jCE7pmoUujy3ASMia-UhFl2KLi_hnf/view | G14: https://docs.google.com/spreadsheets/d/15ELXp81NfvXHgrerTbuIofZOXBsdjocN1YgBK0gPP3E/edit#gid=2111315347
B15: Fund9 | C15: Jun 2022 | D15: Oct 2022 | E15: https://bit.ly/Fund9-Launch-Guide | F15: https://bit.ly/Fund9_Results | G15: https://docs.google.com/spreadsheets/d/1MycQL-dkqf1xEW8xcr7vqcfHY6D7MHnG9ylDKNLSnAA/edit?usp=sharing
B16: Fund10
B17: Fund11
B18: Fund12
B19: Fund13
B20: MIRO | D20: https://bit.ly/3wiBHjP
B22: Each Funded Project is expected to submit one reporting form each month. If this form is missing - funding is paused until it is completed. You can track progress via individual tabs in this document.
B25: Monthly Report Form: | C25: https://bit.ly/CatalystMonthlyReport
B26: Monthly Report Output | C26: https://bit.ly/Funded-Projects-Reports
B28: Final Close Out Report & Video | I28: Browse All Projects
B29: Is your project nearing completion or has already completed? Please reach out to catalyst (at) iohk.io directly to request the close out process to be intiated. If done properly, your project will be marked as COMPLETED on this tracker including link to your final reports. Do you not see your project reporting anymore? Perhaps they've also completed. Reach out to them directly to inspire them to share close out reports with the rest of the community officially. | H29: projectcatalyst.io
B30: Close Out Report Form: | C30: https://bit.ly/3XgkPZr
B32: Contact for Qs: via email catalyst (at) iohk.io
B34: LEGEND:
B35: PENDING | C35: Project is currently under way executing on their deliverables
B36: COMPLETED | C36: Project has completed their scope of delivery based on their voted proposal and are now offboarded from reporting requirements
B37: PAUSED | C37: Project ran into an issue, reached out and decided to pause their operations until further notice - funding also pauses
B39: Note: This is not a real time dashboard. Consider it as a continous work in progress (WIP) and minimum viable product (MVP) as data can change as new input is available. Information is provided as in and does not constitute an investment advice or otherwise. Any feedback or further suggestions how to improve are more than welcome. Is there something you think would bring value to measure/track, let us know. Think about where our attention needs to be. Comment directly in this document or reach out to us Note: ROI dashboard is one of the 2022 goals to tackle! .

Sheet COMPLETED
A1: THIS DOCUMENT WILL BE DEPRECATED SOON If you need support please submit a ticket via zendesk.
C5: Updated: 23 February 2026 | D5: Project Completions | F5: Funding ($) | M5: Mandatory TH pres (preceeding close out reports) | O5: Mandatory Close Outs (since Nov 2021)
B6: # | C6: Project ID# | D6: Project Name (original proposal hyperlink) | E6: Project Status | F6: Requested | G6: Distributed to date | H6: Remaining | I6: Primary Proposer - Guarantor | J6: Fund # | K6: Challenge Category | L6: Date Completed | M6: Final TH Pres | N6: Final TH Video | O6: Final Close Out Report | P6: Final Close Out Video | Q6: Submitted Close Out Video
D7: ='Summary (draft)'!G6 -> 1581 | F7: =SUM(F8:F2729) -> 1.452159e+08 | G7: =SUM(G8:G2729) -> 1.4157987e+08 | H7: =SUM(H8:H2729) -> 3636029.7
B8: 1 | C8: 200003 | D8: Create message signing standard | E8: COMPLETED | F8: 5000 | G8: 5000 | H8: =F8-G8 -> 0 | I8: Sebastien Guillemot | J8: Fund2 | K8: Developer ecosystem | L8: 44287 | M8: https://docs.google.com/presentation/d/1CCkVN0jNpEBZjzjVWkrft2XBxNH2U8NwxvaZdOwRxIY/edit#slide=id.ge8e7e12b51_0_8915 | N8: https://youtu.be/C1pcZWFqAV8?t=898 | O8: n/a | Q8: n/a
B9: 2 | C9: 200010 | D9: Ouroboros over RINA | E9: COMPLETED | F9: 10700 | G9: 10700 | H9: =F9-G9 -> 0 | I9: Jason Durham | J9: Fund2 | K9: Developer ecosystem | L9: 44287 | M9: https://docs.google.com/presentation/d/1DwyQEluti2WMnKAF4KxJS9gnJwM0yIy4PVKj4yzvq7U/edit#slide=id.gd0bd6b1465_0_0 | N9: https://www.youtube.com/watch?v=n4d5iXuEeuo | O9: n/a | Q9: n/a
B10: 3 | C10: 500063 | D10: Testnet Cardanoscan Explorer | E10: COMPLETED | F10: 7500 | G10: 7500 | H10: =F10-G10 -> 0 | I10: Ashish Prajapati | J10: Fund5 | K10: Developer Ecosystem | L10: 44409 | M10: https://docs.google.com/presentation/d/1CCkVN0jNpEBZjzjVWkrft2XBxNH2U8NwxvaZdOwRxIY/edit#slide=id.ge8e7e12b51_0_6235 | N10: https://youtu.be/C1pcZWFqAV8?t=541 | O10: n/a | Q10: n/a
B11: 4 | C11: 300004 | D11: Cardano IntelliJ IDEA Plugin (MVP) | E11: COMPLETED | F11: 15000 | G11: 15000 | H11: =F11-G11 -> 0 | I11: Satya Ranjan | J11: Fund3 | K11: Developer ecosystem | L11: 44440 | M11: https://docs.google.com/presentation/d/1Xi8COzkjn7vINiWNnSRay0as2nyrHNRLkng_oh8JYzU/edit#slide=id.geb801ec31f_1_13938 | N11: https://drive.google.com/file/d/1vgbwTL76_esvtuzEP_BOPTA66DXyqr-j/view | O11: n/a | Q11: n/a
B12: 5 | C12: 300006 | D12: CardanoSharp - .NET Library | E12: COMPLETED | F12: 19520 | G12: 19520 | H12: =F12-G12 -> 0 | I12: Kyle Johns | J12: Fund3 | K12: Developer ecosystem | L12: 44440 | M12: https://docs.google.com/presentation/d/1_BGhCFyPgpzoHmx_wuHcskOWDAQYU9pcVu0XXYCV6g4/edit#slide=id.gef920b8573_0_11 | N12: https://drive.google.com/file/d/1VBaPGjOLOKK_3CYlU6Y5JUqsP03P-Mtb/view | O12: n/a | Q12: n/a
B13: 6 | C13: 400049 | D13: West Africa Proposer Outreach | E13: COMPLETED | F13: 6000 | G13: 6000 | H13: =F13-G13 -> 0 | I13: Josh Fielding | J13: Fund4 | K13: Proposer Outreach | L13: 44440 | M13: https://docs.google.com/presentation/d/1-2GfEnkkK01bp3KzbAVKb7nW6LYXkTOrIZ0qVvNTs9k/edit#slide=id.gef920b8573_0_11 | N13: https://youtu.be/7_171-XgPdI?t=161 | O13: n/a | Q13: n/a
B14: 7 | C14: 200001 | D14: Address Gap in SPO Education/Comms | E14: COMPLETED | F14: 10700 | G14: 10700 | H14: =F14-G14 -> 0 | I14: Ron Hill | J14: Fund2 | K14: n/a | L14: 44440 | M14: n/a | N14: n/a | O14: https://drive.google.com/file/d/17Ac02cFF5YX2VWIYyki-XIJU5S0ORJ-M/view?usp=sharing
B15: 8 | C15: 400019 | D15: Guided Onboarding Experience | E15: COMPLETED | F15: 15000 | G15: 15000 | H15: =F15-G15 -> 0 | I15: Michael McNulty | J15: Fund4 | K15: Catalyst Value Onboarding | L15: 44440 | M15: n/a | N15: n/a | O15: https://drive.google.com/file/d/10JQGY9I-_mvjjfAAfKdyoEUlu2zs0Gpi/view?usp=sharing | P15: https://youtu.be/GcIlwjjnSwI | Q15: https://www.youtube.com/watch?v=0rh_IggFq_A
B16: 9 | C16: 400012 | D16: Cardano-based Marketplace | E16: COMPLETED | F16: 5000 | G16: 5000 | H16: =F16-G16 -> 0 | I16: Michael Parkinson | J16: Fund4 | K16: dApps & Integrations | L16: 44440 | M16: n/a | N16: n/a | O16: https://drive.google.com/file/d/1QLhnoaS5e_sQeYOZ7GAXIUJWdLSXlaRv/view?usp=sharing | P16: https://youtu.be/NA3e3CkFtno | Q16: https://drive.google.com/file/d/1MO883gsGSH0_79hYf19kuTxGGInboRV7/view?usp=sharing
B17: 10 | C17: 300020 | D17: Visual Studio Smart Contract Plugin | E17: COMPLETED | F17: 16450 | G17: 16450 | H17: =F17-G17 -> 0 | I17: Rob Greig | J17: Fund3 | K17: Developer ecosystem | L17: 44470 | M17: https://docs.google.com/presentation/d/1R40XA9w3hdogAkcDJNpL3gM3S9q8pcTIQYCokrEow8s/edit#slide=id.gf9a9b45fbc_0_5002 | N17: https://youtu.be/VudbBWPh-qA?t=2108 | O17: n/a | Q17: n/a
B18: 11 | C18: 400007 | D18: Cardano China Info Hub | E18: COMPLETED | F18: 16700 | G18: 16700 | H18: =F18-G18 -> 0 | I18: Bullish Dumpling | J18: Fund4 | K18: Local Community Centers | L18: 44470 | M18: https://docs.google.com/presentation/d/1KHx-tID5RdWyoXitLQpdf2Ti3EgSF9RjilC8_-jJWwk/edit#slide=id.gf69e0ccf0f_1_2387 | N18: https://youtu.be/yts3EFEODtU?t=240 | O18: n/a | Q18: n/a
B19: 12 | C19: 400032 | D19: NFT-DAO NFT metadata standards | E19: COMPLETED | F19: 28648 | G19: 28648 | H19: =F19-G19 -> 0 | I19: Rich Kopcho | J19: Fund4 | K19: DApps & Integrations | L19: 44470 | M19: n/a | N19: n/a | O19: https://drive.google.com/file/d/1leCReF4Qyhk-1sUm7tzIY59kx78UDRtJ/view?usp=sharing | Q19: https://drive.google.com/file/d/1CHVVhAO8cisL9G-bAw656C3Es7tVN1kF/
B20: 13 | C20: 400003 | D20: Adagov.org (Co-creation) | E20: COMPLETED | F20: 8000 | G20: 8000 | H20: =F20-G20 -> 0 | I20: Ro Mathew | J20: Fund4 | K20: Distributed Decision Making | L20: 44470 | M20: n/a | N20: n/a | O20: https://drive.google.com/file/d/1IpZexVamBRg4mWtrxmK5ZmEIXJj7Tv-K/view?usp=sharing | P20: https://youtu.be/udkz_JBKPEM | Q20: https://drive.google.com/file/d/1qfOaLzw46exfNMLeBH8uIamLnKo53yG5/view?usp=sharing
B21: 14 | C21: 500060 | D21: Quality-Assurance-DAO | E21: COMPLETED | F21: 5 | G21: 5 | H21: =F21-G21 -> 0 | I21: Stephen Whitenstall | J21: Fund5 | K21: Developer Ecosystem | L21: 44501 | M21: https://docs.google.com/presentation/d/11StNCcf4sBhWAgWKL7kWLK1adfXg7i9dd2i7KWgrY8U/edit#slide=id.g1050bd8c40a_0_8840 | N21: https://youtu.be/olOxEinXrgM?t=1402 | Q21: n/a
B22: 15 | C22: 400014 | D22: Diversify Voting Influence | E22: COMPLETED | F22: 14000 | G22: 14000 | H22: =F22-G22 -> 0 | I22: Kenric Nelson | J22: Fund4 | K22: Distributed Decision Making | L22: 44501 | M22: https://docs.google.com/presentation/d/1R40XA9w3hdogAkcDJNpL3gM3S9q8pcTIQYCokrEow8s/edit#slide=id.gf9a9b45fbc_0_10242 | N22: https://youtu.be/VudbBWPh-qA?t=1082 | O22: https://docs.google.com/document/d/147av_tt9p1UgtWemZTJ7uTLrF706PaLBYTw__juwTAE/edit?usp=sharing | P22: https://youtu.be/pfboXRFkucQ | Q22: https://drive.google.com/file/d/1NY20WHgY1YLR32D3TP1v5LyD5zUvUPd1/view
B23: 16 | C23: 500056 | D23: Paper wallet terminal for in a shop | E23: COMPLETED | F23: 12000 | G23: 12000 | H23: =F23-G23 -> 0 | I23: Maarten Menheere | J23: Fund5 | K23: Grow Africa, Grow Cardano | L23: 44501 | M23: https://docs.google.com/presentation/d/10Xk7dbkuSveM0oJefMzTbZqsniikn0Hoe-Rtgx3v8oI/edit#slide=id.gf69e0ccf0f_1_4675 | N23: https://youtu.be/Pw6VdcWi8NE?t=1067 | O23: https://drive.google.com/file/d/1Bt2ZoWSZspJ7dHyw2ZkKgcz4kE7_P-VQ/view?usp=sharing | P23: https://youtu.be/-WTyBVomdtQ | Q23: https://drive.google.com/file/d/1ou8Jsv4-1nOdGJLo5AQ9zQtJ7oLqCmNE/view?%20usp=sharing
B24: 17 | C24: 500068 | D24: WADA Uni Students Catalyst Registry | E24: COMPLETED | F24: 11000 | G24: 11000 | H24: =F24-G24 -> 0 | I24: Mercy Tachie-Menson | J24: Fund5 | K24: Catalyst Value Onboarding | L24: 44501 | M24: n/a | N24: n/a | O24: https://docs.google.com/document/d/1-cZa5MVgX9oJv-gVEVTHsxsd6grd1pe-7nTZVmQJexM/edit?usp=sharing | P24: https://youtu.be/txmgKUFpK6E | Q24: https://drive.google.com/file/d/1u1WjH-eapdgNh9827NfiIoO4GPRtVmzD/view?usp=drive_web
B25: 18 | C25: 400030 | D25: Local Centers in West Africa | E25: COMPLETED | F25: 4000 | G25: 4000 | H25: =F25-G25 -> 0 | I25: Mercy Tachie-Menson | J25: Fund4 | K25: Local Community Centers | L25: 44501 | M25: n/a | N25: n/a | O25: https://docs.google.com/document/d/1-cZa5MVgX9oJv-gVEVTHsxsd6grd1pe-7nTZVmQJexM/edit?usp=sharing | P25: https://youtu.be/IScHE-goK5I | Q25: https://drive.google.com/file/d/1u1WjH-eapdgNh9827NfiIoO4GPRtVmzD/view?usp=drive_web
B26: 19 | C26: 600042 | D26: Community Subscription Fees Recoup | E26: COMPLETED | F26: 581 | G26: 581 | H26: =F26-G26 -> 0 | I26: Steven Aldrich | J26: Fund6 | K26: Catalyst value onboarding | L26: 44501 | M26: n/a | N26: n/a | O26: https://drive.google.com/file/d/1-74_XPCfxDxiOdSn1bUJevlqWsObKkgU/view?usp=sharing | Q26: n/a
B27: 20 | C27: 600084 | D27: Indigo: Synthetic Assets on Cardano | E27: COMPLETED | F27: 60000 | G27: 60000 | H27: 0 | I27: Daniel Short | J27: Fund6 | K27: Atala PRISM DID Mass-Scale Adoption | L27: 44531 | M27: https://docs.google.com/presentation/d/11StNCcf4sBhWAgWKL7kWLK1adfXg7i9dd2i7KWgrY8U/edit#slide=id.g1050bd8c40a_0_6160 | N27: https://youtu.be/olOxEinXrgM?t=328 | O27: https://docs.google.com/document/d/1474INdXZI_EKguvPH3GssQEVM5zdxdz-b4KsraW5JKM/edit?usp=sharing | P27: https://youtu.be/UO91GPqxRpc | Q27: https://drive.google.com/file/d/1YXk8ClEIq4TamUdgB5_SausWNr40h7CI/view?usp=sharing
B28: 21 | C28: 600005 | D28: Add multilanguage to CNFTHub.io | E28: COMPLETED | F28: 500 | G28: 500 | H28: 0 | I28: Huth Solo | J28: Fund6 | K28: Scale-UP Cardano's Community Hubs | L28: 44531 | M28: n/a | N28: n/a | O28: https://docs.google.com/document/d/17w8yN7niNrdGTfB2qk5BquPSVGDk7BHL/edit?usp=sharing&ouid=117059928304090739258&rtpof=true&sd=true | P28: https://youtu.be/sntE2N2qNr4 | Q28: https://youtu.be/SJ_8tQLhyms
B29: 22 | C29: 500006 | D29: Artificial Intelligence/ML API | E29: COMPLETED | F29: 80000 | G29: 80000 | H29: =F29-G29 -> 0 | I29: Javier Paz | J29: Fund5 | K29: Developer Ecosystem | L29: 44531 | M29: n/a | N29: n/a | O29: https://drive.google.com/file/d/1GYbtCl7bPLhPLVaxl08jfOC2i6NTf34D/view?usp=sharing | P29: https://youtu.be/RYuj_wj0nQ4 | Q29: https://youtu.be/iSKDxZH5Vyc
B30: 23 | C30: 500032 | D30: Glow Formal verification | E30: COMPLETED | F30: 60000 | G30: 60000 | H30: =F30-G30 -> 0 | I30: Alexander Smart | J30: Fund5 | K30: Developer Ecosystem | L30: 44531 | M30: n/a | N30: n/a | O30: https://drive.google.com/file/d/1aNPkbKSBdos5swJGgRj00NmQ6N1Tpvyq/view?usp=sharing | P30: https://youtu.be/Xr1MnlaFKM4 | Q30: https://youtu.be/YSvkNDgFbYg
B31: 24 | C31: 300007 | D31: Comprehensive NFT Framework Collab | E31: COMPLETED | F31: 48965 | G31: 48965 | H31: =F31-G31 -> 0 | I31: Rich Kopcho | J31: Fund3 | K31: DApp creation | L31: 44531 | M31: n/a | N31: n/a | O31: https://drive.google.com/file/d/1FqRIxooA_5OpU_EfyvpRat0Qdur2ZWZF/view?usp=sharing | P31: https://youtu.be/KY1c-0dP4zg | Q31: https://youtu.be/i5jOwWzljk4
B32: 25 | C32: 600017 | D32: Books for Blocks | E32: COMPLETED | F32: 600 | G32: 600 | H32: =F32-G32 -> 0 | I32: williamofthesun | J32: Fund6 | K32: Partnerships for Global Adoption | L32: 44531 | M32: n/a | N32: n/a | O32: https://drive.google.com/file/d/14wyU2EaXDs-yCIZut7AafG03mGmnSmCl/view?usp=sharing | P32: https://youtu.be/V6HCIxSqpkU | Q32: https://drive.google.com/file/d/1s19rPZSZrd_rZoImJt9i_1F2G6xVs3Fm/view?usp=sharing
B33: 26 | C33: 500065 | D33: Tokenizing GitHub Pull request | E33: COMPLETED | F33: 12000 | G33: 12000 | H33: =F33-G33 -> 0 | I33: Max Bin Li | J33: Fund5 | K33: Developer Ecosystem | L33: 44531 | M33: n/a | N33: n/a | O33: https://drive.google.com/file/d/1_qFSfFiUWt_IwVjkkDRehRRi2wMUOiSy/view?usp=sharing | P33: https://youtu.be/65UuqD0HTHw | Q33: https://drive.google.com/file/d/1E_-B4AbpSH-rnnvUFsm1xTSNfGpz3wzJ/view
B34: 27 | C34: 500038 | D34: Introducing Empowa | E34: COMPLETED | F34: 60000 | G34: 60000 | H34: =F34-G34 -> 0 | I34: Phil Lewis | J34: Fund5 | K34: Grow Africa, Grow Cardano | L34: 44531 | M34: n/a | N34: n/a | O34: https://drive.google.com/file/d/12D40OuAK3Wi1croI4WhNH-yDxIOgJQ9w/view?usp=sharing | P34: https://youtu.be/2E1BbSdxDMk | Q34: https://youtu.be/5qCnVTKZNuc
B35: 28 | C35: 600026 | D35: Cardano Wallet JS Multisig | E35: COMPLETED | F35: 4800 | G35: 4800 | H35: =F35-G35 -> 0 | I35: Leobel Izquierdo | J35: Fund6 | K35: Developer ecosystem | L35: 44562 | M35: n/a | N35: n/a | O35: https://drive.google.com/file/d/133GxLWHBIxVx_1Tj1M7ydJdmMWgcgdzM/view?usp=sharing | P35: https://youtu.be/NxsSRQgSDE0 | Q35: https://www.youtube.com/watch?v=H7O4b_PtQ-8&t=41s
B36: 29 | C36: 200004 | D36: GimbaLabs (Cardano Starter Kits & APIs) | E36: COMPLETED | F36: 28355 | G36: 28355 | H36: =F36-G36 -> 0 | I36: Juliane Montag | J36: Fund2 | K36: n/a | L36: 44593 | M36: https://docs.google.com/spreadsheets/d/1bfnWFa94Y7Zj0G7dtpo9W1nAYGovJbswipxiHT4UE3g/edit#gid=416498551 | N36: https://youtu.be/PELxvpPWuYk?t=285 | O36: https://drive.google.com/file/d/1BWUA29-O_mbhIT-KhXP-9G-wBAMKIQmL/view?usp=sharing | P36: https://youtu.be/8MauHjTKtGY | Q36: https://drive.google.com/file/d/1mvZ43cGM2y1HtYAAlHNzowerM_qdmf3u/view?usp=sharing
B37: 30 | C37: 500057 | D37: PCDiscord - Bot to Assign Roles | E37: COMPLETED | F37: 500 | G37: 500 | H37: =F37-G37 -> 0 | I37: Tevo Saks | J37: Fund5 | K37: Catalyst Value Onboarding | L37: 44593 | M37: n/a | N37: n/a | O37: https://drive.google.com/file/d/1KK2mFMz4HYyTDZpOZEEiUhnNZY90LE72/view?usp=sharing | P37: https://youtu.be/IoBnqIzjetc | Q37: https://youtu.be/QhEbdpPq5Q0
B38: 31 | C38: 600095 | D38: Mini Proposals as a Service | E38: COMPLETED | F38: 1404 | G38: 1404 | H38: =F38-G38 -> 0 | I38: Tevo Saks | J38: Fund6 | K38: DLT Entrepreneurship Toolbox | L38: 44593 | M38: n/a | N38: n/a | O38: https://drive.google.com/file/d/1296-tef_bbg4LL_kSwHOqPZxN6v6VoVe/view?usp=sharing | P38: https://youtu.be/YQ0sdE2OhOE | Q38: https://youtu.be/EZBnaFt9BPk
B39: 32 | C39: 600051 | D39: Crypto Regulation Surveillance | E39: COMPLETED | F39: 9000 | G39: 9000 | H39: =F39-G39 -> 0 | I39: Maury Shenk | J39: Fund6 | K39: F6: Cardano Emerging Threat Alarm | L39: 44593 | M39: n/a | N39: n/a | O39: https://drive.google.com/file/d/128BeS_xJaO3Ftv9DGVrJ-5GQIgUYXL55/view?usp=sharing | P39: https://youtu.be/040pfxj-xXs | Q39: https://youtu.be/9DHT5mogILo
B40: 33 | C40: 600011 | D40: API for Multi-Delegation Portfolios | E40: COMPLETED | F40: 10000 | G40: 10000 | H40: =F40-G40 -> 0 | I40: viperstakepool | J40: Fund6 | K40: DApps & Integrations | L40: 44593 | M40: n/a | N40: n/a | O40: https://drive.google.com/file/d/1rphX1xB8q9ViUC0rjt0y-FQIn8A-WKb2/view?usp=sharing | P40: https://youtu.be/zV_ZNI74Nhc | Q40: https://youtu.be/2iWbNCLkHMY
... B48: 41 | C48: 600078 | D48: Gravatar for ADA Wallets | E48: COMPLETED | F48: 87700 | G48: 87700 | H48: =F48-G48 -> 0 | I48: Matthias Sieber | J48: Fund6 | K48: Developer ecosystem | L48: 44593 | M48: n/a | N48: n/a | O48: https://drive.google.com/file/d/1oJwqPYBGvh6yO8RU9eIoSErtecChRA-J/view?usp=sharing | P48: https://youtu.be/p-9fwgygrqI | Q48: https://drive.google.com/file/d/1DpUZsPfEzgSK_XGJIbv6DKU53Gjr0BIS/view?usp=sharing
B49: 42 | C49: 700061 | D49: Catalyst Circle Treasury Management | E49: COMPLETED | F49: 11400 | G49: 11400 | H49: =F49-G49 -> 0 | I49: Miroslav Rajh | J49: Fund7 | K49: Miscellaneous Challenge | L49: 44593 | M49: n/a | N49: n/a | O49: https://drive.google.com/file/d/1S3Ktje_yL8Wu8U1KED8VhPGP3r-Qy88g/view?usp=sharing | Q49: https://drive.google.com/drive/folders/1HsTq52QWP6UlWbHO4ZzBFxsIrvysCjNL
B50: 43 | C50: 500062 | D50: Step-by-Step Guide: Off-Chain Code | E50: COMPLETED | F50: 5000 | G50: 5000 | H50: =F50-G50 -> 0 | I50: Michael Parkinson | J50: Fund5 | K50: Developer Ecosystem | L50: 44621 | M50: n/a | N50: n/a | O50: https://drive.google.com/file/d/1WzqMZjJRU0MUXSecuFWnyPTT1SCyjt71/view?usp=sharing | P50: https://youtu.be/2kQiTy-jiJo | Q50: https://www.youtube.com/watch?v=o1UEkVhiAs4
B51: 44 | C51: 600021 | D51: Cardano Health Infrastructure | E51: COMPLETED | F51: 10000 | G51: 10000 | H51: =F51-G51 -> 0 | I51: David Dale | J51: Fund6 | K51: Grow Africa, Grow Cardano | L51: 44621 | M51: n/a | N51: n/a | O51: https://drive.google.com/file/d/1C4vqtRGGjSDzDxnX-JreCTIdcKoVpdSw/view?usp=sharing | P51: https://youtu.be/FMxVav-Rfl4 | Q51: https://youtu.be/vN-V7SjhoPs
B52: 45 | C52: 600085 | D52: Interoperability as growth driver | E52: COMPLETED | F52: 37000 | G52: 37000 | H52: =F52-G52 -> 0 | I52: Rodolfo Miranda | J52: Fund6 | K52: Atala PRISM DID Mass-Scale Adoption | L52: 44621 | M52: n/a | N52: n/a | O52: https://drive.google.com/file/d/1w2i9MpkL1zscFXY9uLS0tFZE6gxhYG0u/view?usp=sharing | P52: https://youtu.be/d6SUDoRwQos | Q52: https://www.youtube.com/watch?v=lUnuMdQEQtM
B53: 46 | C53: 400046 | D53: University/College Outreach | E53: COMPLETED | F53: 10000 | G53: 10000 | H53: =F53-G53 -> 0 | I53: Jeff Granger | J53: Fund4 | K53: Proposer Outreach | L53: 44621 | M53: n/a | N53: n/a | O53: https://drive.google.com/file/d/1qSs1D1tkz4q2_fL00_xYjXSG1WSJt7Hd/view?usp=sharing | P53: https://youtu.be/drHdyFhUy1w | Q53: https://drive.google.com/file/d/1_9tq9xVPJ8OiYQ_7x4qapghdGk1lBhpa/view?usp=sharing
B54: 47 | C54: 700080 | D54: Create Teaming Agreement Templates | E54: COMPLETED | F54: 7000 | G54: 7000 | H54: =F54-G54 -> 0 | I54: Len Delunas | J54: Fund7 | K54: Miscellaneous Challenge | L54: 44621 | M54: n/a | N54: n/a | O54: https://drive.google.com/file/d/1Z7Khe42FeuItld1KipAQ0w-u26uUv2Yb/view?usp=sharing | P54: https://youtu.be/eYhCBEOcze0 | Q54: https://www.youtube.com/watch?v=eAioFRb2RTAA
B55: 48 | C55: 700222 | D55: Rarety - SC based NFT drop platform | E55: COMPLETED | F55: 10000 | G55: 10000 | H55: =F55-G55 -> 0 | I55: Skrypt Labs | J55: Fund7 | K55: Mini/Low-Budget Dapps & Integrations | L55: 44621 | N55: n/a | O55: https://drive.google.com/file/d/1X4EyQqKFUahci2WbQi2cJH2I7DGxFfUU/view?usp=sharing | P55: https://youtu.be/kBFqhcVO2xE | Q55: https://www.youtube.com/watch?v=C9Fxwqypa1c
B56: 49 | C56: 500035 | D56: IdeaScale Improvements | E56: COMPLETED | F56: 10000 | G56: 10000 | H56: =F56-G56 -> 0 | I56: Erik Siebert | J56: Fund5 | K56: Distributed Decision Making | L56: 44621 | M56: n/a | N56: n/a | O56: https://drive.google.com/file/d/1G_H-umnnw1FjOwr78YDTO3GHIOmq_s5C/view?usp=sharing | P56: https://youtu.be/uGCrMKD5XVs | Q56: https://vimeo.com/692050866/39b31c1e2a
B57: 50 | C57: 600086 | D57: Japanese SPO community management | E57: COMPLETED | F57: 16830 | G57: 16830 | H57: =F57-G57 -> 0 | I57: Yu Kagaya | J57: Fund6 | K57: Multilingual resources | L57: 44621 | M57: n/a | N57: n/a | O57: https://drive.google.com/file/d/1nlifaT8sKB6FeHH8L8IiqDp64d09IN2-/view?usp=sharing | P57: https://youtu.be/tMW1NVkQiok | Q57: https://youtu.be/bxw_paVjnlU
B58: 51 | C58: 700076 | D58: Community Pharmacy System | E58: COMPLETED | F58: 24000 | G58: 24000 | H58: =F58-G58 -> 0 | I58: Dale David | J58: Fund7 | K58: Nation Building Dapps | L58: 44621 | M58: n/a | N58: n/a | O58: https://drive.google.com/file/d/1DOE2qbpJeORgJMQxku-tpFmiJ2qwpT0z/view?usp=sharing | P58: https://youtu.be/4Z-mzm8dbLI | Q58: https://youtu.be/sBVUBxq3UpU
B59: 52 | C59: 700262 | D59: Vaccine Management Platform + APIs | E59: COMPLETED | F59: 32000 | G59: 32000 | H59: =F59-G59 -> 0 | I59: Dale David | J59: Fund7 | K59: Nation Building Dapps | L59: 44621 | M59: n/a | N59: n/a | O59: https://drive.google.com/file/d/15FnIAgPL-ksRUxah559msM3l6t9Tz6aI/view?usp=sharing | P59: https://youtu.be/ZrccVXUe3vY | Q59: https://youtu.be/sBVUBxq3UpU
B60: 53 | C60: 600144 | D60: Video content about Mini-Proposals | E60: COMPLETED | F60: 1717 | G60: 1717 | H60: =F60-G60 -> 0 | I60: Tevo Saks | J60: Fund6 | K60: Proposer outreach | L60: 44621 | M60: n/a | N60: n/a | O60: https://drive.google.com/file/d/1chse8TeLLde4j5hNDRqVYR_yebzIJYpr/view?usp=sharing | P60: https://youtu.be/s8-wK2U8Mgg | Q60: https://youtu.be/9dqyPiJpn2k
B61: 54 | C61: 600023 | D61: Cardano in South L.A. | E61: COMPLETED | F61: 1200 | G61: 1200 | H61: =F61-G61 -> 0 | I61: Matthias Sieber | J61: Fund6 | K61: Scale-UP Cardano's Community Hubs | L61: 44652 | M61: n/a | N61: n/a | O61: https://drive.google.com/file/d/17zURLoGgoh-kLiehPtFrL2LOhKXQSd7Q/view?usp=sharing | P61: https://youtu.be/BwWJLGnrCJQ | Q61: https://youtu.be/yOU_dNYZF_8
B62: 55 | C62: 700138 | D62: Idea Fest by Catalyst Swarm | E62: COMPLETED | F62: 22700 | G62: 22700 | H62: =F62-G62 -> 0 | I62: Felix Weber | J62: Fund7 | K62: Community Events | L62: 44652 | M62: n/a | N62: n/a | O62: https://drive.google.com/file/d/1O0UqAM3yGI8w-ogGsZNyadABgONeORZd/view?usp=sharing | P62: https://youtu.be/WfnRcfOGWFg | Q62: https://drive.google.com/file/d/1XLKXGgCUKOx7OIFeoDGaA69fh_trNU86/view?usp=sharing
B63: 56 | C63: 700053 | D63: Cardano Worldwide Community Hubs | E63: COMPLETED | F63: 9636 | G63: 9636 | H63: =F63-G63 -> 0 | I63: Carl Henry Global | J63: Fund7 | K63: Scale-UP Cardano's Community Hubs | L63: 44652 | M63: n/a | N63: n/a | O63: https://drive.google.com/file/d/1jJ1_KKVG-_8jSHa4i_V2dvpPMs1qdxrb/view?usp=sharing | P63: https://youtu.be/oCmn-1jm3ZA | Q63: https://youtu.be/qc8O-h0s-bI
B64: 57 | C64: 700015 | D64: ADA Payments for Joomla 3 & 4 | E64: COMPLETED | F64: 0 | G64: 0 | H64: =F64-G64 -> 0 | I64: Carl Henry Global | J64: Fund7 | K64: Catalyst Natives COTI: Pay with ADA Plug-in | L64: 44652 | M64: n/a | N64: n/a | O64: https://drive.google.com/file/d/1P_KiNmPCon8gT3j8qiSJuuszyD7t-hgi/view?usp=sharing | P64: https://youtu.be/RTiosNdnVq0 | Q64: https://youtu.be/qhuq3jf_r9s
B65: 58 | C65: 600044 | D65: Community-Made Interactive Guides | E65: COMPLETED | F65: 11500 | G65: 11500 | H65: =F65-G65 -> 0 | I65: Matthew Halloran | J65: Fund6 | K65: DLT Entrepreneurship Toolbox | L65: 44652 | M65: n/a | N65: n/a | O65: https://drive.google.com/file/d/1CIi5cp5G8PQ-_Qwz9FncWsnMdm1D5zbM/view?usp=sharing | P65: https://youtu.be/OoRcAnrxuHk | Q65: https://youtu.be/FYXTTFdQgwU
B66: 59 | C66: 500015 | D66: Cardano Wallet Flutter SDK | E66: COMPLETED | F66: 10000 | G66: 10000 | H66: =F66-G66 -> 0 | I66: Richard Easterling | J66: Fund5 | K66: Developer Ecosystem | L66: 44652 | M66: n/a | N66: n/a | O66: https://drive.google.com/file/d/1GsZ--0lea9a0IDW30us-CmmukSn3fgr1/view?usp=sharing | P66: https://youtu.be/gZWCXOR2Va0 | Q66: https://www.youtube.com/watch?v=vGR30KmhTdc
B67: 60 | C67: 600020 | D67: CARDANO DLT-360 RISK RADAR | E67: COMPLETED | F67: 30000 | G67: 30000 | H67: =F67-G67 -> 0 | I67: Heinz Gassner | J67: Fund6 | K67: Cardano Emerging Threat Alarm | L67: 44652 | M67: n/a | N67: n/a | O67: https://drive.google.com/file/d/1N8nJ6FQMcvaZyrxs_RXgiN2ypONpoI08/view?usp=sharing | P67: https://youtu.be/59i3tl4eUdw | Q67: https://drive.google.com/file/d/1XGg2xhIDW9KPdNWHGJDebXv6u9lns2Gq/view?usp=drivesdk
... B87: 80 | C87: 700131 | D87: Geneva Business Development Hub | E87: COMPLETED | F87: 5850 | G87: 5850 | H87: =F87-G87 -> 0 | I87: Yoram | J87: Fund7 | K87: Scale-UP Cardano's Community Hubs | L87: 44682 | M87: n/a | N87: n/a | O87: https://drive.google.com/file/d/1qDMjlYW-iZXu32z8gXX_oKB_SfOYlM85/view?usp=sharing | P87: https://youtu.be/CHuEOsIUvjc | Q87: https://www.youtube.com/watch?v=ZEN5CSVCMR8
B88: 81 | C88: 700084 | D88: DAOJob: The HR Tooling for DAOs | E88: COMPLETED | F88: 24500 | G88: 24500 | H88: =F88-G88 -> 0 | I88: Gabriel Axel | J88: Fund7 | K88: DAOs ❤ Cardano | L88: 44682 | M88: n/a | N88: n/a | O88: https://drive.google.com/file/d/1CjTty4H3KrFj6s7JQXQiaAs4WKqaTMol/view?usp=sharing | Q88: https://drive.google.com/file/d/1dkP-r-FO3TrjVjj3JajZoiQab1OHmuCm/view
B89: 82 | C89: 700225 | D89: Revenue Share Token Smart Contract | E89: COMPLETED | F89: 10000 | G89: 10000 | H89: =F89-G89 -> 0 | I89: Matthias Sieber | J89: Fund7 | K89: Mini/Low-Budget Dapps & Integrations | L89: 44682 | M89: n/a | N89: n/a | O89: https://drive.google.com/file/d/1KHSGDkGQH93U0eFAoKcl4pd_OWCoPeUQ/view?usp=sharing | P89: https://youtu.be/_tHHLUOeEwM | Q89: https://youtu.be/uxYR2SriOCk
B90: 83 | C90: 700107 | D90: Easy Node Deployment - [Revelar] | E90: COMPLETED | F90: 5000 | G90: 5000 | H90: =F90-G90 -> 0 | I90: Jason Toevs | J90: Fund7 | K90: Global Sustainable Indep. SPO's | L90: 44682 | M90: n/a | N90: n/a | O90: https://drive.google.com/file/d/1AWp0J5SN_tAIZE8fH-zsGiIzGkOxQWXA/view?usp=sharing | Q90: https://share.descript.com/view/e6Z2ijDy9t2
B91: 84 | C91: 600131 | D91: Smart Contract Audit Token SCAT DAO | E91: COMPLETED | F91: 15000 | G91: 15000 | H91: =F91-G91 -> 0 | I91: Eric Helms | J91: Fund6 | K91: Improve and Grow Auditability | L91: 44682 | M91: n/a | N91: n/a | O91: https://drive.google.com/file/d/1ZLbsfNeBi_rnrYrIBxkt3v7ilj3n881v/view?usp=sharing | P91: https://youtu.be/cXo5T2qxQM8 | Q91: https://youtu.be/EfS-eBq6zyg
B92: 85 | C92: 700211 | D92: Platform for Cardano Solar Farms | E92: COMPLETED | F92: 14400 | G92: 14400 | H92: =F92-G92 -> 0 | I92: Jose Iadicicco | J92: Fund7 | K92: Grow Latin America, Grow Cardano | L92: 44682 | M92: n/a | N92: n/a | O92: https://docs.google.com/document/d/1IhxydkjAr9p9magQfJIwuQXMQzSDBChm/edit?usp=sharing&ouid=117059928304090739258&rtpof=true&sd=true | P92: https://youtu.be/iP1YM7pji04 | Q92: https://youtu.be/bkimSaCN8Nk
B93: 86 | C93: 700147 | D93: Interoperability within Atala Prism | E93: COMPLETED | F93: 5500 | G93: 5500 | H93: =F93-G93 -> 0 | I93: rodolfo.miranda | J93: Fund7 | K93: Accelerate Decentralized Identity | L93: 44682 | M93: n/a | N93: n/a | O93: https://drive.google.com/file/d/1VkzKcyaKivrNuAZ7l7QY6VqKio50EM5s/view?usp=sharing | P93: https://youtu.be/uKX2eXqUUfg | Q93: https://youtu.be/M5oz4pAw94E
B94: 87 | C94: 700007 | D94: A Community Vesting Dapp | E94: COMPLETED | F94: 10000 | G94: 10000 | H94: =F94-G94 -> 0 | I94: quinn | J94: Fund7 | K94: Mini/Low-Budget Dapps & Integrations | L94: 44713 | M94: n/a | N94: n/a | O94: https://drive.google.com/file/d/1DggWfq9No8loAEEaJz9YMb2kAHrPg00S/view?usp=sharing | P94: https://youtu.be/Q5J8mJA4J5U | Q94: https://www.youtube.com/watch?v=ULoiQab4OD0
B95: 88 | C95: 700101 | D95: Dumpling Twitter Space | E95: COMPLETED | F95: 9941 | G95: 9941 | H95: =F95-G95 -> 0 | I95: Bullish Dumpling | J95: Fund7 | K95: Community Events | L95: 44713 | M95: n/a | N95: n/a | O95: https://drive.google.com/file/d/1jRgIzEaJS5eHR1Fkc9QogiKCpWAKcvEZ/view?usp=sharing | P95: https://youtu.be/r44PhwAFRUY | Q95: https://drive.google.com/file/d/1JBcoj6myZMPfQhkWO9snKdriyfYIo_32/view?usp=sharing
B96: 89 | C96: 800291 | D96: PLUTUS FOR DEVS IN SPANISH | E96: COMPLETED | F96: 2200 | G96: 2200 | H96: =F96-G96 -> 0 | I96: Sebastian Pabon | J96: Fund8 | K96: Developer Ecosystem | L96: 44713 | M96: n/a | N96: n/a | O96: https://drive.google.com/file/d/1Y4heFLDBjwuctQp5jxkS3IRdNSTJlMy9/view?usp=sharing | P96: https://youtu.be/FbLWHKEtUCc | Q96: https://vimeo.com/718519720
B97: 90 | C97: 600122 | D97: Proposals Mentors Marketplace | E97: COMPLETED | F97: 39000 | G97: 39000 | H97: =F97-G97 -> 0 | I97: Alex Pestchanker | J97: Fund6 | K97: Proposer outreach | L97: 44682 | M97: n/a | N97: n/a | O97: https://drive.google.com/file/d/1c_SfxJO4M-OVCVrpjqZ7FUb6s4_PEepn/view?usp=sharing | P97: https://youtu.be/XKpfu82oZjc | Q97: https://youtu.be/Rx_htF3tIiw
B98: 91 | C98: 600087 | D98: Koios - Elastic Cardano Query Layer | E98: COMPLETED | F98: 30000 | G98: 30000 | H98: =F98-G98 -> 0 | I98: Damjan Ostrelic | J98: Fund6 | K98: Developer ecosystem | L98: 44621 | M98: n/a | N98: n/a | O98: https://drive.google.com/file/d/1RwjYDOq4pjSP6bqiWQMfbXzcVz05fZ1S/view?usp=sharing | P98: https://youtu.be/-wfzPyRnOKU | Q98: https://www.youtube.com/watch?v=lOoPNYiVxkg
B99: 92 | C99: 700190 | D99: Odoo plugin | E99: COMPLETED | F99: 0 | G99: 0 | H99: =F99-G99 -> 0 | I99: rodolfo.miranda | J99: Fund7 | K99: Catalyst Natives COTI: Pay with ADA Plug-in | L99: 44713 | M99: n/a | N99: n/a | O99: https://drive.google.com/file/d/1DBHjsoGm2wp9gjKWupL2j_T29-zyrcgz/view?usp=sharing | P99: https://youtu.be/NOcFmhgxr3E | Q99: https://youtu.be/5u_rsQZQKB0
B100: 93 | C100: 700257 | D100: Transaction Editor & wallet | E100: COMPLETED | F100: 16400 | G100: 16400 | H100: =F100-G100 -> 0 | I100: Oscar | J100: Fund7 | K100: Open Source Developer Ecosystem | L100: 44713 | M100: n/a | N100: n/a | O100: https://drive.google.com/file/d/1pcCL93-XYvDjS3EIUW7W57XecjBm880f/view?usp=sharing | P100: https://youtu.be/6nkb4d9C0EA | Q100: https://www.youtube.com/watch?v=fTDCxC8No6o
B101: 94 | C101: 600142 | D101: Universal Skills Authentication | E101: COMPLETED | F101: 48000 | G101: 48000 | H101: =F101-G101 -> 0 | I101: Maury Shenk | J101: Fund6 | K101: Atala PRISM DID Mass-Scale Adoption | L101: 44713 | M101: n/a | N101: n/a | O101: https://drive.google.com/file/d/14hMw2JHGQf6M0Gd1dnct0onzpwZMdCgD/view?usp=sharing | P101: https://youtu.be/WTNnx6-wxJg | Q101: https://youtu.be/b0LDP0Xkaec
B102: 95 | C102: 700259 | D102: Translation for Proposal API DATA | E102: COMPLETED | F102: 3475 | G102: 3475 | H102: =F102-G102 -> 0 | I102: Darlington Wleh | J102: Fund7 | K102: Improve and Grow Auditability | L102: 44652 | M102: n/a | N102: n/a | O102: https://drive.google.com/file/d/1pjeQRi8LdCU8jFXEmm7S2fJO5mhxl0eQ/view?usp=sharing | P102: https://youtu.be/JqFBVdwmcKI | Q102: https://www.youtube.com/watch?v=ssR8PAv2so0
... B124: 117 | C124: 700158 | D124: LATAM Town Hall by Catalyst Swarm | E124: COMPLETED | F124: 19488 | G124: 19488 | H124: =F124-G124 -> 0 | I124: Felix Weber | J124: Fund7 | K124: Grow Latin America, Grow Cardano | L124: 44713 | M124: n/a | N124: n/a | O124: https://drive.google.com/file/d/1Z4l1ZnA0NCq77E91gmqjt-B8fxajicLs/view?usp=sharing | P124: https://youtu.be/2wk9kFKjUII | Q124: https://youtu.be/VPiIR3Zeibw
B125: 118 | C125: 600060 | D125: Direct Donation for Education | E125: COMPLETED | F125: 9280 | G125: 9280 | H125: =F125-G125 -> 0 | I125: Simon Sällström | J125: Fund6 | K125: DeFi and Microlending for Africa | L125: 44682 | M125: n/a | N125: n/a | O125: https://drive.google.com/file/d/1PkUFyWg_ciQgyzdnKjKSeevSTvghzc8C/view?usp=sharing | Q125: https://www.loom.com/share/b0f41dbb3c7943fd989dd8988c08b6ed
B126: 119 | C126: 700081 | D126: Crypto regulations in India | E126: COMPLETED | F126: 9000 | G126: 9000 | H126: =F126-G126 -> 0 | I126: Reshm | J126: Fund7 | K126: Lobbying for favorable legislation | L126: 44713 | M126: n/a | N126: n/a | O126: https://drive.google.com/file/d/1L7-9RFG4L3ZZcfDwlDiSmwldKefiC5bG/view?usp=sharing | P126: https://youtu.be/Skp1kAoWBTQ | Q126: https://drive.google.com/file/d/1D6m1OJ9-u6hHt0m-XeBYySPi5IMD474w/view?usp=sharing
B127: 120 | C127: 600018 | D127: Bring Smart Contracts to Vietnam | E127: COMPLETED | F127: 29000 | G127: 29000 | H127: =F127-G127 -> 0 | I127: tienna | J127: Fund6 | K127: Multilingual resources | L127: 44682 | M127: n/a | N127: n/a | O127: https://youtu.be/pfxZPxSGeSs | P127: https://youtu.be/1Qk1Idz7E4g | Q127: https://youtu.be/pfxZPxSGeSs
B128: 121 | C128: 400006 | D128: Cardano Adoption in D.R. of Congo | E128: COMPLETED | F128: 3000 | G128: 3000 | H128: =F128-G128 -> 0 | I128: Frédéric Samvura | J128: Fund4 | K128: Local Community Centers | L128: 44593 | M128: n/a | N128: n/a | O128: https://drive.google.com/file/d/11ndeEDyWeKNbKmHlhQ3XAT4qy9q7c8SA/view?usp=sharing | P128: https://youtu.be/CvyF_bVRHHc | Q128: https://drive.google.com/file/d/1aW8JmU7jRv05yR-4Zmp9x2lqs8_mva1x/view?usp=sharing
B129: 122 | C129: 600143 | D129: University/College Outreach | E129: COMPLETED | F129: 4900 | G129: 4900 | H129: =F129-G129 -> 0 | I129: Jeffrey Granger | J129: Fund6 | K129: Proposer outreach | L129: 44713 | M129: n/a | N129: n/a | O129: https://drive.google.com/file/d/1wQQMkvcEaABl-PLuoI8QXACey44vo3fO/view?usp=sharing | P129: https://youtu.be/hV_78s_vqnk | Q129: https://drive.google.com/file/d/1uA0ngEy64yihAKNOgxD_JA3e98Jx33PF/view?usp=sharing
B130: 123 | C130: 600058 | D130: DID Solutions for Local Governments | E130: COMPLETED | F130: 10000 | G130: 10000 | H130: =F130-G130 -> 0 | I130: Kuniaki Abe | J130: Fund6 | K130: Atala PRISM DID Mass-Scale Adoption | L130: 44743 | M130: n/a | N130: n/a | O130: https://drive.google.com/file/d/1IhCmd9MAbGH-Ftr1Uw47j3aYwOBH-IEZ/view?usp=sharing | Q130: https://youtu.be/Bktrcr7ZaiU
B131: 124 | C131: 500036 | D131: iGIVit - The Future of Giving | E131: COMPLETED | F131: 20416 | G131: 20416 | H131: =F131-G131 -> 0 | I131: David Poulin | J131: Fund5 | K131: Daaps & Integrations | L131: 44470 | M131: n/a | N131: n/a | O131: https://drive.google.com/file/d/1RXgTv50L7seqC_0-ke-AAF1OQV8zWDfR/view?usp=sharing | P131: https://youtu.be/FYiiUqKAtko | Q131: https://drive.google.com/file/d/1k5GZEFf5TGh-XuUDU0X2PdArwqCzQHIm/view?usp=sharing
B132: 125 | C132: 500022 | D132: Charles Hoskinson in Russian | E132: COMPLETED | F132: 6500 | G132: 6500 | H132: =F132-G132 -> 0 | I132: Evgeniy Sereda | J132: Fund5 | K132: Catalyst Value Onboarding | L132: 44621 | M132: n/a | N132: n/a | O132: https://drive.google.com/file/d/1FJF_lpzsxQgbClOdsfMOMWcOer-DcrFi/view?usp=sharing | P132: https://youtu.be/E9DQRjBgoIk | Q132: https://drive.google.com/file/d/1e4NZVE7qN-nn9bLCvq41uD1INqWBobt8/view?usp=sharing
B133: 126 | C133: 600133 | D133: Stake Pool Reachability Dashboard | E133: COMPLETED | F133: 1000 | G133: 1000 | H133: =F133-G133 -> 0 | I133: Bryan Lesiuk | J133: Fund6 | K133: Disaster: When all is at stake | L133: 44713 | M133: n/a | N133: n/a | O133: https://drive.google.com/file/d/1NbB5Lilnn1vn6biY4wlgnQKyYUUviy1D/view?usp=sharing | P133: https://youtu.be/ncGHh1VQ8fA | Q133: https://drive.google.com/file/d/1a42IJL8QIGZ5i_83uBX35h5BW_Y6x86g
B134: 127 | C134: 700218 | D134: Proposals Mentors Marketplace -Cont | E134: COMPLETED | F134: 35000 | G134: 35000 | H134: =F134-G134 -> 0 | I134: Alex Pestchanker | J134: Fund7 | K134: Catalyst Accelerator & Mentors | L134: 44713 | M134: n/a | N134: n/a | O134: https://drive.google.com/file/d/1Fox5zNWD2raVJs2GFFgfcFEB-V9kapOO/view?usp=sharing | P134: https://youtu.be/Q1qdm4fSUWg | Q134: https://youtu.be/U-JRTSl0Pd0
B135: 128 | C135: 300001 | D135: ABCD | E135: COMPLETED | F135: 13800 | G135: 13800 | H135: =F135-G135 -> 0 | I135: Joshua Akpan | J135: Fund3 | K135: Developer ecosystem | L135: 44621 | M135: n/a | N135: n/a | O135: https://drive.google.com/file/d/1NddTL7Z1tgmHQVhIzp1gyF3KKBztRFso/view?usp=sharing | P135: https://youtu.be/lyACnIRYwv8 | Q135: https://drive.google.com/drive/folders/1KlzbNWoN8d8y_ePMAZ5LM_zAPgmmvwf5?usp=sharing
B136: 129 | C136: 800223 | D136: KILT & Cardano | E136: COMPLETED | F136: 5000 | G136: 5000 | H136: =F136-G136 -> 0 | I136: Tomi Astikainen | J136: Fund8 | K136: Cross-Chain Collaboration | L136: 44713 | M136: n/a | N136: n/a | O136: https://drive.google.com/file/d/1j6sY2gJFsIgpWJ1PDDP9Lphq2Y-2CxVi/view?usp=sharing | P136: https://youtu.be/ePmsJOTc6c8 | Q136: https://drive.google.com/file/d/1OzWdoGAc9TrZX_Jwr7Q7PKBKtOBI49TE/view
B137: 130 | C137: 600037 | D137: Catalyst-Swarm-Genesis GitBook | E137: COMPLETED | F137: 3480 | G137: 3480 | H137: =F137-G137 -> 0 | I137: Stephen Whitenstall | J137: Fund6 | K137: Catalyst value onboarding | L137: 44562 | M137: n/a | N137: n/a | O137: https://docs.google.com/document/d/1eCaKQnkpca1SamCUugWTxkmTqMsqhvKT/edit?usp=sharing&ouid=117059928304090739258&rtpof=true&sd=true | P137: https://youtu.be/LiesUqwLMU4 | Q137: https://youtu.be/UbAgX1wLXa8
B138: 131 | C138: 800099 | D138: Catalyst Africa Town Hall (CATH) | E138: COMPLETED | F138: 9800 | G138: 9800 | H138: =F138-G138 -> 0 | I138: Felix Weber | J138: Fund8 | K138: Grow Africa, Grow Cardano | L138: 44682 | M138: n/a | N138: n/a | O138: https://drive.google.com/file/d/1IMBHBU7X8QLBsDHqG8lZT4nFehZAkY-5/view?usp=sharing | P138: https://youtu.be/NIBYbGOtT4E | Q138: https://drive.google.com/file/d/1_fcH2oqlQMmE9BrRYlF3_vwG7HzWtA2o/view
B139: 132 | C139: 500008 | D139: Blockchain Authentication Mechanism | E139: COMPLETED | F139: 6000 | G139: 6000 | H139: =F139-G139 -> 0 | I139: Giovanni Gargiulo | J139: Fund5 | K139: Metadata Challenge | L139: 44743 | M139: n/a | N139: n/a | O139: https://drive.google.com/file/d/1NuMlMd0p09bvz6y2RGn7nGCTw4KnRRWh/view?usp=sharing | P139: https://youtu.be/pLhN1EATCxU | Q139: https://youtu.be/oaiLx3KznAM
B140: 133 | C140: 600069 | D140: Exhibit Largest BlockChainEXPO(JP) | E140: COMPLETED | F140: 7250 | G140: 7250 | H140: =F140-G140 -> 0 | I140: shusuke wakuda | J140: Fund6 | K140: Scale-UP Cardano's Community Hubs | L140: 44501 | M140: n/a | N140: n/a | O140: https://docs.google.com/document/d/1hleT1zIlP9BDS8xd_ZgGQ8fSD7w5S0ny/edit?usp=sharing&ouid=117059928304090739258&rtpof=true&sd=true | P140: https://youtu.be/zZNGeoYda3Y | Q140: https://youtu.be/MFxkdSHJeJM
B141: 134 | C141: 700216 | D141: Project Evaluation Website | E141: COMPLETED | F141: 16875 | G141: 16875 | H141: =F141-G141 -> 0 | I141: VCoinCheck | J141: Fund7 | K141: Miscellaneous Challenge | L141: 44713 | M141: n/a | N141: n/a | O141: https://drive.google.com/file/d/1lFil8Yu-0mMtSNNjkA95IIc3u9flBPwf/view?usp=sharing | P141: https://youtu.be/3VP0xvjy-q4 | Q141: https://www.youtube.com/watch?v=qf1JySIQ1Ko
B142: 135 | C142: 700151 | D142: Japanese Ambassadors & Catalyst | E142: COMPLETED | F142: 6500 | G142: 6500 | H142: =F142-G142 -> 0 | I142: Felix Weber | J142: Fund7 | K142: Connecting Japan/日本 Community | L142: 44713 | M142: n/a | N142: n/a | O142: https://drive.google.com/file/d/15vDElKz4jhu02t_qJrC6n-R41o0Aip0j/view?usp=sharing | P142: https://youtu.be/E2T-_vND8GA | Q142: https://youtu.be/qSawI0by-Zw
... B147: 140 | C147: 700123 | D147: Fund7Proposals + SDGs - Cardano AIM | E147: COMPLETED | F147: 5500 | G147: 5500 | H147: =F147-G147 -> 0 | I147: Raz | J147: Fund7 | K147: Open Source Developer Ecosystem | L147: 44652 | M147: n/a | N147: n/a | O147: https://drive.google.com/file/d/1nqJuK3JR562_hjHC_obiLU6exy6qV4rq/view?usp=sharing | P147: https://youtu.be/HJqcvAMTAeU | Q147: https:/www.youtube.com/watch?v=-srwJ9SimK8
B148: 141 | C148: 700017 | D148: After Town Hall by Catalyst Swarm | E148: COMPLETED | F148: 25000 | G148: 25000 | H148: =F148-G148 -> 0 | I148: Felix Weber | J148: Fund7 | K148: Community Events | L148: 44682 | M148: n/a | N148: n/a | O148: https://drive.google.com/file/d/1Jowy6hQFz-RigjEKrIznOCuQXF-DYW2W/view?usp=sharing | Q148: requested
B149: 142 | C149: 700065 | D149: Catalyst Swarm Operations | E149: COMPLETED | F149: 8000 | G149: 8000 | H149: =F149-G149 -> 0 | I149: Felix Weber | J149: Fund7 | K149: Miscellaneous Challenge | L149: 44682 | M149: n/a | N149: n/a | O149: https://drive.google.com/file/d/1lTabPpLIPcQG_s_lP82QNZrmwCvbG-ms/view?usp=sharing | Q149: requested
B150: 143 | C150: 400045 | D150: The Great Filter | E150: COMPLETED | F150: 30669 | G150: 30669 | H150: =F150-G150 -> 0 | I150: Lead Time Null | J150: Fund4 | K150: Distributed Decision Making | L150: 44593 | M150: n/a | N150: n/a | O150: https://drive.google.com/file/d/1PkU4ZQNR98060yOt0tCudOa3tNLVx-kp/view?usp=sharing | P150: https://youtu.be/UnyCVvhRfVQ | Q150: https://youtu.be/nAj5CpL9y-o
B151: 144 | C151: 500004 | D151: ALDEA Wiki - Cardano Encyclopedia | E151: COMPLETED | F151: 5960 | G151: 5960 | H151: =F151-G151 -> 0 | I151: Matias Falcone | J151: Fund5 | K151: Proposer Outreach | L151: 44713 | M151: n/a | N151: n/a | O151: https://drive.google.com/file/d/1YkE8oMlglzTcHvixoqq4aipFDESE8Rpy/view?usp=sharing | P151: https://youtu.be/6eoLabT_yIs | Q151: https://www.youtube.com/watch?v=qAf6-rfknMo
B152: 145 | C152: 700152 | D152: Japanese FUD / SCAM Buster 100 | E152: COMPLETED | F152: 1500 | G152: 1500 | H152: =F152-G152 -> 0 | I152: yutazzz | J152: Fund7 | K152: Disarm cyber disinformation attacks | L152: 44743 | M152: n/a | N152: n/a | O152: https://drive.google.com/file/d/1LIka5WC94VR5ua4K3KhIBDTWW_UKCUkK/view?usp=sharing | P152: https://youtu.be/SavVUTeXaw8 | Q152: https://youtu.be/8a-14aj0xC4
B153: 146 | C153: 700148 | D153: Introducing 100 Cardano Defi in JP | E153: COMPLETED | F153: 1500 | G153: 1500 | H153: =F153-G153 -> 0 | I153: yutazzz | J153: Fund7 | K153: : Scale-UP Cardano's Community Hubs | L153: 44743 | M153: n/a | N153: n/a | O153: https://drive.google.com/file/d/1Muf9zka5tuNmOcScEkFSiMOF-8Ao-qfc/view?usp=sharing | P153: https://youtu.be/xFurX4rE9VU | Q153: https://youtu.be/tJbpgt27E_o
B154: 147 | C154: 800352 | D154: Universal Resolver for did:prism | E154: COMPLETED | F154: 6425 | G154: 6425 | H154: =F154-G154 -> 0 | I154: rodolfo.miranda | J154: Fund8 | K154: Accelerate Decentralized Identity | L154: 44713 | M154: n/a | N154: n/a | O154: https://drive.google.com/file/d/1tuGBkU3eWGyWqOr4N-CYxGQjfqEu3F8Y/view?usp=sharing | P154: https://youtu.be/AGiqZHHvh8k | Q154: https://youtu.be/8TxgPK7pXj0
...

Sheet Monthly TXs
B1: Distribution # | C1: Actual date | D1: Telegram Announcement | E1: Fund4 (tx id) | F1: Fund5 (tx id) | G1: Fund6 (tx id) | H1: Fund7 (tx id) | I1: Fund8 (tx id) | J1: Fund9 (tx id) | K1: Fund10 (tx id) | L1: Fund11 (tx id) | M1: Fund12 (tx id) | N1: Fund13 (tx id) | O1: Fund14 (tx id)
A2: 2023 | B2: October #1 | C2: 45208 | D2: https://t.me/c/1522687916/340 | F2: 9198dedcaf2793604a94d9d512c324194a7278315341a2f3ee5432d9ef5ce2a5 | G2: c2e58a716887d0a558b3d9fc18911293d1685a5014d90f0fdddcbfb283f15f5a | H2: 234a75d2202bac3c2364d291c0509c03f1a0b2d3f0c2ea58a0caaa13afdce28f | I2: ea073131bdaa5cad85d5af0f23c447fc06db1a457eb17d914cfb961bbc4eeb61 | J2: 07e44d0e0dc15747c021b8ef0929f8efaa71275ef234b80aba9a7ac3f16be918
B3: October #2 | C3: 45215 | D3: https://t.me/c/1522687916/344 | K3: 374aa9c45ec5b379b66b170939e9d70070ec3f4c012bb1ed3bda7cf8edec5cd0
B4: October #3 | C4: 45222 | D4: https://t.me/c/1522687916/347 | K4: b3b3fbea76297dd7d6d6c5830afb5fcf3f51cb498c7a4a7884b9a72c9d0742a1
B5: October #4 | C5: 45229 | D5: https://t.me/c/1522687916/349 | H5: 2af879b5a06c8ace266fe79e0c5394058a24f8accadda2f5ca73ca1a84e2264b | I5: 212696c539b76d5c9872f6fb9706fc4f6bbd7b2236a3706dae4d3493a2c106f5 | J5: f5756244a79525c73421e5796779fdda79b00cd24eb25aea4f2413cf6d948ff3 | K5: 44e7dff4601cfe0388a660f486e25fe8d6cf65f2dbc0b3f73dc30ed1bfcfc443
B6: November #1 | C6: 45243 | D6: https://t.me/c/1522687916/356 | H6: 022b4faf3c4c7c1d0b3e5c2eec2954e7fc2eb160ab16c12c38397478da3e2850 | I6: 9119a85b164a0a6dde31b045a5f535c7ec9e72d1e7d4bad628d65027121d12f9 | J6: dc8820a2766ba60f2bf6a752cf8c8efc811fb5b2bcaf40cd99a8b99bcf4d60b6 | K6: 3fd7990db5f25dc63e7abf2d28e74f7bbd76d7930d6eeaae90fd8320b3c4b1e9
B7: November #2 | C7: 45257 | D7: https://t.me/c/1522687916/361 | H7: 0bbfb15e3ab47bcadc3b391094b14e1fd88870b4206a3f6a7c77dc1a41b98b08 | I7: d1fbeafdea6d73036b8d08ac4ce66c97b77bb31a6046cd0b85a28cc48a6bc3d9 | J7: 86730efcbe55568fc54cd68842afc91c8170e4738162097e6cc0808ef5ec4a2a | K7: 56b053a4e36bed56a15fc0ca3eb47c27253b7fe0558e355da15b5121693e0360
B8: December #1 | C8: 45271 | D8: https://t.me/c/1522687916/369 | H8: 33876bb46b2b2828e6bfa292fdf5b6ceebd44089f1c27e3a83fbbed7c8b0cd84 | I8: 43066fb014884d80d542e7b518d5441feb1c2aaa6db3628eb3f4dbd5967f854c | J8: 7932529d2af6e4d7c8699211b5f1d74f04556e73d26f7202eb1d7d0b1f7cedb8 | K8: 426ded707d991345c28170c882846d1a310b70fa220aa3cb78ecf1ade9717e9b
A9: 2024 | B9: January #1 | C9: 45306 | D9: https://t.me/c/1522687916/372 | E9: 6dd26ae1a945f870238acca678622c5554d59a0cb4ae5c159e0679bfcd6ede19 | H9: e51833b9d69e71a1964e3fb05fa9d9e811da892d1be36952608daed1a510be1a | I9: fe18dd7c36eceb66900c153b0536bd3b84389f3192c230c3a9e9c0367e90566b | J9: 13a43dd6b384aaf3352f9368ae0c53641569e6402af9ec05808511996c2e188c | K9: b603453bb85d24458562cfd5af49bee7bec650a26c8339f2c33a5bef19acc6f5
B10: January #2 | C10: 45321 | D10: https://t.me/c/1522687916/379 | H10: c96316cda6b12dede86e5493a4e76724bb70899b91fd769a57d7e7689f8686a9 | I10: 951c9127773d87161479e45dcba1d766a359d6f1008ee958cd6afcf7a1149488 | J10: 487492339725716661c5ba1db552a2ea2493759988253b2edc51624fb28e21df | K10: a11ba64cfcf1f36c36a4ade98651cc3ee3d706d21cd8c3adc50db8c3b5f4943b
B11: February #1 | C11: 45334 | D11: https://t.me/c/1522687916/391 | H11: 9d8378bf3ea12a0b4da57cb20c6323f5263b2d57fea4c02d77c5926fa1f57b46 | I11: 3fb1f992e5414e461b8cd8503700e2a9400c9d74b700577a253931e0b5fbe76d | J11: fdff1386e5a2b340e170b91d49ae77a63a47569e3ae017ba8b54ef37dda4c1ca | K11: 05a56689a4f97951a5a72ec3d7f900f8732e37395b8495a31ba47da5f1d3bc69
B12: February #2 | C12: 45349 | D12: https://t.me/c/1522687916/401 | I12: d2d3dd643796deb63c411c6ac46c62bc42850e4a15bc1ad79968e3220ef979cb | J12: b4a70d65bc28f5ed796f3b5d95aa380ab292dc499cb2a99e0127596c5cd29e14 | K12: 3ec653057c545f16e259ce6a3da4531a83fb5c3b4d06633d6740dee37e5ac4e4
B13: March #1 | C13: 45362 | D13: https://t.me/c/1522687916/413 | I13: c3f4f08770c5525c131d44cef26d0d1423b638aeb4a2b41419945161eae7e623 | K13: b6e1c9a5630feb934c16a06dd25ed1dab1ff3dfa45aac90877c10b45ce39bbe7
B14: March #2 | C14: 45366 | D14: https://t.me/c/1522687916/418 | L14: 1e1c32004b864c7cbb495e8ff884a04eda4a6106675a60b6760c2b198da8deb2 97fc940a82a5cd3453f3435d4d0835e69059f33fe0683907e66b72e326a41ba0
B15: March #3 | C15: 45379 | D15: https://t.me/c/1522687916/424 | H15: a16bc4ccc60875f2edd7a289fe8880ac533f203f5d43ad299c8651eeae4b8692 | I15: 6ce75cbf4a215d3bdc1ebd64ff270cacd64c14589719dba3cca072e8eebdddc5 | J15: 7410c6d41e25a010a9b171b635324eb7a89d228882e6d14f011b60aadf3fca71 | K15: 7c897c8d903fc58d3a24b69d15382f4a428d84eb63d649f0ac6016056761c749 | L15: fcc0d894622818d167429c3af4ffdeaab503a79f0a1861dfb7422005820fc856
B16: April #1 | C16: 45390 | D16: https://t.me/c/1522687916/426 | H16: 78b789cf70a5bb8a81a9745d0d1e5db777229d20bd0d462aca9c982acc2d6721 | I16: 051a29a01b0164ef608a3171d43826d6ee2e0fe3801070b4c3442c8364afd42d | J16: 42ed9db67ae909f72b1ad7b3cc16ae0dc68147e6b25211f0238d0f1e5f767e8d | K16: f39b56ead8a684679aa11f8cd1de1a62bd7b0e465b3cade02768aaf8ed552d6e | L16: 42a09d20ef9d938d7cf162e85e3e1a11ca2a1ea8aa2167c85c68d43d5aa47b91
B17: April #2 | C17: 45405 | D17: https://t.me/c/1522687916/437 | J17: 6c07ff12f909f1849847b2b2235a1bd4874d4f0e7bc05214afc5f81bf6885b3b | K17: d28ff3e1c561e2c1e3aa4270635e602d1aa1fcf3ef076399a2f5cd7bd3950341 | L17: 04aef83fac4042d16fb1b7a81bbde4d592220df7a042d94492d3730f30796e18
B18: May #1 | C18: 45428 | D18: https://t.me/c/1522687916/450 | H18: 15f4995c4ff3ab6dad99864b16b4369b54f062d043b32504837a88ec9c956bd4 | I18: adb1ad59ea19285edcfecb17f9bbd24c1538323326a6dcc3366902191c09ad3f | J18: 1af5bfd692efb233d86a250b41adb4b7de691e447ef26fafe9cfe5f036446b33 | K18: 2ea020481b5f263ae52c68c44566cc8783884f4b112a7771c9108a3aa136f5b8 | L18: c1d89a671b58fbba0740cb8aae907afd95fd6cfbd7e460c5ae1198236869b1ce
B19: May #2 | C19: N/A | D19: N/A
B20: June #1 | C20: 45454 | D20: https://t.me/c/1522687916/461 | H20: 330cbb7f86606e473374d497745b06a91a9a5b1d5a2fe3d1540aab579b0c1c3a | I20: 0babda03734309a3c473630b24fe5d44487f1c50d191130c122c766f29cd8731 | J20: 20be8edce6b70d77523a61062be0f144985a0141e88e2f1b280d4dd1ce26fa13 | K20: b482f165a2bc82a88618211312f43e6169017407124cb02b094f0092b395eb71 | L20: 8b5f9033c0b3bcd6c8deeabc4ce63d4a34df37f5220af2fb76aeda872d814913
B21: June #2 | C21: N/A | D21: N/A
B22: July #1 | C22: 45481 | D22: https://t.me/c/1522687916/468 | I22: d3a5623c5484815318fe8cef4708a0f81ebde2a1f02745e810d83f32eb72ae6a | J22: f5a4fb9c28d949273fd4ecf5cd0728254346d9445cb0cbacb3e67324d2ea8087 | K22: da974b0a50e60b57fc150dbbbe0d52e04141c8dda62ecc03ab9de3046d9937c4 | L22: b9952d05fac2836ec79bbc5df18db0e7fdfc578eec5644bac204885a695f3c89
B23: July #2 | C23: 45506 | D23: https://t.me/c/1522687916/474 | F23: 94248a1dca33cb8be7aaae6dbf6e0e734f798294c242d252079b2f61daedf6da | I23: ee6fbaa9e8f654e6768d3075b12a6fd7deeaa125eb49fc4278ac31fc06327938 | J23: 8101364984cabf655e8c9aaeb17d4ad3c0586feba7032859ebaca99fa502a70f | K23: c33d499ca68d73364fea50c0cffeb81a044e9ec8d65e6c71955bb422b5e1b67a | L23: bc9caf79e5d29a37671c061c645470acb33990d6b88727e7de162faf6856f9e0
B24: August #1 | C24: 45533 | D24: https://t.me/c/1522687916/482 | H24: 4cdee8c6a71c2c444aaf0aa1b87b8a589801817b2e3d70a82fc227e48fde8449 | J24: 453bd7afe0aee80f23eaae103a161d213f169052289403114e612b15ee9b80a3 | K24: 699d2005877e0f1b06ebcba7e9a1be4db8d1cb7409eda778b464dd86535980f6 | L24: 556d317bfe8738fa9a833ca9746abf4836e6c1e1a4bf7b883c57ea91908cda05
B25: August #2 | C25: N/A | D25: N/A
B26: September #1 | C26: 45547 | D26: https://t.me/c/1522687916/486 | K26: d62642e769d842b9e5c9b73281120d8b52018928515e4e16f2f24c6a0abd206f | L26: 1a0c19ba1ba87852b4e53ad9ac7d921fcf3f067bd893b8a54e31211c76dd4167 | M26: 29edc2cd98460685c0e309595d2c8f7090bf925aead573555abb12458f5c957d
B27: September #2 | C27: 45566 | D27: https://t.me/c/1522687916/494 | I27: 4937b08eabc2db8bd612ab12edb94eb5e2fa0f9b1bc3656517a5510467223532 | K27: 3f81f78309fd4caa5d2b23b358188d620448a3709ec97628f58035186471701b | L27: 8887b6018a612fa67ce62f75911538d814bb45ede9f92e570046e00c8cf85621 | M27: 2617b25592527fd1024a0ea15fb994c907ddc2de840efe830d932c9f5568f345
B28: October #1 | C28: 45581 | D28: https://t.me/c/1522687916/497 | J28: c52d6ef803929e06c94cd6d8e7ff7e1f7d4975cfb6a9084fe9cb80f9cb958199 | K28: 8a23780e6ec5d5404bbbd1b8b89bcb8eeb38042932d3574ba66a16269ee78ed6 | L28: d9b7a51e5e08a7bd7622f2bf685f70705f9b3516cdd1d896b2ce3a4d75a71721 | M28: d78915b139dae29bc025b86c0b6b615bdd2e99ad124d00cd360ab736c11a1c71
B29: October #2 | C29: 45596 | D29: https://t.me/c/1522687916/500 | K29: a2747639d73edbf3df226479676ab87672df6272df885c557b20ddfa06b680c0 | L29: 4be342044345e63f2c71304ff6a91975d6a8f1990cc49abab4839e0ab70d211d | M29: d9c658fe4d2be8710009dabbf1746535a640c0e8aa0e0c28464bc2284cd35c71
B30: November #1 | C30: 45615 | D30: https://t.me/c/1522687916/507 | H30: 786db177c39d87da733d4bea8d959c958ed1c66ff6824586bffe33fd3045b79c | I30: e07d1e2ef8c0fd09023bad8fd945399c157090ea6aff8fc8c2aaf72ba220093a | K30: 2f5a6cacc8d6ec1da974a49d7e40e6a3932b1c80fd03f167a67929f9954ac1b6 | L30: 18bcd23c45fd54e393aaa5f48b20979a61ad4abb39005843c6d50b8fb484fae3 | M30: 12d9e020db3cedc21aa936aa9d7642d736e91531110b33a639c927fd9c0dea0f
B31: November #2 | C31: 45628 | D31: https://t.me/c/1522687916/509 | K31: 4d77e3c52113be9a0b4bf2693820d22e556723f1d1c1c44f0015cf0dd4263542 | L31: 568063bded1f5722b84494c9865cf511907f2789fce451ff320eaff0159e839c | M31: 3dfbcb687defa153fd33fa21fee78e23e002ff2a43700ec4ac7f7ab326532fc5
B32: December #1 | C32: 45642 | D32: https://t.me/c/1522687916/514 | I32: bec6334451e50dbe85a6fe353d76120c320cb78436fbb23a98189e3c55949962 | J32: fe8020cc8e9ed3c23761548dd6a854c66ef1a93d6abd1e4c5a40e8c62ae78552 | K32: 6ce51a855da8feec8fc36b4b7c3472a7c7d9033352070c67772fc8ec3f44809e | L32: d4fe884fadd6865da11ec19b340ea44fcfe691b4fc7735e94307da82be13eab2 | M32: 734eb7388630cbaf8593827ca7f5d2ad309e701a26b0eb4d5524bc0908711877
A33: 2025 | B33: January #1 | C33: 45673 | D33: https://t.me/c/1522687916/520 | H33: d6fbfce98a189e855a078e57df7cf65af25dff72158608de3578af6070a10a9f | I33: be259e338d0c9d95b2e5df204c2e6696e37a32ff1078ba8d61ab3006b7faeeba | J33: 724bbed34482844a276882163f2f379bda67d42b1eee3b0e5b469e72d7cb277e | K33: 8370b0f959891b944c5c8fbba7689c468a8f05966316b2b445b524372a789169 | L33: 1050398f7ccc301e85979b09541010fcf513deb2dc7ef26dccea4167ce3eecc2 | M33: 23df1e6afe6ef7737c4f443c7a94f1c95fabb3fb0878e43a83f256b5d726d464
B34: January #2 | C34: 45687 | D34: https://t.me/c/1522687916/527 | J34: cc8331e4da46e75e91847249c860fdaf243f1bfb574f28ab651f14271271876e | K34: cd60a426e4428342591479d94447ecb1327244bff066e791e1467bd5b94f0787 | L34: dd9c0d029e37851e08f03fe24036784985415d233586f8c85275b94fe6411888 | M34: 7dc5e2b5dbfbd9e7b293bdc0e6881e15ee79c7989ec7c8f0f06074c72ae6f038 | N34: 85a3171d405634aa337c972554c4d557fc6f0ced59255605944252108a1de884
B35: February #1 | C35: 45701 | D35: https://t.me/c/1522687916/531 | J35: 42559dffa8d36341230375bb34083b3d4e96d39e1ec752c08f6909ef9d56fd5a | K35: 31101b4710161df50b6b6d69ce9dd0196f3e4b6cc5941163ae248a4c1ea10fd1 | L35: f748692055487689e4afe3fe2c96797357d7a6afca99c54af033780aac87117d | M35: a208179fae7056ba8e768ab2f20f8b79857951a5675a2077de7a8648132783bf | N35: 9994469fa6f3d5adddb46d2b2ab2ef77c77395a01f8b487005bbe2664427d5ea
B36: February #2 | C36: 45713 | D36: https://t.me/c/1522687916/533 | I36: 74e6de01a1dcb03b9e4da5787216c37b811d737957a3f0eae9dfdfbd5c3cbc95 | J36: 5a2a570748400d5094f9ac969848e805dcb02526eaffb6a6420bd37b1c0a02c7 | K36: 7d1780e84f6f2f01035bd96631fc3a34608c4f8d0c668aa51116038220761a83 | L36: 138ecc3d485cb4167000a557d1871dc85a58cf4cfe11b7ff96ef5e9db528d2ec | M36: 26ca288a0865454caf3f5af6c92c98ad627be27189380fa0005e27ed5079ba9f | N36: d94bb5660fc55dfe2e08eadf2ce69fc817ec3a8f825dc07fe02c6c3a128fd1a2
B37: March #1 | C37: 45729 | D37: https://t.me/c/1522687916/535 | I37: 2218df78edf664dc74dd2dfb61448d27d3b1cb92530990eafc3f2d7095994b20 | J37: 6383a4cb036f379aae567702d55a45866f658a45b56681e24aef6618de3e13cb | K37: 19654d16c2a1ed8975b729796c7d6fc9bb9cb4a6846a74196981946194c921c9 | L37: 9f9d44080c9d98611b2909eecf7c99e784dd8d24dc983fd1e18c1de108500f96 | M37: 052cd36b6fe2e4c050eb5b7c9c7d2ebcacb05380df3146ea8eafc8ed1c4a806f | N37: 1ac231fb7090528861eb0e7373a2581373c0a8b41fd1cdd217f3a6decb5ce3f2
B38: March #2 | C38: 45741 | D38: https://t.me/c/1522687916/541 | K38: f2e8c6c0da38b7ae26d5c3be5e4be733abfeea19c8e669a4491d4eea54e7f877 | L38: e0fc69a9397bbdbe989e8be3d40a84db1a07d4e659e4de5b11ded3b691d636c7 | M38: 443f75f83355a5adb69c1cb8dfe80350a9eeaf6999fb32d217ddf1ce8cf7d7d3 | N38: 4cf8862e942b50a18b0031ce8bba3c12f9b5dfbf00986f20db28b27363bfe5e3
B39: April #1 | C39: 45762 | D39: https://t.me/c/1522687916/547 | J39: c9dee487b0633358e02ab3e4dd1de07c8d93b7189191d99cfd2451435e8730b6 | K39: 8832fbc697338456c04635a916d7881cab71cf1b5a743b665ab9489f389d08a8 | L39: 252e81b010c1186beb45f1b40c7204cdfb12a7c1240493beaefc78d0fa2897a2 | M39: f475467c9b2f0eb4833dac51a3a5f43fdd7ae92c21cc19cda9b642e06a2372d1 | N39: da23226af171165a5b137bb055a4e4f51e95b08eeb2f38cba93f82a621cd0ec9
B40: April #2 | C40: 45776 | D40: https://t.me/c/1522687916/553 | I40: 19a6dd38ba68d20331e54f5927d35d2299c5395f3d11e6f1e9116389dab0d1cf | J40: dc0e180d53218316a86e5237dc3efe3226a3d0e97de8bf2ae07cadbfa6a23e09 | K40: 5d6c13043377e2c6cb967a52a1478f855f654e43cafecc0f7a3258b613edcda2 | L40: 14017cf2acfe895be67ec152fc49ec02778e89ec6962e8465a124e9dd8b835b8 | M40: 3fc5734cca297259dde45830990ba20b024a1042d051ff7ae236e90f51b40f32 | N40: 6c4821787c89e4073bda62ebbf486137de73ea5c6390895e939a065f5d82b1e3
B41: May #1 | C41: 45792 | D41: https://t.me/c/1522687916/555 | G41: efe251396fc44f1d4c9b4f1058a0c5453c4deff73426cada7e675e7136593527 | H41: b61a2e18cb979b64415e714b091ebe8abd194f1f6e792c62643b63d1a3d0af0f | I41: 712955fddfa53a9e66d09c1bf3496d24e6812033040dc6c3c1dcb4d90185696b | J41: ef18edfe2ec758e0cb49cd0277ce7d0d02337a46e4c37c5e83185a48040c01b4 | K41: b20322cc464efa027d7249eecbd4ee7aec3d061c68708926594dbad715e6c999 | L41: afbca999304c59abf5529b50b88653033237ed107eff72f4e62b6b6df6121b41 | M41: 6be33f6e25c3bc0fee94195d5c87459c1324b14ab9d0dba4f197fa9f3f9499d6 | N41: 2e5781bb56fbb3bd1b778c7bb81fa95bd507b41fb676dfad7c33e18ee431b80d
B42: May #2 | C42: 45804 | D42: https://t.me/c/1522687916/559 | I42: d8654d28d4323451f1a54f889bd74016a3feb2728ec9aa0802910ce3d7be6a61 | J42: 7527f0e12a6a981a21ed2f28c6c65607f6610e5ab20d9f6021b605f90f34cdde | K42: 23c8b1ef3af95ad01781c55160f54b6fb3cc2e689f3e9a8c4ba11b1e9fde67f8 | L42: 376883c0e2e8116cfcab06900c7d5772557f574b023b3a0b90f910cb12f41195 | M42: 9b156b9d53271e720099fe0960872ebd0b66bee339dd847e9d4c856736902a65 | N42: 11b89dc820872418193d2b88be69c983e442afa18a9bb6a5acfa11ae8e4811c0
B43: June #1 | C43: 45820 | D43: https://t.me/c/1522687916/562 | H43: 361e474e9f5634fc33a9e9beabdf663289cb8cb101697a84a80177de562a45fd | I43: eedfc0125165b8c53c0b141578fd4ae46ed496518f68c3bc3e8f49526a8a1bae | K43: 8e64ff78aea2c356abd3d6423dbad376a81a368ba790d2f4a2677ced9ef9bc64 | L43: 0d5a7c81334e8d8da952501971c750c0a08d9ba8695ca820eb5d5fa7893d8254 | M43: f4f1d56a7b8906c8491c66ee399e0ae4132ff1ec5f21fbeff31a7a73f32be4a0 | N43: e605007b5816c74ffa2af95af37608afeed719a8f16148d1c0ffeb0313731681
B44: June #2 | C44: 45833 | D44: https://t.me/c/1522687916/564 | K44: 9f552a4c84dcb13437cbeb580ea36be21f6290127acb32d01ddf149c11229333 | L44: 26548ddfa4257c656e7c0edc04089e9923e8b082f96d5f63039ea5c7bada0834 | M44: ddb1a44a789914404f4bedee2768a96b0c6d8126cc96d71f3e95a936fd6dc1b0 | N44: 092568daf259bcbe4dd8aad30a9be81be3947939f5dc140e220d8d32d303bb71
B45: July #1 | C45: 45855 | D45: https://t.me/c/1522687916/568 | H45: cf8d3f280bd9b3e857121211308173a42043207fa8d355a7fd0b401978654516 | I45: 14f731abb1100138a4b12c94eca58a10d8f20daafbe863d1abf09ff6e53cef35 | J45: b3c78826616f201bea501234eba88e8ffbb9ee75706a0c36877a3a1c23ec73a9 | K45: 248d3a3ff24cdda2c0ad13084e205bbdccf20f5525b33bb79aef7576e1122457 | L45: 8cdb0473df15f4306472feb93e8ec9496d1c6724c889171f8b0d41885bf4d05a | M45: bd91bfa3c6a531090546f698e57709e68288fe48bca5981b36496c0264deb7c9 | N45: 7f47b0172e78e75f89787556be6d2782f03d1bbd86ad5c9a201f89f445e007a5
B46: July #2 | C46: 45869 | D46: https://t.me/c/1522687916/571 | I46: 0ac73d8387e6bc4e8f49750c8f23f93af7c57b710f5a6d2aaf8da6d418f8e644 | K46: 705e1e62e988943e4041b2c2414891f24256d90444f9f5f33b9c59cfdbb9db15 | L46: f9a5c63ab7bcd8300513d9a8868f2b8490a8ec97c79deeb1403268e9101866c9 | M46: 9cd2b820047efdeb7dbc0f42f0382ea24df019bea9659ebe0c4d107122afdf22 | N46: 625995cd0d15ba8447cfa646412210902157dd7f85a27dad6f3004cc81f59bc8
B47: August #1 | C47: 45883 | D47: https://t.me/c/1522687916/574 | H47: ebdd425332983f2d1f5e4ecc9a9026d25ca349221250c1bac4ba45b15e473a71 | K47: 1e55713db33be6176bc84fe5dfb3c5508f768f7ff306dfa21f0c77f3502d789b | L47: f4d88ddadc103b518488d3d01ad2ec56940be799a032cbf09ae99e016f9beb7a | M47: 759f0b963425c9a78bc723549dc56089c5d08a4cbf1a4505c9241834e41a59e9 | N47: 305c043ca2680154a10bb01f34118d1d7c6c982bbaf0c570eefd7e2ca74a3013
B48: August #2 | C48: 45897 | D48: https://t.me/c/1522687916/579 | K48: 15d134a84047818847aadaee47e3a14823157433f4b27925cf8fcf244e6a2505 | L48: 1298bc5d543f53fc332cbdb563fa284de89bffea42ba7baefcad12769cb8662f | M48: 29b3c1e1a0f95d558296fd780f498b2c2c474f9a9dcf05a07bb70af405e490ca | N48: 8f2956e9c15f3b4f20cda20ca845ddaf894f50d4ecf094a0cbe15a015b4bd0b5
B49: September #1 | C49: 45911 | D49: https://t.me/c/1522687916/583 | H49: 4198e9ea4ee049ba407ff1fe28053a4be88c82fe3f52e0186a5100b3ccbbbf02 | K49: e6ecff4cab613a761d70ac169825a39895552724e620937b17d1c61fba8d3921 | L49: fc0ec6a499d099c6af38ce4e73d8477bd78ac4000875fe0dcfd93219c15f0d37 | M49: cc2c40acc28d04180dd38b6d51da475a5171ee791917469719f112bdea768444 | N49: 6528c318678c53ef46847383f64eb4bcc955712719d3f195d3e0f992665a9858
B50: September #2 | C50: 45925 | D50: https://t.me/c/1522687916/589 | H50: ea948af5198206095562a19f94fed3aa5c1775a6d154cc568f3e3eff53d3c032 | I50: c0f31a44935b18bec728e571cf524fcdfc9a0477d80e7c09e79a52d08b14a373 | K50: c460ea7ebeacba2f14c2bbeef9e91d0b1f1446396dc24eb8516887900a2e8512 | L50: 72b88d78b02141d8ea5922ffb21c3364c86b3a05580447a19902912da2cd4a1f | M50: 0368374b25259cbf0db136f5105bb4a846b0ba1949caf4210aac6764faa0edce | N50: 02aeaa29244fb36d949cab6617a1c30eccb649411ebad6ed57cc30bf06689b08
B51: October #1 | C51: 45946 | D51: https://t.me/c/1522687916/597 | H51: 38c205242c9c7e14d70bbb301ae72cfdc0c04f4c4335261b98dbf8b137f934ef | I51: 64aeda8f401bac95b5789d17293aa4b9079ab11a0a815bf5b7f10252e0749358 | K51: aa1561ce5f630e98baf14337bc8dc9ee469c871bea7c342ee70a6208cd5d9ea9 | L51: 05885f7039220a2d315327cb084c0cdce75fefad77a5155f4a4e5d7e90fcc6b3 | M51: 6861e1ac47cb37276dd72421c0f5d93297ab1b53565fa4afc738def28c367f4a | N51: c58da6546fef45ec2db7fdf99c12e3247a77e835081098e515968e5f9ebfefd3
B52: October #2 | C52: 45965 | D52: https://t.me/c/1522687916/602 | I52: d7c6af5d6c006db3b23a881943d8952bb2fdd8af0fd46d44adf8f4cac35e56ce | K52: a9e58d19b74bc6c3f2d4a8f6a840101af70c97e0bed5aa6c44932614a6929e5e | L52: 0fbb0dd6af6b25dc018d5eb5adc089793e2b64b86f153889b3650d7d18602133 | M52: ce27f3340d6795d1328858f9c99dae4571c1f245d31d1ac8c4412e38f870f4d3 | N52: e111246cfb6ee29f9831e7702da51bac2552dddd123f96caeaa8b816a3b86597
B53: November #1 | C53: 45974 | D53: https://t.me/c/1522687916/605 | J53: 3382ecea29eef125269ab9c1b7995f90e502d07758671d1302c0d72bd41847f4 | K53: c37b0fe3c7548a3d6bbf207aac1a0a7cef3e8a6d7060679067acbe227612c590 | L53: dfc6732130167a99dd6dff803366d6bcba2d0ec811198d71908e520b1714c32d | M53: 481fd62c1c96897f73f1bd55de812e9219d130b2737aac016deb83ecf4233b90 | N53: 102e6a0087e18f1677a10fc352e7e9343ef01d98c9eb781c249eaf4d4e77ada7
B54: November #2 | C54: 45986 | D54: https://t.me/c/1522687916/614 | K54: 8b3430636aea309a70a6e988aa3fff24b337fe032bb6c8a65eecf05c323f3d31 | L54: d2b0ca1ae4d6efc6306e8e5742f011c7acd0cead28d90b3a8b7a2c1e513d060b | M54: 2ed4a0ae8a99a0b9fbc29ac1cd72884c33ba5a4eb2370013d4e9609fccef1b01 | N54: b8d80713ca6627a729f67f1d06d2f48c33ed6ed8649f3639f60e1a1c21e48f9d | O54: 1f7de21057be6ecbfba1cf54ac26466941ba51676d9ab4eb2173483bc38e6110
B55: December #1 | C55: 46009 | D55: https://t.me/c/1522687916/618 | J55: 61c2b7bd268df027b7946b0994ac86eb46a49669d20fc7618565d434d4b07ccf | K55: 02ed56ae7e52d312d562dbeceb1b1ca56dfb00a0e554950df24b6ab8a315c98d | L55: 1e7c4dc3325994bf5230d6ff1990c77aad7de0d9a5a82175717e762722c8f690 | M55: 2eb3dee1448cc1f4bd4ff00e5785ee3f759025c392e8b2e77127ce1858720054 | N55: ef85f5f8703039df2651e64a5a0dbc63363187652d4c2206cc90d0726fcc0b1d | O55: d7f0dd84918f6406a59099eeddd084c4978f413b789b8fa1cfa2ca4df6db8abd
A56: 2026 | B56: January #1 | C56: 46037 | D56: https://t.me/c/1522687916/623 | K56: 0debbf47b2b08da882a7bc86468ec3fff7b86b31848381af758ec4b3679fc5b3 | L56: 9aed55150ae333159427ef4c9ec58e561bfbedc7ec3902faec05509edaeafd7d | M56: 5649b3e4a60b227969bff69996df511c520a9d21bb9022274a87b7df7ed764e4 | N56: cae2eebfdadbdbc74f96846c7c8837e3c7dd0c80fe83fc0135779cb73f3db1a3 | O56: 4c16951c9175a6f4fed97c06fb8cc1cf398c4c8a701a4143a8591e00c69366de
B57: January #2 | C57: 46051 | D57: https://t.me/c/1522687916/627 | K57: c0398826140f8d41bf756569321b1a46e0e59d1af184b278f6cc94657fd5c3b8 | L57: 856fe184d49f650fdd5be64f22370963dd2250f11c6e173731a87500a5a97fa6 | M57: 412be0c5e5dbe48d3a7efb485492f5e5f220727c2ae19c9cbdfbda3d738374aa | N57: b04a82e87b68c9eb24a2e407c0367fe4f6dcec27bcb6f1a42b36189a704ffc26 | O57: b8c96ca0418fa89bc67eef547d729e0c2ca259241454e0948c7489041ac3ea99
B58: February #1 | C58: 46065 | D58: https://t.me/c/1522687916/631 | K58: c9358546302ca4c7f661a0fde97b031e5fc3bc07aa90efbdfc93d36b2cc1c90c | L58: 699d14766dabb4092420347a625b998740915d0c1c6630c83bbcc0272d28d3a8 | M58: 1466d95042dda61fd89cdc364fd7f0be6eb7923889ef72bf1661914201c306b1 | N58: 673bca940fc4c4f3333894b268b0e3184e4f7c0d2c549e9e9b1f85b667c0a103 | O58: 1e1d8ccc92eeaffc324ae6b682045818d0e57effbf3e2c3f10c334111967c614
B59: February #2
B60: March #1
B61: March #2
B62: April #1
B63: April #2
B64: May #1
B65: May #2
B66: June #1
B67: June #2
B68: July #1
B69: July #2
B70: August #1
... B78: December #1

Sheet Fund14 Reporting
A1: THIS DOCUMENT WILL BE DEPRECATED SOON If you need support please submit a ticket via zendesk.
C4: FUND14 | E4: Funding (₳)
A5: # | B5: ID | C5: Project Name | D5: Project Status | E5: Requested | F5: Distributed to date | G5: Remaining | H5: Primary Proposer - Guarantor | I5: Challenge
E6: =SUM(E9:E139) -> 18591246 | F6: =SUM(F9:F139) -> 4230962.4 | G6: =SUM(G9:G139) -> 14360284
C8: =Counta(C9:C139) -> 131
A9: 1 | B9: 1400001 | C9: [Aladin]: Building a Freelancer Community for Cardano | D9: PENDING | E9: 56380 | F9: 11276 | G9: =E9-F9 -> 45104 | H9: Thanh Nguyen | I9: Cardano Open: Ecosystem
A10: 2 | B10: 1400002 | C10: [C2VN]: Hydra on Cardano – Complete Step-by-Step DApp Guide | D10: PENDING | E10: 30120 | F10: 12960 | G10: =E10-F10 -> 17160 | H10: Khanh Duy Nguyen | I10: Cardano Open: Ecosystem
A11: 3 | B11: 1400003 | C11: A Token-Incentivized Mental Health Ecosystem Using DID | D11: PENDING | E11: 100000 | F11: 16000 | G11: =E11-F11 -> 84000 | H11: Mineko Enomoto | I11: Cardano Use Cases: Concept
A12: 4 | B12: 1400004 | C12: Activating IPDC Blockchain through Real Broadcasting Waves | D12: PENDING | E12: 100000 | F12: 24000 | G12: =E12-F12 -> 76000 | H12: JUN HAMADA | I12: Cardano Use Cases: Concept
A13: 5 | B13: 1400005 | C13: AIRA : Hydra Loyalty & Crypto for Regional Revitalization | D13: PENDING | E13: 698000 | F13: 0 | G13: =E13-F13 -> 698000 | H13: Shigeki Tabira : AIRA Inc, CEO | I13: Cardano Use Cases: Partners & Products
A14: 6 | B14: 1400006 | C14: Amplify Cardano: Community-Led Events by Rare Network | D14: PENDING | E14: 50000 | F14: 12000 | G14: =E14-F14 -> 38000 | H14: Wes Parkinson | I14: Cardano Open: Ecosystem
A15: 7 | B15: 1400007 | C15: Amplify Cardano: Community-Led Marketing by Rare Network | D15: PENDING | E15: 50000 | F15: 12000 | G15: =E15-F15 -> 38000 | H15: Wes Parkinson | I15: Cardano Open: Ecosystem
A16: 8 | B16: 1400008 | C16: An all-in-one platform for the Korean Cardano community | D16: PENDING | E16: 30000 | F16: 16200 | G16: =E16-F16 -> 13800 | H16: KTOP SPO | I16: Cardano Open: Ecosystem
A17: 9 | B17: 1400009 | C17: Anastasia Labs - Smart Contract Design Patterns Conway+ | D17: PENDING | E17: 100000 | F17: 0 | G17: =E17-F17 -> 100000 | H17: Philip DiSarro | I17: Cardano Open: Developers
A18: 10 | B18: 1400010 | C18: Anti-Front-Running ZKPerps on Cardano w/MidnightZK | D18: PENDING | E18: 74000 | F18: 16000 | G18: =E18-F18 -> 58000 | H18: Sricharan Ganta | I18: Cardano Use Cases: Concept
A19: 11 | B19: 1400011 | C19: Anvil - Semi-Custodial Wallet: Enterprise ready Wallet SDK | D19: PENDING | E19: 60000 | F19: 27600 | G19: =E19-F19 -> 32400 | H19: Zachary Soesbee | I19: Cardano Use Cases: Concept
A20: 12 | B20: 1400012 | C20: Bifrost: Bitcoin-Cardano bridge secured by Cardano SPOs | D20: PENDING | E20: 739000 | F20: 0 | G20: =E20-F20 -> 739000 | H20: Matteo Coppola (FluidTokens) | I20: Cardano Use Cases: Partners & Products
... A139: 131 | B139: 1400131 | C139: ZK-Stables: USDC/USDT Non Custodial Bridge | D139: PENDING | E139: 85000 | F139: 59500 | G139: =E139-F139 -> 25500 | H139: Dextr Labs | I139: Cardano Open: Developers

Sheet Fund13 Reporting
A1: THIS DOCUMENT WILL BE DEPRECATED SOON If you need support please submit a ticket via zendesk.
C4: FUND13 | E4: Funding (₳)
A5: # | B5: ID | C5: Project Name | D5: Project Status | E5: Requested | F5: Distributed to date | G5: Remaining | H5: Primary Proposer - Guarantor | I5: Challenge
E6: =SUM(E9:E207) -> 46476623 | F6: =SUM(F9:F207) -> 31425560 | G6: =SUM(G9:G207) -> 15051063
C8: =Counta(C9:C207) -> 199
A9: 1 | B9: 1300001 | C9: “Cardano Unleashed: Hybrid Events to Inspire Innovation” | D9: PENDING | E9: 50000 | F9: 27000 | G9: =E9-F9 -> 23000 | I9: Cardano Open: Ecosystem
A10: 2 | B10: 1300002 | C10: "Together Learning Haskell/Plutus in native language" Club (Phase 2) | D10: COMPLETED | E10: 35500 | F10: 35500 | G10: =E10-F10 -> 0 | I10: Cardano Open: Ecosystem
A11: 3 | B11: 1300003 | C11: [BBO] Virtual Assistant GovernCardanoBot = AI + Telegram - A tool to help you better understand Cardano Governance | D11: COMPLETED | E11: 66250 | F11: 66250 | G11: =E11-F11 -> 0 | I11: Cardano Open: Developers
A12: 4 | B12: 1300004 | C12: [BUTC] Fueling Growth: Cardano Hackathons to Inspire Startup Success | D12: COMPLETED | E12: 68000 | F12: 68000 | G12: =E12-F12 -> 0 | I12: Cardano Open: Ecosystem
A13: 5 | B13: 1300005 | C13: [C2VN]: Promoting education through the development of Blockchain lecturer teams at universities in Vietnam (Phase 2: Advanced course on on-chain and off-chain programming on the Cardano Blockchain) | D13: COMPLETED | E13: 67900 | F13: 67900 | G13: =E13-F13 -> 0 | I13: Cardano Open: Ecosystem
A14: 6 | B14: 1300006 | C14: [DLC] Cardano Ecosystem Growth - Marketing DeFi Products | D14: COMPLETED | E14: 100000 | F14: 100000 | G14: =E14-F14 -> 0 | I14: Cardano Open: Ecosystem
A15: 7 | B15: 1300007 | C15: [DLC] Cardano Ecosystem Growth - Short Form Video Marketing | D15: COMPLETED | E15: 100000 | F15: 100000 | G15: =E15-F15 -> 0 | I15: Cardano Open: Ecosystem
A16: 8 | B16: 1300008 | C16: [HTLABS] 5 Project templates combining blockchain and internet of things | D16: PENDING | E16: 35857 | F16: 18000.01 | G16: =E16-F16 -> 17856.99 | I16: Cardano Open: Developers
A17: 9 | B17: 1300009 | C17: [LANTR] Scalus: Multiplatform Tx Builder – same code for front&backend | D17: COMPLETED | E17: 100000 | F17: 100000 | G17: =E17-F17 -> 0 | I17: Cardano Open: Developers
A18: 10 | B18: 1300010 | C18: [PKL] Cardano Governance Explorer Visualized with Graphs | D18: COMPLETED | E18: 120000 | F18: 120000 | G18: =E18-F18 -> 0 | I18: Cardano Use Cases: Concept
A19: 11 | B19: 1300011 | C19: [Tempo] Multi-party alliance | D19: PENDING | E19: 135000 | F19: 45000 | G19: =E19-F19 -> 90000 | I19: Cardano Use Cases: Concept
A20: 12 | B20: 1300012 | C20: 🇻🇳 Cardano App Development Course: A Step-by-Step Guide for Beginners - From basic Web development to use Cardano Libraries and interacting with Smart Contracts | D20: PENDING | E20: 34857 | F20: 27000 | G20: =E20-F20 -> 7857 | I20: Cardano Open: Ecosystem
... A207: 199 | B207: 1300199 | C207: zkFold x Asterizm - Interoperability Solution | D207: PENDING | E207: 500000 | F207: 420000 | G207: =E207-F207 -> 80000 | I207: Cardano Use Cases: Product

Sheet Fund12 Reporting
A1: THIS DOCUMENT WILL BE DEPRECATED SOON If you need support please submit a ticket via zendesk.
C4: FUND12 | E4: Funding (₳)
A5: # | B5: ID | C5: Project Name | D5: Project Status | E5: Requested | F5: Distributed to date | G5: Remaining | H5: Primary Proposer - Guarantor | I5: Challenge
E6: =SUM(E9:E266) -> 46484802 | F6: =SUM(F9:F266) -> 36912782 | G6: =SUM(G9:G266) -> 9572019.7
C8: =Counta(C9:C266) -> 258 | D8: =COUNTIF(D9:D266,"=COMPLETED") -> 163
A9: 1 | B9: 1200001 | C9: [5PC] Cardano Journey - Cardano Education Podcast Series for the Vietnamese Community | D9: COMPLETED | E9: 17352 | F9: 17352 | G9: =E9-F9 -> 0 | H9: 5 Minutes Crypto | I9: Cardano Open: Ecosystem
A10: 2 | B10: 1200002 | C10: [C2VN]: Cardano blockchain courseware in Universities | D10: COMPLETED | E10: 92000 | F10: 92000 | G10: =E10-F10 -> 0 | H10: cardano2vn | I10: Cardano Open: Ecosystem
A11: 3 | B11: 1200003 | C11: [C2VN]: Developing the Blockchain Lecturer Team at Universities in Vietnam | D11: COMPLETED | E11: 41250 | F11: 41250 | G11: =E11-F11 -> 0 | H11: nvhieu | I11: Cardano Open: Ecosystem
A12: 4 | B12: 1200004 | C12: [CaFi] Cardano news - Vietnamese version | D12: COMPLETED | E12: 17995 | F12: 17995 | G12: =E12-F12 -> 0 | H12: Duc Nguyen | I12: Cardano Open: Ecosystem
A13: 5 | B13: 1200005 | C13: [CaFi] Peer-Reviewed Technical Research Paper Library in Vietnamese version | D13: COMPLETED | E13: 18873 | F13: 18873 | G13: =E13-F13 -> 0 | H13: Tu Nguyen | I13: Cardano Open: Ecosystem
A14: 6 | B14: 1200006 | C14: [CASIA] Cardano Asia TikTok Channel (expand Korean, maintain Japanese/Vietnamese/English) + NEW Youtube Channel | D14: COMPLETED | E14: 79028 | F14: 79028 | G14: =E14-F14 -> 0 | H14: Cardano_Asia Team | I14: Cardano Open: Ecosystem
A15: 7 | B15: 1200007 | C15: [FIMI] Blockchain course for Vietnamese | D15: COMPLETED | E15: 74900 | F15: 74900 | G15: =E15-F15 -> 0 | H15: Fimi | I15: Cardano Open: Ecosystem
A16: 8 | B16: 1200008 | C16: [FIMI] Podcast Cardano on Telegram for Vietnamese | D16: COMPLETED | E16: 57150 | F16: 57150 | G16: =E16-F16 -> 0 | H16: Fimi | I16: Cardano Open: Ecosystem
A17: 9 | B17: 1200009 | C17: [nftcdn.io] Open Source JavaScript NFT Media Viewer/Player (music, video, 3D, etc.) | D17: COMPLETED | E17: 195349 | F17: 195349 | G17: =E17-F17 -> 0 | H17: Smaug | I17: Cardano Open: Developers
A18: 10 | B18: 1200010 | C18: Academic Research at UBA, one of the most prestigious Universities in LATAM, with focus on Decentralized Governance Research. | D18: COMPLETED | E18: 96000 | F18: 96000 | G18: =E18-F18 -> 0 | H18: LATAM Cardano Community | I18: Cardano Open: Ecosystem
A19: 11 | B19: 1200011 | C19: Accelerate Mass Adoption: Open Source Atala Wallet SDK with No Seed Phrase Vulnerability and a No-Code Self-Sovereign Identity Platform | D19: COMPLETED | E19: 489091 | F19: 489091 | G19: =E19-F19 -> 0 | H19: Socious Team | I19: Cardano Use Cases: Product
A20: 12 | B20: 1200012 | C20: ADA Cashback from Top Retailers, for Cardano Wallets | D20: COMPLETED | E20: 100000 | F20: 100000 | G20: =E20-F20 -> 0 | H20: Ethan Hanoch | I20: Cardano Use Cases: Concept
... A266: 258 | B266: 1200258 | C266: µgraph: Instant, Untraceable Payments in Cardano | D266: PENDING | E266: 300000 | F266: 192000 | G266: =E266-F266 -> 108000 | H266: Cainã Costa | I266: Cardano Use Cases: MVP

Sheet Fund11 Reporting
A1: THIS DOCUMENT WILL BE DEPRECATED SOON If you need support please submit a ticket via zendesk.
C4: FUND11 | E4: Funding (₳)
A5: # | B5: ID | C5: Project Name | D5: Project Status | E5: Requested | F5: Distributed to date | G5: Remaining | H5: Primary Proposer - Guarantor | I5: Challenge
E6: =SUM(E9:E308) -> 46489869 | F6: =SUM(F9:F308) -> 41424810 | G6: =SUM(G9:G308) -> 5065059
C7: Reporting %
C8: =Counta(C9:C308) -> 300
A9: 1 | B9: 1100001 | C9: "Together Learning Haskell/Plutus in native language" Club | D9: COMPLETED | E9: 33000 | F9: 33000 | G9: =E9-F9 -> 0 | H9: Tam Hoang | I9: Cardano Open: Ecosystem
A10: 2 | B10: 1100002 | C10: (Dead-man-switch) Permission based Wallet | D10: PENDING | E10: 100000 | F10: 8000 | G10: =E10-F10 -> 92000 | H10: Sandro Schaier | I10: Cardano Use Cases: Concept
A11: 3 | B11: 1100003 | C11: 10 Marlowe contract templates - the real life use cases | D11: PENDING | E11: 99040 | F11: 77040 | G11: =E11-F11 -> 22000 | H11: Jimmy Lee | I11: Cardano Open: Developers
A12: 4 | B12: 1100004 | C12: 45B - Marlowe workshops for Business professionals | D12: PENDING | E12: 49500 | F12: 19602 | G12: =E12-F12 -> 29898 | H12: 45B - Cardano Enablement | I12: Cardano Open: Ecosystem
A13: 5 | B13: 1100005 | C13: [5PC] Cardano Education Video on TikTok for the Vietnamese Community | D13: COMPLETED | E13: 15392 | F13: 15392 | G13: =E13-F13 -> 0 | H13: 5 Minutes Crypto | I13: Cardano Open: Ecosystem
A14: 6 | B14: 1100006 | C14: [C2VN] Accelerate Atala PRISM learning and adoption in Universities | D14: COMPLETED | E14: 148225 | F14: 148225 | G14: =E14-F14 -> 0 | H14: cardano2vn | I14: Cardano Open: Ecosystem
A15: 7 | B15: 1100007 | C15: [C2VN]: Cardano developer club in Universities | D15: COMPLETED | E15: 118361 | F15: 118361 | G15: =E15-F15 -> 0 | H15: cardano2vn | I15: Cardano Open: Ecosystem
A16: 8 | B16: 1100008 | C16: [FIMI] cardano.vn - Cardano information portal for Vietnamese people | D16: COMPLETED | E16: 17550 | F16: 17550 | G16: =E16-F16 -> 0 | H16: Fimi | I16: Cardano Open: Ecosystem
A17: 9 | B17: 1100009 | C17: [FIMI] Free Marlowe Course for Vietnamese | D17: COMPLETED | E17: 25000 | F17: 25000 | G17: =E17-F17 -> 0 | H17: Fimi | I17: Cardano Open: Ecosystem
A18: 10 | B18: 1100010 | C18: [FIMI] Plutus Pioneer #4 - Translating video dubbing in Vietnamese | D18: COMPLETED | E18: 20628 | F18: 20628 | G18: =E18-F18 -> 0 | H18: Fimi | I18: Cardano Open: Ecosystem
A19: 11 | B19: 1100011 | C19: Account NFT Smart-contract - Mint Verifiably Unique User Accounts that store data on-chain | D19: COMPLETED | E19: 140000 | F19: 140000 | G19: =E19-F19 -> 0 | H19: Peyton(bigpey) | I19: Cardano Open: Developers
A20: 12 | B20: 1100012 | C20: Accra Resource Center: Igniting African Youth in Cardano & Decentralised Web Innovation. | D20: COMPLETED | E20: 180000 | F20: 180000 | G20: =E20-F20 -> 0 | H20: Afia Owusu | I20: Cardano Open: Ecosystem
... A308: 300 | B308: 1100300 | C308: đź‡»đź‡ł The Complete Aiken Course Cardano: From Zero to Expert! | D308: COMPLETED | E308: 20000 | F308: 20000 | G308: =E308-F308 -> 0 | H308: Blockalpha Innova | I308: Cardano Open: Ecosystem

Sheet Fund10 Reporting
A1: THIS DOCUMENT WILL BE DEPRECATED SOON If you need support please submit a ticket via zendesk.
C4: FUND10 | E4: Funding (₳)
A5: # | B5: ID | C5: Project Name | D5: Project Status | E5: Requested | F5: Distributed to date | G5: Remaining | H5: Primary Proposer - Guarantor | I5: Challenge | J5: Progress Report | K5: Progress Report
E6: =SUM(E9:E200) -> 50857438 | F6: =SUM(F9:F200) -> 44470209 | G6: =SUM(G9:G200) -> 6387229.1 | J6: November '23 | K6: December '23
C7: Reporting % | I7: =Average(J7:K7) -> 0.71465969 | J7: =J8/($C$8 - (COUNTIF(J9:J200, "COMPLETED")+COUNTIF(J9:J200, ""))) -> 0.7434555 | K7: =K8/($C$8 - (COUNTIF(K9:K200, "COMPLETED")+COUNTIF(K9:K200, ""))) -> 0.68586387
C8: =Counta(C9:C200) -> 192 | J8: =COUNTIF(J9:J200, TRUE) -> 142 | K8: =COUNTIF(K9:K200, TRUE) -> 131
A9: 1 | B9: 1000001 | C9: [3] Student-Driven Demonstration of the Use of SSI and the Cardano Blockchain to Capture their Cardano Blockchain Skills | D9: COMPLETED | E9: 17800 | F9: 17800 | G9: =E9-F9 -> 0 | H9: Mark Byers | I9: F10: Startups & Onboarding for Students | J9: TRUE | K9: FALSE
A10: 2 | B10: 1000002 | C10: [Fimi] Cardanotalk for Vietnamese | D10: COMPLETED | E10: 33000 | F10: 33000 | G10: =E10-F10 -> 0 | H10: Fimi | I10: F10: Catalyst Open | J10: FALSE | K10: TRUE
A11: 3 | B11: 1000003 | C11: [Fimi] CatalystTalk for Vietnamese | D11: COMPLETED | E11: 16500 | F11: 16500 | G11: =E11-F11 -> 0 | H11: Do Viet Cuong | I11: F10: Catalyst Open | J11: TRUE | K11: TRUE
A12: 4 | B12: 1000004 | C12: 🇻🇳 Vietnam Cardano Catalyst - NFT Exchange testing and development environment helps young people approach with the Web3.0 platform | D12: COMPLETED | E12: 32000 | F12: 32000 | G12: =E12-F12 -> 0 | H12: Khuat Dinh Thanh | I12: F10: Startups & Onboarding for Students | J12: TRUE | K12: FALSE
A13: 5 | B13: 1000005 | C13: A Zero Knowledge Proof framework for Cardano based on Hydra and ZK-SNARKS | D13: COMPLETED | E13: 75000 | F13: 75000 | G13: =E13-F13 -> 0 | H13: Antonio Hernandez | I13: F10: Development & Infrastructure | J13: TRUE | K13: TRUE
A14: 6 | B14: 1000006 | C14: Adosia Open Governance Model | D14: COMPLETED | E14: 107500 | F14: 107500 | G14: =E14-F14 -> 0 | H14: Adosia Operations | I14: F10: DAOs ❤ Cardano | J14: TRUE | K14: TRUE
A15: 7 | B15: 1000007 | C15: Agora Suite Expansion: NFT Standards and Novel Token Structures Integration | D15: PENDING | E15: 275000 | F15: 219999.98 | G15: =E15-F15 -> 55000.02 | H15: john Valdez | I15: F10: DAOs ❤ Cardano | J15: FALSE | K15: FALSE
A16: 8 | B16: 1000008 | C16: Allow Cardano users to call Sidechain smart contracts directly from their Cardano mainnet wallet | D16: COMPLETED | E16: 448276 | F16: 448276 | G16: =E16-F16 -> 0 | H16: Sebastien Guillemot | I16: F10: Development & Infrastructure | J16: FALSE | K16: FALSE
A17: 9 | B17: 1000009 | C17: Allow using NFTs from Cardano and other ecosystem in onchain games hosted in the Cardano ecosystem | D17: PENDING | E17: 650000 | F17: 420000 | G17: =E17-F17 -> 230000 | H17: Sebastien Guillemot | I17: F10: Development & Infrastructure | J17: TRUE | K17: TRUE
A18: 10 | B18: 1000010 | C18: Anastasia Labs - Open Source Production Grade DApps | D18: COMPLETED | E18: 135500 | F18: 135500 | G18: =E18-F18 -> 0 | H18: philipdisarro | I18: F10: Developer Ecosystem - The Evolution | J18: TRUE | K18: TRUE
A19: 11 | B19: 1000011 | C19: Anastasia Labs - Smart Beacons, Router NFTs | D19: COMPLETED | E19: 150000 | F19: 150000 | G19: =E19-F19 -> 0 | H19: micah Kendall | I19: F10: OSDE: Open Source Dev Ecosystem | J19: TRUE | K19: TRUE
A20: 12 | B20: 1000012 | C20: Anastasia Labs - Streamlining Development: A User-Friendly Smart Contract Library for Plutarch and Aiken Design Patterns & Efficiency | D20: COMPLETED | E20: 250000 | F20: 250000 | G20: =E20-F20 -> 0 | H20: philipdisarro | I20: F10: Development & Infrastructure | J20: TRUE | K20: TRUE
... A42: 34 | B42: 1000034 | C42: Cardano Student Blockchain Ambassador Program | D42: COMPLETED | E42: 25000 | F42: 25000 | G42: =E42-F42 -> 0 | H42: Barbara Ofosu | I42: F10: Startups & Onboarding for Students | J42: TRUE | K42: TRUE
A43: 35 | B43: 1000035 | C43: Cardano Summit 2023 NFT Hoodies - Verifiable Ownership Of Real World Merch | D43: COMPLETED | E43: 50000 | F43: 50000 | G43: =E43-F43 -> 0 | H43: Pritesh Gosai | I43: F10: Catalyst Open | J43: COMPLETED | K43: COMPLETED
A44: 36 | B44: 1000036 | C44: Cardano Tax & Accounting Tool | D44: COMPLETED | E44: 300500 | F44: 300500 | G44: =E44-F44 -> 0 | H44: philipdisarro | I44: F10: Products & Integrations | J44: TRUE | K44: TRUE
A45: 37 | B45: 1000037 | C45: Cardano Woman Indonesia | D45: COMPLETED | E45: 24211 | F45: 24211 | G45: =E45-F45 -> 0 | H45: Fanny Wijaya | I45: F10: Catalyst Open | J45: TRUE | K45: TRUE
A46: 38 | B46: 1000038 | C46: CardanoCodex'23: A Hackathon Aiming to Increase Exposure for Cardano Within a Massive Developer Base | D46: COMPLETED | E46: 35666 | F46: 35666 | G46: =E46-F46 -> 0 | H46: Adnan | I46: F10: Startups & Onboarding for Students | J46: FALSE | K46: FALSE
A47: 39 | B47: 1000039 | C47: Cardanoscan.io Maintenance | D47: COMPLETED | E47: 78000 | F47: 78000 | G47: =E47-F47 -> 0 | H47: Strica | I47: F10: Development & Infrastructure | J47: FALSE | K47: FALSE
A48: 40 | B48: 1000040 | C48: CardanoShield: Protecting Cardano Wallet Users | D48: COMPLETED | E48: 250000 | F48: 250000 | G48: =E48-F48 -> 0 | H48: Shawn Roller | I48: F10: Development & Infrastructure | J48: TRUE | K48: TRUE
A49: 41 | B49: 1000041 | C49: Catalyst Africa Town Hall Operations | D49: COMPLETED | E49: 75000 | F49: 75000 | G49: =E49-F49 -> 0 | H49: Catalyst Africa Town Hall | I49: F10: Catalyst Open | J49: TRUE | K49: TRUE
A50: 42 | B50: 1000042 | C50: Catalyst Africa Town Hall: Bridging the Gap for Continental Expansion | D50: COMPLETED | E50: 75000 | F50: 75000 | G50: =E50-F50 -> 0 | H50: Catalyst Africa Town Hall | I50: F10: Catalyst Open | J50: TRUE | K50: TRUE
A51: 43 | B51: 1000043 | C51: Catalyst Completed Project NFTs | D51: COMPLETED | E51: 49800 | F51: 49800 | G51: =E51-F51 -> 0 | H51: LIDO Nation Foundation | I51: F10: Building on NMKR | J51: TRUE | K51: TRUE
A52: 44 | B52: 1000044 | C52: Catalyst Explorer 2.5: Accessible Catalyst Data & Tools | D52: COMPLETED | E52: 172666 | F52: 172666 | G52: =E52-F52 -> 0 | H52: LIDO Nation Foundation | I52: F10: Products & Integrations | J52: TRUE | K52: TRUE
A53: 45 | B53: 1000045 | C53: Catalyst Explorer dRep module: Directory, Community, Draft Ballots | D53: COMPLETED | E53: 148000 | F53: 148000 | G53: =E53-F53 -> 0 | H53: LIDO Nation Foundation | I53: F10: dRep improvement and onboarding | J53: TRUE | K53: TRUE
A54: 46 | B54: 1000046 | C54: Catalyst Fund Operations by IOG Catalyst Team | D54: COMPLETED | E54: 6420000 | F54: 6420000 | G54: =E54-F54 -> 0 | H54: Catalyst Team | I54: F10: Catalyst Fund Operations | J54: FALSE | K54: FALSE
A55: 47 | B55: 1000047 | C55: Catalyst Outreach 4 The Unreached in Ghana | D55: COMPLETED | E55: 21000 | F55: 21000 | G55: =E55-F55 -> 0 | H55: Emelia Sarfo | I55: F10: Catalyst Open | J55: TRUE | K55: TRUE
... A200: 192 | B200: 1000192 | C200: Xerberus: Risk Ratings for all Fungible Assets on Cardano | D200: PENDING | E200: 400000 | F200: 320000 | G200: =E200-F200 -> 80000 | H200: Xerberus | I200: F10: Products & Integrations | J200: TRUE | K200: FALSE

Sheet Fund9 Reporting
A1: THIS DOCUMENT WILL BE DEPRECATED SOON If you need support please submit a ticket via zendesk.
C4: FUND9 | E4: Funding ($)
A5: # | B5: ID | C5: Project Name | D5: Project Status | E5: Requested | F5: Distributed to date | G5: Remaining | H5: Primary Proposer - Guarantor | I5: Challenge | J5: Progress Report | K5: Progress Report | L5: Progress Report | M5: Progress Report | N5: Progress Report | O5: Progress Report | P5: Progress Report | Q5: Progress Report | R5: Progress Report | S5: Progress Report | T5: Progress Report | U5: Progress Report | V5: Progress Report | W5: Progress Report
E6: =SUM(E9:E224) -> 12799696 | F6: =SUM(F9:F224) -> 12040510 | G6: =SUM(G9:G224) -> 759186.21 | J6: November '22 | K6: December '22 | L6: January '23 | M6: February '23 | N6: March '23 | O6: April '23 | P6: May '23 | Q6: June '23 | R6: July '23 | S6: August '23 | T6: September '23 | U6: October '23 | V6: November '23 | W6: December '23
C7: Reporting % | I7: =Average(J7:L7) -> 0.62291953 | J7: =J8/($C$8 - (COUNTIF(J9:J224, "COMPLETED")+COUNTIF(J9:J224, ""))) -> 0.72769953 | K7: =K8/($C$8 - (COUNTIF(K9:K224, "COMPLETED")+COUNTIF(K9:K224, ""))) -> 0.53301887 | L7: =L8/($C$8 - (COUNTIF(L9:L224, "COMPLETED")+COUNTIF(L9:L224, ""))) -> 0.6080402 | M7: =M8/($C$8 - (COUNTIF(M9:M224, "COMPLETED")+COUNTIF(M9:M224, ""))) -> 0.63372093 | N7: =N8/($C$8 - (COUNTIF(N9:N224, "COMPLETED")+COUNTIF(N9:N224, ""))) -> 0.57058824 | O7: =O8/($C$8 - (COUNTIF(O9:O224, "COMPLETED")+COUNTIF(O9:O224, ""))) -> 0.41059603 | P7: =P8/($C$8 - (COUNTIF(P9:P224, "COMPLETED")+COUNTIF(P9:P224, ""))) -> 0.26206897 | Q7: =Q8/($C$8 - (COUNTIF(Q9:Q224, "COMPLETED")+COUNTIF(Q9:Q224, ""))) -> 0.25735294 | ... W7: =W8/($C$8 - (COUNTIF(W9:W224, "COMPLETED")+COUNTIF(W9:W224, ""))) -> 0.0625
C8: =Counta(C9:C224) -> 216 | J8: =COUNTIF(J9:J224, TRUE) -> 155 | K8: =COUNTIF(K9:K224, TRUE) -> 113 | L8: =COUNTIF(L9:L224, TRUE) -> 121 | M8: =COUNTIF(M9:M224, TRUE) -> 109 | N8: =COUNTIF(N9:N224, TRUE) -> 97 | O8: =COUNTIF(O9:O224, TRUE) -> 62 | P8: =COUNTIF(P9:P224, TRUE) -> 38 | Q8: =COUNTIF(Q9:Q224, TRUE) -> 35 | ... W8: =COUNTIF(W9:W224, TRUE) -> 5
A9: 1 | B9: 900001 | C9: 500+ â‚łCommunity Sent to Conferences | D9: DID NOT FINISH | E9: 420000 | F9: 210000 | G9: =E9-F9 -> 210000 | H9: Ninh Tran | I9: F9: Dapps, Products & Integrations | J9: TRUE | K9: FALSE | L9: TRUE | M9: TRUE | N9: FALSE | O9: FALSE | P9: FALSE | Q9: FALSE | R9: FALSE | S9: FALSE | T9: FALSE | U9: FALSE | V9: FALSE | W9: FALSE
A10: 2 | B10: 900002 | C10: A standard for token verification | D10: COMPLETED | E10: 22000 | F10: 22000 | G10: =E10-F10 -> 0 | H10: MuesliSwap Team | I10: F9: Dapps, Products & Integrations | J10: FALSE | K10: FALSE | L10: TRUE | M10: TRUE | N10: TRUE | O10: FALSE | P10: FALSE | Q10: FALSE | R10: FALSE | S10: FALSE | T10: FALSE | U10: COMPLETED | V10: COMPLETED | W10: COMPLETED
A11: 3 | B11: 900003 | C11: Accelerator batch #3 | D11: DID NOT FINISH | E11: 120000 | F11: 10000 | G11: =E11-F11 -> 110000 | H11: Sebastien Guillemot | I11: F9: The Great Migration (from Ethereum) | J11: FALSE | K11: FALSE | L11: TRUE | M11: FALSE | N11: FALSE | O11: FALSE | P11: FALSE | Q11: FALSE | R11: FALSE | S11: FALSE | T11: FALSE | U11: FALSE | V11: FALSE | W11: FALSE
A12: 4 | B12: 900004 | C12: Accounting Reporting France | D12: COMPLETED | E12: 11200 | F12: 11200 | G12: =E12-F12 -> 0 | H12: Yoram | I12: F9: Legal & Financial Implementations | J12: TRUE | K12: TRUE | L12: TRUE | M12: TRUE | N12: TRUE | O12: TRUE | P12: FALSE | Q12: COMPLETED | R12: COMPLETED | S12: COMPLETED | T12: COMPLETED | U12: COMPLETED | V12: COMPLETED | W12: COMPLETED
A13: 5 | B13: 900005 | C13: ADA Bug Bounty Website | D13: COMPLETED | E13: 55100 | F13: 55100 | G13: =E13-F13 -> 0 | H13: Steven Fisher | I13: F9: Dapps, Products & Integrations | J13: TRUE | K13: TRUE | L13: TRUE | M13: TRUE | N13: TRUE | O13: FALSE | P13: FALSE | Q13: FALSE | R13: COMPLETED | S13: COMPLETED | T13: COMPLETED | U13: COMPLETED | V13: COMPLETED | W13: COMPLETED
A14: 6 | B14: 900006 | C14: ADABET.iO | Cardano Betting DApp | D14: COMPLETED | E14: 125005 | F14: 125005 | G14: =E14-F14 -> 0 | H14: Trong | I14: F9: Dapps, Products & Integrations | J14: TRUE | K14: FALSE | L14: TRUE | M14: TRUE | N14: TRUE | O14: TRUE | P14: TRUE | Q14: TRUE | R14: TRUE | S14: TRUE | T14: TRUE | U14: TRUE | V14: FALSE | W14: COMPLETED
A15: 7 | B15: 900007 | C15: ADAO - Plutus Token Vesting DApp | D15: COMPLETED | E15: 33000 | F15: 33000 | G15: =E15-F15 -> 0 | H15: Adaminnow | I15: F9: Dapps, Products & Integrations | J15: FALSE | K15: FALSE | L15: FALSE | M15: FALSE | N15: FALSE | O15: FALSE | P15: FALSE | Q15: FALSE | R15: FALSE | S15: FALSE | T15: TRUE | U15: FALSE | V15: FALSE | W15: FALSE
A16: 8 | B16: 900008 | C16: ADAO - RoundTable v2: Staking + | D16: COMPLETED | E16: 43350 | F16: 43350 | G16: =E16-F16 -> 0 | H16: Adaminnow | I16: F9: Dapps, Products & Integrations | J16: FALSE | K16: TRUE | L16: FALSE | M16: COMPLETED | N16: COMPLETED | O16: COMPLETED | P16: COMPLETED | Q16: COMPLETED | R16: COMPLETED | S16: COMPLETED | T16: COMPLETED | U16: COMPLETED | V16: COMPLETED | W16: COMPLETED
A17: 9 | B17: 900009 | C17: ADAO- NFT Fractionalization Dapp | D17: COMPLETED | E17: 33750 | F17: 33750 | G17: =E17-F17 -> 0 | H17: Adaminnow | I17: F9: Dapps, Products & Integrations | J17: FALSE | K17: TRUE | L17: TRUE | M17: FALSE | N17: FALSE | O17: FALSE | P17: FALSE | Q17: FALSE | R17: FALSE | S17: FALSE | T17: FALSE | U17: FALSE | V17: FALSE | W17: FALSE
A18: 10 | B18: 900010 | C18: ADAO Open Source Development | D18: COMPLETED | E18: 76000 | F18: 76000 | G18: =E18-F18 -> 0 | H18: Adaminnow | I18: F9: DAOs <3 Cardano | J18: FALSE | K18: FALSE | L18: FALSE | M18: COMPLETED | N18: COMPLETED | O18: COMPLETED | P18: COMPLETED | Q18: COMPLETED | R18: COMPLETED | S18: COMPLETED | T18: COMPLETED | U18: COMPLETED | V18: COMPLETED | W18: COMPLETED
A19: 11 | B19: 900011 | C19: ADAO: Comprehensive DAO's Course | D19: COMPLETED | E19: 12160 | F19: 12160 | G19: =E19-F19 -> 0 | H19: baxter30 | I19: F9: DAOs <3 Cardano | J19: TRUE | K19: FALSE | L19: FALSE | M19: FALSE | N19: TRUE | O19: FALSE | P19: FALSE | Q19: FALSE | R19: FALSE | S19: FALSE | T19: FALSE | U19: FALSE | V19: FALSE | W19: FALSE
A20: 12 | B20: 900012 | C20: AdaPulse: Independent Media Outlet | D20: COMPLETED | E20: 222800 | F20: 222800 | G20: =E20-F20 -> 0 | H20: Jeff | I20: F9: Dapps, Products & Integrations | J20: FALSE | K20: FALSE | L20: FALSE | M20: TRUE | N20: FALSE | O20: FALSE | P20: TRUE | Q20: FALSE | R20: FALSE | S20: TRUE | T20: FALSE | U20: FALSE | V20: FALSE | W20: FALSE
A21: 13 | B21: 900013 | C21: ADATOMS Science & DeFi FREE Ed. | D21: COMPLETED | E21: 7000 | F21: 7000 | G21: =E21-F21 -> 0 | H21: adatomsnft | I21: F9: Dapps, Products & Integrations | J21: FALSE | K21: FALSE | L21: TRUE | M21: TRUE | N21: FALSE | O21: TRUE | P21: FALSE | Q21: FALSE | R21: FALSE | S21: COMPLETED | T21: COMPLETED | U21: COMPLETED | V21: COMPLETED | W21: COMPLETED
A22: 14 | B22: 900014 | C22: ADAwell: Wellbeing DAO | D22: COMPLETED | E22: 5690 | F22: 5690 | G22: =E22-F22 -> 0 | H22: Ada Raimova | I22: F9: DAOs <3 Cardano | J22: TRUE | K22: TRUE | L22: COMPLETED | M22: COMPLETED | N22: COMPLETED | O22: COMPLETED | P22: COMPLETED | Q22: COMPLETED | R22: COMPLETED | S22: COMPLETED | T22: COMPLETED | U22: COMPLETED | V22: COMPLETED | W22: COMPLETED
A23: 15 | B23: 900015 | C23: Add Senior Developers to Ecosystem | D23: COMPLETED | E23: 31000 | F23: 31000 | G23: =E23-F23 -> 0 | H23: Udai Solanki | I23: F9: Developer Ecosystem | J23: TRUE | K23: FALSE | L23: TRUE | M23: FALSE | N23: TRUE | O23: TRUE | P23: FALSE | Q23: FALSE | R23: FALSE | S23: FALSE | T23: FALSE | U23: FALSE | V23: FALSE | W23: FALSE
A24: 16 | B24: 900016 | C24: Adosia Marketplace Updates | D24: COMPLETED | E24: 175000 | F24: 175000 | G24: =E24-F24 -> 0 | H24: Adosia Operations | I24: F9: Dapps, Products & Integrations | J24: TRUE | K24: FALSE | L24: TRUE | M24: TRUE | N24: TRUE | O24: FALSE | P24: FALSE | Q24: TRUE | R24: COMPLETED | S24: COMPLETED | T24: COMPLETED | U24: COMPLETED | V24: COMPLETED | W24: COMPLETED
A25: 17 | B25: 900017 | C25: Adosia Spaceprinter Lite | D25: DID NOT FINISH | E25: 50000 | F25: 40000 | G25: =E25-F25 -> 10000 | H25: Adosia Operations | I25: F9: Dapps, Products & Integrations | J25: TRUE | K25: TRUE | L25: TRUE | M25: TRUE | N25: TRUE | O25: FALSE | P25: FALSE | Q25: TRUE | R25: FALSE | S25: FALSE | T25: FALSE | U25: FALSE | V25: FALSE | W25: FALSE
A26: 18 | B26: 900018 | C26: AI lawyer on Cardano - Profila/HSLU | D26: COMPLETED | E26: 78000 | F26: 78000 | G26: =E26-F26 -> 0 | H26: Michiel Van Roey | I26: F9: Legal & Financial Implementations | J26: TRUE | K26: TRUE | L26: TRUE | M26: TRUE | N26: TRUE | O26: FALSE | P26: FALSE | Q26: COMPLETED | R26: COMPLETED | S26: COMPLETED | T26: COMPLETED | U26: COMPLETED | V26: COMPLETED | W26: COMPLETED
A27: 19 | B27: 900019 | C27: Algae Token a Sustainable Future | D27: PENDING | F27: 0 | G27: =E27-F27 -> 0 | H27: AlgaeToken | I27: F9: Catalyst Natives X Cardashift: Demonstrating and monetizing impact | J27: FALSE | K27: FALSE | L27: FALSE | M27: FALSE | N27: FALSE | O27: FALSE | P27: FALSE | Q27: FALSE | R27: FALSE | S27: FALSE | T27: FALSE | U27: FALSE | V27: FALSE | W27: FALSE
A28: 20 | B28: 900020 | C28: ALOHA for Cardano | D28: COMPLETED | E28: 4160 | F28: 4160 | G28: =E28-F28 -> 0 | H28: Benji | I28: F9: Challenge & Scouted for Students🎓 | J28: TRUE | K28: FALSE | L28: FALSE | M28: TRUE | N28: TRUE | O28: TRUE | P28: COMPLETED | Q28: COMPLETED | R28: COMPLETED | S28: COMPLETED | T28: COMPLETED | U28: COMPLETED | V28: COMPLETED | W28: COMPLETED
A29: 21 | B29: 900021 | C29: AMA with Cross-Chain Communities | D29: COMPLETED | E29: 3420 | F29: 3420 | G29: =E29-F29 -> 0 | H29: ivankwananda | I29: F9: Cross-Chain Collaboration | J29: TRUE | K29: TRUE | L29: TRUE | M29: COMPLETED | N29: COMPLETED | O29: COMPLETED | P29: COMPLETED | Q29: COMPLETED | R29: COMPLETED | S29: COMPLETED | T29: COMPLETED | U29: COMPLETED | V29: COMPLETED | W29: COMPLETED
A30: 22 | B30: 900022 | C30: Atala Integration with Milkomeda | D30: COMPLETED | E30: 46100 | F30: 46100 | G30: =E30-F30 -> 0 | H30: Seira Yun Socious.io | I30: F9: Dapps, Products & Integrations | J30: TRUE | K30: TRUE | L30: TRUE | M30: TRUE | N30: TRUE | O30: TRUE | P30: FALSE | Q30: COMPLETED | R30: COMPLETED | S30: COMPLETED | T30: COMPLETED | U30: COMPLETED | V30: COMPLETED | W30: COMPLETED
A31: 23 | B31: 900023 | C31: ATALA Prism zKP + Hyperledger Aries | D31: DID NOT FINISH | E31: 82000 | F31: 73800 | G31: =E31-F31 -> 8200 | H31: Ninh Tran | I31: F9: Cross-Chain Collaboration | J31: TRUE | K31: FALSE | L31: TRUE | M31: TRUE | N31: TRUE | O31: FALSE | P31: FALSE | Q31: FALSE | R31: FALSE | S31: FALSE | T31: FALSE | U31: FALSE | V31: FALSE | W31: FALSE
A32: 24 | B32: 900024 | C32: Attract ETH NFT Projects & Talent | D32: COMPLETED | E32: 28837 | F32: 28837 | G32: =E32-F32 -> 0 | H32: newmindflow | I32: F9: The Great Migration (from Ethereum) | J32: TRUE | K32: TRUE | L32: FALSE | M32: FALSE | N32: FALSE | O32: FALSE | P32: FALSE | Q32: FALSE | R32: FALSE | S32: FALSE | T32: FALSE | U32: FALSE | V32: FALSE | W32: FALSE
A33: 25 | B33: 900025 | C33: Blockchain Surveys for DAOs & More | D33: COMPLETED | E33: 34560 | F33: 34560 | G33: =E33-F33 -> 0 | H33: Darlington Wleh | I33: F9: DAOs <3 Cardano | J33: TRUE | K33: FALSE | L33: FALSE | M33: FALSE | N33: FALSE | O33: FALSE | P33: FALSE | Q33: FALSE | R33: FALSE | S33: FALSE | T33: FALSE | U33: FALSE | V33: FALSE | W33: TRUE
A34: 26 | B34: 900026 | C34: BLOCKTRUST identity wallet (PRISM) | D34: COMPLETED | E34: 45000 | F34: 45000 | G34: =E34-F34 -> 0 | H34: Björn Sandmann | I34: F9: Dapps, Products & Integrations | J34: TRUE | K34: FALSE | L34: TRUE | M34: TRUE | N34: TRUE | O34: FALSE | P34: FALSE | Q34: FALSE | R34: TRUE | S34: TRUE | T34: TRUE | U34: COMPLETED | V34: COMPLETED | W34: COMPLETED
A35: 27 | B35: 900027 | C35: Blueprint for Investment Funds | D35: COMPLETED | E35: 39857 | F35: 39857 | G35: =E35-F35 -> 0 | H35: dynamicstrategiesio | I35: F9: Legal & Financial Implementations | J35: TRUE | K35: FALSE | L35: FALSE | M35: TRUE | N35: FALSE | O35: FALSE | P35: FALSE | Q35: FALSE | R35: FALSE | S35: FALSE | T35: FALSE | U35: FALSE | V35: COMPLETED | W35: COMPLETED
A36: 28 | B36: 900028 | C36: Boosting Cardano In South Africa | D36: COMPLETED | E36: 27410 | F36: 27410 | G36: =E36-F36 -> 0 | H36: Kaelo Lentsoe | I36: F9: Grow Africa, Grow Cardano | J36: TRUE | K36: TRUE | L36: COMPLETED | M36: COMPLETED | N36: COMPLETED | O36: COMPLETED | P36: COMPLETED | Q36: COMPLETED | R36: COMPLETED | S36: COMPLETED | T36: COMPLETED | U36: COMPLETED | V36: COMPLETED | W36: COMPLETED
A37: 29 | B37: 900029 | C37: Bringing Business to Cardano | D37: COMPLETED | E37: 10329 | F37: 10329 | G37: =E37-F37 -> 0 | H37: Token Allies | I37: F9: Cross-Chain Collaboration | J37: TRUE | K37: FALSE | L37: TRUE | M37: TRUE | N37: TRUE | O37: FALSE | P37: COMPLETED | Q37: COMPLETED | R37: COMPLETED | S37: COMPLETED | T37: COMPLETED | U37: COMPLETED | V37: COMPLETED | W37: COMPLETED
A38: 30 | B38: 900030 | C38: Bringing Cardano to Cambridge | D38: DID NOT FINISH | E38: 4900 | F38: 0 | G38: =E38-F38 -> 4900 | H38: Alan Casey | I38: F9: Challenge & Scouted for Students🎓 | J38: TRUE | K38: FALSE | L38: FALSE | M38: FALSE | N38: FALSE | O38: FALSE | P38: FALSE | Q38: FALSE | R38: FALSE | S38: FALSE | T38: FALSE | U38: FALSE | V38: FALSE | W38: FALSE
A39: 31 | B39: 900031 | C39: Buy food & make an impact | D39: COMPLETED | E39: 31500 | F39: 31500 | G39: =E39-F39 -> 0 | H39: Magnus Edvard Nielsen | I39: F9: Dapps, Products & Integrations | J39: TRUE | K39: TRUE | L39: FALSE | M39: COMPLETED | N39: COMPLETED | O39: COMPLETED | P39: COMPLETED | Q39: COMPLETED | R39: COMPLETED | S39: COMPLETED | T39: COMPLETED | U39: COMPLETED | V39: COMPLETED | W39: COMPLETED
A40: 32 | B40: 900032 | C40: Cardano 101 Course - Kaizen Crypto | D40: COMPLETED | E40: 30000 | F40: 30000 | G40: =E40-F40 -> 0 | H40: Pritesh Gosai | I40: F9: Dapps, Products & Integrations | J40: TRUE | K40: TRUE | L40: TRUE | M40: TRUE | N40: TRUE | O40: TRUE | P40: FALSE | Q40: TRUE | R40: TRUE | S40: TRUE | T40: FALSE | U40: FALSE | V40: FALSE | W40: FALSE
A41: 33 | B41: 900033 | C41: Cardano Africa SmartFarming DApp | D41: COMPLETED | E41: 15000 | F41: 15000 | G41: =E41-F41 -> 0 | H41: Angela | I41: F9: Grow Africa, Grow Cardano | J41: TRUE | K41: FALSE | L41: TRUE | M41: TRUE | N41: FALSE | O41: COMPLETED | P41: COMPLETED | Q41: COMPLETED | R41: COMPLETED | S41: COMPLETED | T41: COMPLETED | U41: COMPLETED | V41: COMPLETED | W41: COMPLETED
A42: 34 | B42: 900034 | C42: Cardano Asia TikTok Channel | D42: COMPLETED | E42: 16800 | F42: 16800 | G42: =E42-F42 -> 0 | H42: Cardano_Asia | I42: F9: Grow East Asia, Grow Cardano | J42: TRUE | K42: TRUE | L42: TRUE | M42: TRUE | N42: TRUE | O42: TRUE | P42: FALSE | Q42: FALSE | R42: COMPLETED | S42: COMPLETED | T42: COMPLETED | U42: COMPLETED | V42: COMPLETED | W42: COMPLETED
A43: 35 | B43: 900035 | C43: Cardano Bridges in Japanese | D43: COMPLETED | E43: 5800 | F43: 5800 | G43: =E43-F43 -> 0 | H43: Leo King | I43: F9: Grow East Asia, Grow Cardano | J43: TRUE | K43: FALSE | L43: TRUE | M43: TRUE | N43: TRUE | O43: TRUE | P43: FALSE | Q43: FALSE | R43: COMPLETED | S43: COMPLETED | T43: COMPLETED | U43: COMPLETED | V43: COMPLETED | W43: COMPLETED
A44: 36 | B44: 900036 | C44: Cardano Community Center Cape Town | D44: COMPLETED | E44: 100000 | F44: 100000 | G44: =E44-F44 -> 0 | H44: The Art Bank | I44: F9: Grow Africa, Grow Cardano | J44: FALSE | K44: FALSE | L44: FALSE | M44: TRUE | N44: TRUE | O44: TRUE | P44: FALSE | Q44: TRUE | R44: TRUE | S44: COMPLETED | T44: COMPLETED | U44: COMPLETED | V44: COMPLETED | W44: COMPLETED
A45: 37 | B45: 900037 | C45: Cardano DAO Dashboard | D45: COMPLETED | E45: 12500 | F45: 12500 | G45: =E45-F45 -> 0 | H45: Clear Contracts | I45: F9: DAOs <3 Cardano | J45: FALSE | K45: TRUE | L45: FALSE | M45: FALSE | N45: FALSE | O45: FALSE | P45: FALSE | Q45: FALSE | R45: FALSE | S45: FALSE | T45: FALSE | U45: FALSE | V45: FALSE | W45: FALSE
A46: 38 | B46: 900038 | C46: Cardano for Africa | D46: COMPLETED | E46: 5000 | F46: 5000 | G46: =E46-F46 -> 0 | H46: Yosr Benmahmoud | I46: F9: Challenge & Scouted for Students🎓 | J46: TRUE | K46: TRUE | L46: FALSE | M46: TRUE | N46: FALSE | O46: FALSE | P46: FALSE | Q46: FALSE | R46: FALSE | S46: FALSE | T46: FALSE | U46: FALSE | V46: FALSE | W46: FALSE
A47: 39 | B47: 900039 | C47: Cardano for MENA | D47: COMPLETED | E47: 5000 | F47: 5000 | G47: =E47-F47 -> 0 | H47: Yosr Benmahmoud | I47: F9: Challenge & Scouted for Students🎓 | J47: TRUE | K47: TRUE | L47: FALSE | M47: TRUE | N47: FALSE | O47: FALSE | P47: FALSE | Q47: FALSE | R47: COMPLETED | S47: COMPLETED | T47: COMPLETED | U47: COMPLETED | V47: COMPLETED | W47: COMPLETED
A48: 40 | B48: 900040 | C48: Cardano for STEM Brazilian students | D48: COMPLETED | E48: 5000 | F48: 5000 | G48: =E48-F48 -> 0 | H48: Gilvânia Vilela | I48: F9: Challenge & Scouted for Students🎓 | J48: TRUE | K48: TRUE | L48: COMPLETED | M48: COMPLETED | N48: COMPLETED | O48: COMPLETED | P48: COMPLETED | Q48: COMPLETED | R48: COMPLETED | S48: COMPLETED | T48: COMPLETED | U48: COMPLETED | V48: COMPLETED | W48: COMPLETED
A49: 41 | B49: 900041 | C49: Cardano Forest - blocktree.asia | D49: COMPLETED | E49: 37800 | F49: 37800 | G49: =E49-F49 -> 0 | H49: Quoc ADAUP | I49: F9: Dapps, Products & Integrations | J49: TRUE | K49: FALSE | L49: FALSE | M49: FALSE | N49: TRUE | O49: TRUE | P49: TRUE | Q49: TRUE | R49: TRUE | S49: COMPLETED | T49: COMPLETED | U49: COMPLETED | V49: COMPLETED | W49: COMPLETED
A50: 42 | B50: 900042 | C50: Cardano General Help Desk | D50: COMPLETED | E50: 2150 | F50: 2150 | G50: =E50-F50 -> 0 | H50: Leo King | I50: F9: Dapps, Products & Integrations | J50: TRUE | K50: FALSE | L50: TRUE | M50: TRUE | N50: TRUE | O50: FALSE | P50: FALSE | Q50: FALSE | R50: FALSE | S50: FALSE | T50: FALSE | U50: FALSE | V50: COMPLETED | W50: COMPLETED
A51: 43 | B51: 900043 | C51: Cardano NFT Gaming - Lovelace Saga! | D51: COMPLETED | E51: 250000 | F51: 250000 | G51: =E51-F51 -> 0 | H51: Pritesh Gosai | I51: F9: Dapps, Products & Integrations | J51: TRUE | K51: TRUE | L51: TRUE | M51: TRUE | N51: FALSE | O51: TRUE | P51: TRUE | Q51: TRUE | R51: FALSE | S51: COMPLETED | T51: COMPLETED | U51: COMPLETED | V51: COMPLETED | W51: COMPLETED
A52: 44 | B52: 900044 | C52: Cardano Peer Education | D52: COMPLETED | E52: 5000 | F52: 5000 | G52: =E52-F52 -> 0 | H52: ddlezu01 | I52: F9: Challenge & Scouted for Students🎓 | J52: COMPLETED | M52: COMPLETED | N52: COMPLETED | O52: COMPLETED | P52: COMPLETED | Q52: COMPLETED | R52: COMPLETED | S52: COMPLETED | T52: COMPLETED | U52: COMPLETED | V52: COMPLETED | W52: COMPLETED
A53: 45 | B53: 900045 | C53: Cardano SSI Contributors - Season 2 | D53: COMPLETED | E53: 9100 | F53: 9100 | G53: =E53-F53 -> 0 | H53: RootsID | I53: F9: Cross-Chain Collaboration | J53: TRUE | K53: TRUE | L53: FALSE | M53: COMPLETED | N53: COMPLETED | O53: COMPLETED | P53: COMPLETED | Q53: COMPLETED | R53: COMPLETED | S53: COMPLETED | T53: COMPLETED | U53: COMPLETED | V53: COMPLETED | W53: COMPLETED
A54: 46 | B54: 900046 | C54: Cardano Start Guide | D54: PENDING | E54: 9600 | F54: 8399.99 | G54: =E54-F54 -> 1200.01 | H54: Leo King | I54: F9: Dapps, Products & Integrations | J54: TRUE | K54: FALSE | L54: TRUE | M54: TRUE | N54: TRUE | O54: TRUE | P54: FALSE | Q54: FALSE | R54: FALSE | S54: FALSE | T54: FALSE | U54: FALSE | V54: FALSE | W54: FALSE
A55: 47 | B55: 900047 | C55: Cardano Student Learning Platform | D55: COMPLETED | E55: 1800 | F55: 1800 | G55: =E55-F55 -> 0 | H55: Kingsley Ampofo | I55: F9: Challenge & Scouted for Students🎓 | J55: TRUE | K55: FALSE | L55: COMPLETED | M55: COMPLETED | N55: COMPLETED | O55: COMPLETED | P55: COMPLETED | Q55: COMPLETED | R55: COMPLETED | S55: COMPLETED | T55: COMPLETED | U55: COMPLETED | V55: COMPLETED | W55: COMPLETED
A56: 48 | B56: 900048 | C56: Cardano Submit API in Golang | D56: COMPLETED | E56: 5000 | F56: 5000 | G56: =E56-F56 -> 0 | H56: Chris Gianelloni | I56: F9: Dapps, Products & Integrations | J56: FALSE | K56: FALSE | L56: TRUE | M56: COMPLETED | N56: COMPLETED | O56: COMPLETED | P56: COMPLETED | Q56: COMPLETED | R56: COMPLETED | S56: COMPLETED | T56: COMPLETED | U56: COMPLETED | V56: COMPLETED | W56: COMPLETED
A57: 49 | B57: 900049 | C57: Cardano Tunisia | D57: COMPLETED | E57: 5000 | F57: 5000 | G57: =E57-F57 -> 0 | H57: Yosr Benmahmoud | I57: F9: Challenge & Scouted for Students🎓 | J57: TRUE | K57: TRUE | L57: FALSE | M57: TRUE | N57: FALSE | O57: FALSE | P57: COMPLETED | Q57: COMPLETED | R57: COMPLETED | S57: COMPLETED | T57: COMPLETED | U57: COMPLETED | V57: COMPLETED | W57: COMPLETED
A58: 50 | B58: 900050 | C58: Cardano Wallet OneBox | D58: COMPLETED | E58: 45000 | F58: 45000 | G58: =E58-F58 -> 0 | H58: Sebastien Guillemot | I58: F9: Developer Ecosystem | J58: TRUE | K58: FALSE | L58: FALSE | M58: FALSE | N58: TRUE | O58: FALSE | P58: FALSE | Q58: COMPLETED | R58: COMPLETED | S58: COMPLETED | T58: COMPLETED | U58: COMPLETED | V58: COMPLETED | W58: COMPLETED
A59: 51 | B59: 900051 | C59: Cardano Youth Ambassadors | D59: COMPLETED | E59: 50000 | F59: 50000 | G59: =E59-F59 -> 0 | H59: bd | I59: F9: Grow Africa, Grow Cardano | J59: TRUE | K59: TRUE | L59: TRUE | M59: TRUE | N59: TRUE | O59: TRUE | P59: TRUE | Q59: TRUE | R59: FALSE | S59: COMPLETED | T59: COMPLETED | U59: COMPLETED | V59: COMPLETED | W59: COMPLETED
A60: 52 | B60: 900052 | C60: CardanoPress, A Plugin for Builders | D60: COMPLETED | E60: 12000 | F60: 12000 | G60: =E60-F60 -> 0 | H60: Peter | I60: F9: Building (on) Blockfrost | J60: FALSE | K60: FALSE | L60: TRUE | M60: COMPLETED | N60: COMPLETED | O60: COMPLETED | P60: COMPLETED | Q60: COMPLETED | R60: COMPLETED | S60: COMPLETED | T60: COMPLETED | U60: COMPLETED | V60: COMPLETED | W60: COMPLETED
A61: 53 | B61: 900053 | C61: CardanoPress: Governance Plugin | D61: COMPLETED | E61: 12000 | F61: 12000 | G61: =E61-F61 -> 0 | H61: Peter | I61: F9: DAOs <3 Cardano | J61: FALSE | K61: FALSE | L61: TRUE | M61: COMPLETED | N61: COMPLETED | O61: COMPLETED | P61: COMPLETED | Q61: COMPLETED | R61: COMPLETED | S61: COMPLETED | T61: COMPLETED | U61: COMPLETED | V61: COMPLETED | W61: COMPLETED
A62: 54 | B62: 900054 | C62: CardanoPress: ISPO Dashboard | D62: COMPLETED | E62: 9600 | F62: 9600 | G62: =E62-F62 -> 0 | H62: Peter | I62: F9: Dapps, Products & Integrations | J62: FALSE | K62: FALSE | L62: TRUE | M62: COMPLETED | N62: COMPLETED | O62: COMPLETED | P62: COMPLETED | Q62: COMPLETED | R62: COMPLETED | S62: COMPLETED | T62: COMPLETED | U62: COMPLETED | V62: COMPLETED | W62: COMPLETED
A63: 55 | B63: 900055 | C63: Carp over-budget + maintenance | D63: COMPLETED | E63: 65000 | F63: 65000 | G63: =E63-F63 -> 0 | H63: Sebastien Guillemot | I63: F9: Developer Ecosystem | J63: TRUE | K63: TRUE | L63: FALSE | M63: COMPLETED | N63: COMPLETED | O63: COMPLETED | P63: COMPLETED | Q63: COMPLETED | R63: COMPLETED | S63: COMPLETED | T63: COMPLETED | U63: COMPLETED | V63: COMPLETED | W63: COMPLETED
A64: 56 | B64: 900056 | C64: Catalyst Campus Train | D64: COMPLETED | E64: 19575 | F64: 19575 | G64: =E64-F64 -> 0 | H64: Mustapha Yakubu | I64: F9: Grow Africa, Grow Cardano | J64: TRUE | K64: TRUE | L64: TRUE | M64: COMPLETED | N64: COMPLETED | O64: COMPLETED | P64: COMPLETED | Q64: COMPLETED | R64: COMPLETED | S64: COMPLETED | T64: COMPLETED | U64: COMPLETED | V64: COMPLETED | W64: COMPLETED
A65: 57 | B65: 900057 | C65: Catalyst Research & Voter Tool | D65: COMPLETED | E65: 34560 | F65: 34560 | G65: =E65-F65 -> 0 | H65: LIDO Nation Foundation | I65: F9: Dapps, Products & Integrations | J65: TRUE | K65: TRUE | L65: FALSE | M65: TRUE | N65: TRUE | O65: COMPLETED | P65: COMPLETED | Q65: COMPLETED | R65: COMPLETED | S65: COMPLETED | T65: COMPLETED | U65: COMPLETED | V65: COMPLETED | W65: COMPLETED
A66: 58 | B66: 900058 | C66: Catalyst SDK dRep support | D66: COMPLETED | E66: 40000 | F66: 40000 | G66: =E66-F66 -> 0 | H66: Sebastien Guillemot | I66: F9: dRep improvement and onboarding | J66: TRUE | K66: TRUE | L66: TRUE | M66: TRUE | N66: FALSE | O66: TRUE | P66: TRUE | Q66: TRUE | R66: FALSE | S66: COMPLETED | T66: COMPLETED | U66: COMPLETED | V66: COMPLETED | W66: COMPLETED
A67: 59 | B67: 900059 | C67: Catalyst Swarm & SingularityNET | D67: COMPLETED | E67: 60400 | F67: 60400 | G67: =E67-F67 -> 0 | H67: Catalyst Swarm | I67: F9: Cross-Chain Collaboration | J67: TRUE | K67: TRUE | L67: FALSE | M67: FALSE | N67: FALSE | O67: COMPLETED | P67: COMPLETED | Q67: COMPLETED | R67: COMPLETED | S67: COMPLETED | T67: COMPLETED | U67: COMPLETED | V67: COMPLETED | W67: COMPLETED
A68: 60 | B68: 900060 | C68: Catalyst Swarm DAO Tools | D68: COMPLETED | E68: 73600 | F68: 73600 | G68: =E68-F68 -> 0 | H68: Catalyst Swarm | I68: F9: DAOs <3 Cardano | J68: TRUE | K68: TRUE | L68: FALSE | M68: COMPLETED | N68: COMPLETED | O68: COMPLETED | P68: COMPLETED | Q68: COMPLETED | R68: COMPLETED | S68: COMPLETED | T68: COMPLETED | U68: COMPLETED | V68: COMPLETED | W68: COMPLETED
A69: 61 | B69: 900061 | C69: Catalyst tournament | D69: COMPLETED | E69: 5000 | F69: 5000 | G69: =E69-F69 -> 0 | H69: Benji | I69: F9: Challenge & Scouted for Students🎓 | J69: TRUE | K69: FALSE | L69: FALSE | M69: TRUE | N69: TRUE | O69: TRUE | P69: FALSE | Q69: FALSE | R69: COMPLETED | S69: COMPLETED | T69: COMPLETED | U69: COMPLETED | V69: COMPLETED | W69: COMPLETED
A70: 62 | B70: 900062 | C70: CEVI - INFO HUB FOR VN (EN) | D70: COMPLETED | E70: 10240 | F70: 10240 | G70: =E70-F70 -> 0 | H70: Cardano Ecosystem Hub in Viet Nam | I70: F9: Grow East Asia, Grow Cardano | J70: TRUE | K70: TRUE | L70: TRUE | M70: COMPLETED | N70: COMPLETED | O70: COMPLETED | P70: COMPLETED | Q70: COMPLETED | R70: COMPLETED | S70: COMPLETED | T70: COMPLETED | U70: COMPLETED | V70: COMPLETED | W70: COMPLETED
A71: 63 | B71: 900063 | C71: cexplorer.io - cardano explorer | D71: COMPLETED | E71: 3000 | F71: 3000 | G71: =E71-F71 -> 0 | H71: ADApools.org | I71: F9: Developer Ecosystem | J71: FALSE | K71: FALSE | L71: FALSE | M71: COMPLETED | N71: COMPLETED | O71: COMPLETED | P71: COMPLETED | Q71: COMPLETED | R71: COMPLETED | S71: COMPLETED | T71: COMPLETED | U71: COMPLETED | V71: COMPLETED | W71: COMPLETED
A72: 64 | B72: 900064 | C72: China Info Hub Continued | D72: COMPLETED | E72: 13527 | F72: 13527 | G72: =E72-F72 -> 0 | H72: Bullish Dumpling | I72: F9: Grow East Asia, Grow Cardano | J72: TRUE | K72: TRUE | L72: FALSE | M72: COMPLETED | N72: COMPLETED | O72: COMPLETED | P72: COMPLETED | Q72: COMPLETED | R72: COMPLETED | S72: COMPLETED | T72: COMPLETED | U72: COMPLETED | V72: COMPLETED | W72: COMPLETED
A73: 65 | B73: 900065 | C73: cip25 (NFT) Rust & WASM library | D73: COMPLETED | E73: 7000 | F73: 7000 | G73: =E73-F73 -> 0 | H73: Sebastien Guillemot | I73: F9: Developer Ecosystem | J73: TRUE | K73: TRUE | L73: TRUE | M73: COMPLETED | N73: COMPLETED | O73: COMPLETED | P73: COMPLETED | Q73: COMPLETED | R73: COMPLETED | S73: COMPLETED | T73: COMPLETED | U73: COMPLETED | V73: COMPLETED | W73: COMPLETED
A74: 66 | B74: 900066 | C74: Clarity DAO Infrastructure | D74: COMPLETED | E74: 99200 | F74: 99200 | G74: =E74-F74 -> 0 | H74: Clear Contracts | I74: F9: DAOs <3 Cardano | J74: FALSE | K74: TRUE | L74: TRUE | M74: TRUE | N74: TRUE | O74: FALSE | P74: FALSE | Q74: FALSE | R74: COMPLETED | S74: COMPLETED | T74: COMPLETED | U74: COMPLETED | V74: COMPLETED | W74: COMPLETED
A75: 67 | B75: 900067 | C75: CNFT Alliance: Japanese Community! | D75: COMPLETED | E75: 7500 | F75: 7500 | G75: =E75-F75 -> 0 | H75: Conward | I75: F9: Grow East Asia, Grow Cardano | J75: TRUE | K75: FALSE | L75: FALSE | M75: FALSE | N75: FALSE | O75: COMPLETED | P75: COMPLETED | Q75: COMPLETED | R75: COMPLETED | S75: COMPLETED | T75: COMPLETED | U75: COMPLETED | V75: COMPLETED | W75: COMPLETED
A76: 68 | B76: 900068 | C76: CNFT Community in Asian Community | D76: COMPLETED | E76: 31500 | F76: 31500 | G76: =E76-F76 -> 0 | H76: yunya | I76: F9: Grow East Asia, Grow Cardano | J76: TRUE | K76: FALSE | L76: TRUE | M76: TRUE | N76: TRUE | O76: TRUE | P76: FALSE | Q76: FALSE | R76: COMPLETED | S76: COMPLETED | T76: COMPLETED | U76: COMPLETED | V76: COMPLETED | W76: COMPLETED
A77: 69 | B77: 900069 | C77: Community CIP Editor: 1 year budget | D77: COMPLETED | E77: 19200 | F77: 19200 | G77: =E77-F77 -> 0 | H77: Robert Phair | I77: F9: The Great Migration (from Ethereum) | J77: TRUE | K77: FALSE | L77: TRUE | M77: TRUE | N77: TRUE | O77: TRUE | P77: TRUE | Q77: TRUE | R77: TRUE | S77: TRUE | T77: COMPLETED | U77: COMPLETED | V77: COMPLETED | W77: COMPLETED
A78: 70 | B78: 900070 | C78: Community Cyber Security Support | D78: COMPLETED | E78: 120000 | F78: 120000 | G78: =E78-F78 -> 0 | H78: woodkm | I78: F9: Dapps, Products & Integrations | J78: TRUE | K78: TRUE | L78: TRUE | M78: TRUE | N78: TRUE | O78: TRUE | P78: TRUE | Q78: TRUE | R78: TRUE | S78: TRUE | T78: TRUE | U78: FALSE | V78: FALSE | W78: COMPLETED
A79: 71 | B79: 900071 | C79: Connecting Asian Voter and Proposer | D79: COMPLETED | E79: 15000 | F79: 15000 | G79: =E79-F79 -> 0 | H79: Eastern Townhall | I79: F9: Grow East Asia, Grow Cardano | J79: TRUE | K79: FALSE | L79: FALSE | M79: FALSE | N79: FALSE | O79: FALSE | P79: FALSE | Q79: FALSE | R79: COMPLETED | S79: COMPLETED | T79: COMPLETED | U79: COMPLETED | V79: COMPLETED | W79: COMPLETED
A80: 72 | B80: 900072 | C80: Connecting Tabletop Games & Cardano | D80: DID NOT FINISH | E80: 52500 | F80: 35000 | G80: =E80-F80 -> 17500 | H80: GAIA Stake Pool | I80: F9: Dapps, Products & Integrations | J80: TRUE | K80: FALSE | L80: FALSE | M80: FALSE | N80: TRUE | O80: FALSE | P80: FALSE | Q80: TRUE | R80: FALSE | S80: TRUE | T80: FALSE | U80: FALSE | V80: FALSE | W80: FALSE
A81: 73 | B81: 900073 | C81: Courses & Education Crypto MKTPLACE | D81: COMPLETED | E81: 39100 | F81: 39100 | G81: =E81-F81 -> 0 | H81: Otávio (Cardano Feed) | I81: F9: Dapps, Products & Integrations | J81: TRUE | K81: FALSE | L81: FALSE | M81: FALSE | N81: FALSE | O81: FALSE | P81: FALSE | Q81: COMPLETED | R81: COMPLETED | S81: COMPLETED | T81: COMPLETED | U81: COMPLETED | V81: COMPLETED | W81: COMPLETED
A82: 74 | B82: 900074 | C82: Cross-Chain Fake NFT Protection | D82: COMPLETED | E82: 51250 | F82: 51250 | G82: =E82-F82 -> 0 | H82: brerrabbit3 | I82: F9: The Great Migration (from Ethereum) | J82: TRUE | K82: TRUE | L82: COMPLETED | M82: COMPLETED | N82: COMPLETED | O82: COMPLETED | P82: COMPLETED | Q82: COMPLETED | R82: COMPLETED | S82: COMPLETED | T82: COMPLETED | U82: COMPLETED | V82: COMPLETED | W82: COMPLETED
A83: 75 | B83: 900075 | C83: DADF - Disruptive Comm. Application | D83: COMPLETED | E83: 100000 | F83: 100000 | G83: =E83-F83 -> 0 | H83: Wolfram Blockchain Labs | I83: F9: Dapps, Products & Integrations | J83: FALSE | K83: TRUE | L83: TRUE | M83: TRUE | N83: TRUE | O83: COMPLETED | P83: COMPLETED | Q83: COMPLETED | R83: COMPLETED | S83: COMPLETED | T83: COMPLETED | U83: COMPLETED | V83: COMPLETED | W83: COMPLETED
A84: 76 | B84: 900076 | C84: Daedalus Turbo - 10x Quicker Sync | D84: COMPLETED | E84: 759000 | F84: 759000 | G84: =E84-F84 -> 0 | H84: Alex Sierkov | I84: F9: Dapps, Products & Integrations | J84: FALSE | K84: FALSE | L84: TRUE | M84: TRUE | N84: TRUE | O84: TRUE | P84: FALSE | Q84: TRUE | R84: FALSE | S84: FALSE | T84: FALSE | U84: TRUE | V84: FALSE | W84: TRUE
A85: 77 | B85: 900077 | C85: DAO-NET: Small Developer Funding | D85: DID NOT FINISH | E85: 30000 | F85: 5000 | G85: =E85-F85 -> 25000 | H85: DAO Coders | I85: F9: Developer Ecosystem | J85: FALSE | K85: FALSE | L85: FALSE | M85: FALSE | N85: FALSE | O85: FALSE | P85: FALSE | Q85: FALSE | R85: FALSE | S85: FALSE | T85: FALSE | U85: FALSE | V85: FALSE | W85: FALSE
A86: 78 | B86: 900078 | C86: DCOne Crypto | D86: COMPLETED | E86: 30300 | F86: 30300 | G86: =E86-F86 -> 0 | H86: dconecrypto.finance | I86: F9: Dapps, Products & Integrations | J86: TRUE | K86: TRUE | L86: TRUE | M86: TRUE | N86: TRUE | O86: COMPLETED | P86: COMPLETED | Q86: COMPLETED | R86: COMPLETED | S86: COMPLETED | T86: COMPLETED | U86: COMPLETED | V86: COMPLETED | W86: COMPLETED
A87: 79 | B87: 900079 | C87: dcSpark (the company iteslf) | D87: COMPLETED | E87: 400000 | F87: 400000 | G87: =E87-F87 -> 0 | H87: Sebastien Guillemot | I87: F9: Dapps, Products & Integrations | J87: TRUE | K87: FALSE | L87: TRUE | M87: TRUE | N87: FALSE | O87: TRUE | P87: FALSE | Q87: FALSE | R87: FALSE | S87: FALSE | T87: FALSE | U87: FALSE | V87: FALSE | W87: FALSE
A88: 80 | B88: 900080 | C88: Decentralized Escrow for Remote Job | D88: COMPLETED | E88: 54400 | F88: 54400 | G88: =E88-F88 -> 0 | H88: Seira Yun Socious.io | I88: F9: Developer Ecosystem | J88: TRUE | K88: TRUE | L88: TRUE | M88: TRUE | N88: TRUE | O88: TRUE | P88: FALSE | Q88: COMPLETED | R88: COMPLETED | S88: COMPLETED | T88: COMPLETED | U88: COMPLETED | V88: COMPLETED | W88: COMPLETED
A89: 81 | B89: 900081 | C89: Decentralized Social Intelligence | D89: COMPLETED | E89: 200000 | F89: 200000 | G89: =E89-F89 -> 0 | H89: pres | I89: F9: Dapps, Products & Integrations | J89: TRUE | K89: TRUE | L89: TRUE | M89: TRUE | N89: TRUE | O89: TRUE | P89: FALSE | Q89: FALSE | R89: TRUE | S89: FALSE | T89: COMPLETED | U89: COMPLETED | V89: COMPLETED | W89: COMPLETED
A90: 82 | B90: 900082 | C90: Discord Social Credential | D90: COMPLETED | E90: 8425 | F90: 8425 | G90: =E90-F90 -> 0 | H90: RootsID | I90: F9: Dapps, Products & Integrations | J90: TRUE | K90: TRUE | L90: FALSE | M90: COMPLETED | N90: COMPLETED | O90: COMPLETED | P90: COMPLETED | Q90: COMPLETED | R90: COMPLETED | S90: COMPLETED | T90: COMPLETED | U90: COMPLETED | V90: COMPLETED | W90: COMPLETED
A91: 83 | B91: 900083 | C91: Dolos: Cardano â€śData Nodeâ€ť | D91: COMPLETED | E91: 75680 | F91: 75680 | G91: =E91-F91 -> 0 | H91: Santiago Carmuega | I91: F9: Developer Ecosystem | J91: TRUE | K91: TRUE | L91: TRUE | M91: FALSE | N91: FALSE | O91: FALSE | P91: FALSE | Q91: FALSE | R91: TRUE | S91: FALSE | T91: TRUE | U91: TRUE | V91: COMPLETED | W91: COMPLETED
A92: 84 | B92: 900084 | C92: dRep Education Book Club | D92: COMPLETED | E92: 3750 | F92: 3750 | G92: =E92-F92 -> 0 | H92: Nori Nishigaya | I92: F9: dRep improvement and onboarding | J92: FALSE | K92: TRUE | L92: TRUE | M92: TRUE | N92: TRUE | O92: TRUE | P92: FALSE | Q92: FALSE | R92: FALSE | S92: FALSE | T92: FALSE | U92: COMPLETED | V92: COMPLETED | W92: COMPLETED
A93: 85 | B93: 900085 | C93: dRep Interview Channel | D93: COMPLETED | E93: 16800 | F93: 16800 | G93: =E93-F93 -> 0 | H93: VCT | I93: F9: dRep improvement and onboarding | J93: TRUE | K93: TRUE | L93: TRUE | M93: TRUE | N93: TRUE | O93: COMPLETED | P93: COMPLETED | Q93: COMPLETED | R93: COMPLETED | S93: COMPLETED | T93: COMPLETED | U93: COMPLETED | V93: COMPLETED | W93: COMPLETED
A94: 86 | B94: 900086 | C94: dRep tool for non-English speakers | D94: COMPLETED | E94: 26500 | F94: 26500 | G94: =E94-F94 -> 0 | H94: ProSkills39 | I94: F9: dRep improvement and onboarding | J94: FALSE | K94: FALSE | L94: TRUE | M94: FALSE | N94: FALSE | O94: FALSE | P94: FALSE | Q94: FALSE | R94: FALSE | S94: FALSE | T94: COMPLETED | U94: COMPLETED | V94: COMPLETED | W94: COMPLETED
A95: 87 | B95: 900087 | C95: DripDropz Cardano Mainstreet Suite | D95: COMPLETED | E95: 326000 | F95: 326000 | G95: =E95-F95 -> 0 | H95: Drip Dropz | I95: F9: Dapps, Products & Integrations | J95: TRUE | K95: TRUE | L95: TRUE | M95: TRUE | N95: TRUE | O95: FALSE | P95: TRUE | Q95: FALSE | R95: FALSE | S95: TRUE | T95: FALSE | U95: FALSE | V95: FALSE | W95: FALSE
A96: 88 | B96: 900088 | C96: DripDropz Open Source Voting Tool | D96: COMPLETED | E96: 150000 | F96: 150000 | G96: =E96-F96 -> 0 | H96: Drip Dropz | I96: F9: Dapps, Products & Integrations | J96: TRUE | K96: TRUE | L96: TRUE | M96: FALSE | N96: FALSE | O96: FALSE | P96: TRUE | Q96: FALSE | R96: FALSE | S96: COMPLETED | T96: COMPLETED | U96: COMPLETED | V96: COMPLETED | W96: COMPLETED
A97: 89 | B97: 900089 | C97: Driving Adoption via Travel D'Apps | D97: COMPLETED | E97: 70000 | F97: 70000.75 | G97: =E97-F97 -> -0.75 | H97: Jaymeon Jones | I97: F9: Dapps, Products & Integrations | J97: TRUE | K97: TRUE | L97: TRUE | M97: TRUE | N97: COMPLETED | O97: COMPLETED | P97: COMPLETED | Q97: COMPLETED | R97: COMPLETED | S97: COMPLETED | T97: COMPLETED | U97: COMPLETED | V97: COMPLETED | W97: COMPLETED
A98: 90 | B98: 900090 | C98: đź’§ Democracy Means Everyone is dRep | D98: DID NOT FINISH | E98: 100 | F98: 0 | G98: =E98-F98 -> 100 | H98: JO8N | I98: F9: dRep improvement and onboarding | J98: FALSE | K98: FALSE | L98: FALSE | M98: FALSE | N98: FALSE | O98: FALSE | P98: FALSE | Q98: FALSE | R98: FALSE | S98: FALSE | T98: FALSE | U98: FALSE | V98: FALSE | W98: FALSE
A99: 91 | B99: 900091 | C99: Eastern Hemisphere dRep TownHall | D99: COMPLETED | E99: 23060 | F99: 23060 | G99: =E99-F99 -> 0 | H99: Eastern Townhall | I99: F9: dRep improvement and onboarding | J99: TRUE | K99: FALSE | L99: FALSE | M99: FALSE | N99: FALSE | O99: FALSE | P99: FALSE | Q99: FALSE | R99: FALSE | S99: FALSE | T99: FALSE | U99: FALSE | V99: FALSE | W99: FALSE
A100: 92 | B100: 900092 | C100: Eastern Town Hall Team Operation | D100: COMPLETED | E100: 22500 | F100: 22500 | G100: =E100-F100 -> 0 | H100: Eastern Townhall | I100: F9: Grow East Asia, Grow Cardano | J100: TRUE | K100: FALSE | L100: FALSE | M100: TRUE | N100: FALSE | O100: FALSE | P100: FALSE | Q100: FALSE | R100: COMPLETED | S100: COMPLETED | T100: COMPLETED | U100: COMPLETED | V100: COMPLETED | W100: COMPLETED
A101: 93 | B101: 900093 | C101: Education impact and monetization | D101: PENDING | F101: 0 | G101: =E101-F101 -> 0 | H101: Gustavo Pugliese | I101: F9: Catalyst Natives X Cardashift: Demonstrating and monetizing impact | J101: TRUE | K101: FALSE | L101: TRUE | M101: FALSE | N101: FALSE | O101: FALSE | P101: FALSE | Q101: FALSE | R101: FALSE | S101: FALSE | T101: FALSE | U101: FALSE | V101: FALSE | W101: FALSE
A102: 94 | B102: 900094 | C102: e-Learning DAO,Revenue share policy | D102: PENDING | F102: 0 | G102: =E102-F102 -> 0 | H102: altimario | I102: F9: Catalyst Natives X Cardashift: Demonstrating and monetizing impact | J102: FALSE | K102: FALSE | L102: FALSE | M102: FALSE | N102: FALSE | O102: FALSE | P102: FALSE | Q102: FALSE | R102: FALSE | S102: FALSE | T102: FALSE | U102: FALSE | V102: FALSE | W102: FALSE
...

Sheet Fund8 Reporting
A1: THIS DOCUMENT WILL BE DEPRECATED SOON If you need support please submit a ticket via zendesk.
A4: 115 | C4: FUND8 | E4: Funding ($)
A5: # | B5: ID | C5: Project Name | D5: Project Status | E5: Requested | F5: Distributed to date | G5: Remaining | H5: Primary Proposer - Guarantor | I5: Challenge | J5: Progress Report | K5: Progress Report | L5: Progress Report | M5: Progress Report | N5: Progress Report | O5: Progress Report | P5: Progress Report | Q5: Progress Report | R5: Progress Report | S5: Progress Report | T5: Progress Report | U5: Progress Report | V5: Progress Report | W5: Progress Report | X5: Progress Report | Y5: Progress Report | Z5: Progress Report | AA5: Progress Report | AB5: Progress Report | AC5: Progress Report
E6: =SUM(E9:E375) -> 12799901 | F6: =SUM(F9:F375) -> 12321368 | G6: =SUM(G9:G375) -> 478533.33 | J6: May '22 | K6: June '22 | L6: July '22 | M6: August '22 | N6: September '22 | O6: October '22 | P6: November '22 | Q6: December '22 | R6: January '23 | S6: February '23 | T6: March '23 | U6: April '23 | V6: May '23 | W6: June '23 | X6: July '23 | Y6: August '23 | Z6: September '23 | AA6: October '23 | AB6: November '23 | AC6: December '23
C7: Reporting % | I7: =Average(J7:R7) -> 0.66460313 | J7: =J8/($C$8 - (COUNTIF(J9:J375, "COMPLETED")+COUNTIF(J9:J375, ""))) -> 0.91008174 | K7: =K8/($C$8 - (COUNTIF(K9:K375, "COMPLETED")+COUNTIF(K9:K375, ""))) -> 0.91436464 | L7: =L8/($C$8 - (COUNTIF(L9:L375, "COMPLETED")+COUNTIF(L9:L375, ""))) -> 0.86158192 | M7: =M8/($C$8 - (COUNTIF(M9:M375, "COMPLETED")+COUNTIF(M9:M375, ""))) -> 0.80060423 | N7: =N8/($C$8 - (COUNTIF(N9:N375, "COMPLETED")+COUNTIF(N9:N375, ""))) -> 0.72258065 | O7: =O8/($C$8 - (COUNTIF(O9:O375, "COMPLETED")+COUNTIF(O9:O375, ""))) -> 0.64948454 | P7: =P8/($C$8 - (COUNTIF(P9:P375, "COMPLETED")+COUNTIF(P9:P375, ""))) -> 0.46067416 | Q7: =Q8/($C$8 - (COUNTIF(Q9:Q375, "COMPLETED")+COUNTIF(Q9:Q375, ""))) -> 0.30188679 | ... AC7: =AC8/($C$8 - (COUNTIF(AC9:AC375, "COMPLETED")+COUNTIF(AC9:AC375, ""))) -> 0.039370079
C8: =Counta(C9:C375) -> 367 | J8: =COUNTIF(J9:J375, TRUE) -> 334 | K8: =COUNTIF(K9:K375, TRUE) -> 331 | L8: =COUNTIF(L9:L375, TRUE) -> 305 | M8: =COUNTIF(M9:M375, TRUE) -> 265 | N8: =COUNTIF(N9:N375, TRUE) -> 224 | O8: =COUNTIF(O9:O375, TRUE) -> 189 | P8: =COUNTIF(P9:P375, TRUE) -> 123 | Q8: =COUNTIF(Q9:Q375, TRUE) -> 80 | ... AC8: =COUNTIF(AC9:AC375, TRUE) -> 5
A9: 1 | B9: 800001 | C9: .NET Blazor Web wallet Support | D9: COMPLETED | E9: 2800 | F9: 2800 | G9: =E9-F9 -> 0 | H9: Jacques Bosch | I9: F8: Open Source Development Ecosystem | J9: TRUE | K9: TRUE | L9: TRUE | M9: COMPLETED | S9: COMPLETED | T9: COMPLETED | U9: COMPLETED | V9: COMPLETED | W9: COMPLETED | X9: COMPLETED | Y9: COMPLETED | Z9: COMPLETED | AA9: COMPLETED | AB9: COMPLETED | AC9: COMPLETED
A10: 2 | B10: 800002 | C10: .NET CardanoSharp Â– Deserialization | D10: COMPLETED | E10: 3700 | F10: 3700 | G10: =E10-F10 -> 0 | H10: Jacques Bosch | I10: F8: Open Source Development Ecosystem | J10: TRUE | K10: TRUE | L10: COMPLETED | S10: COMPLETED | T10: COMPLETED | U10: COMPLETED | V10: COMPLETED | W10: COMPLETED | X10: COMPLETED | Y10: COMPLETED | Z10: COMPLETED | AA10: COMPLETED | AB10: COMPLETED | AC10: COMPLETED
A11: 3 | B11: 800003 | C11: 🔥Regulation-as-code for DApps | D11: COMPLETED | E11: 111100 | F11: 111100 | G11: =E11-F11 -> 0 | H11: jo allum | I11: F8: Nation Building Dapps | J11: TRUE | K11: TRUE | L11: TRUE | M11: TRUE | N11: TRUE | O11: TRUE | P11: TRUE | Q11: FALSE | R11: FALSE | S11: FALSE | T11: FALSE | U11: FALSE | V11: FALSE | W11: FALSE | X11: FALSE | Y11: FALSE | Z11: FALSE | AA11: FALSE | AB11: FALSE | AC11: FALSE
A12: 4 | B12: 800004 | C12: $272Bn Carbon Credits on Cardano | D12: DID NOT FINISH | E12: 59000 | F12: 49167 | G12: =E12-F12 -> 9833 | H12: Nik Karagiorgos | I12: F8: Business Solutions (B2B & B2C) | J12: TRUE | K12: TRUE | L12: TRUE | M12: TRUE | N12: TRUE | O12: TRUE | P12: FALSE | Q12: TRUE | R12: FALSE | S12: FALSE | T12: FALSE | U12: FALSE | V12: FALSE | W12: FALSE | X12: FALSE | Y12: FALSE | Z12: FALSE | AA12: FALSE | AB12: FALSE | AC12: FALSE
A13: 5 | B13: 800005 | C13: 1,000+ projects on Interactive Map | D13: COMPLETED | E13: 28800 | F13: 28800 | G13: =E13-F13 -> 0 | H13: Otávio (Cardano Feed) | I13: F8: Business Solutions (B2B & B2C) | J13: TRUE | K13: TRUE | L13: TRUE | M13: TRUE | N13: COMPLETED | S13: COMPLETED | T13: COMPLETED | U13: COMPLETED | V13: COMPLETED | W13: COMPLETED | X13: COMPLETED | Y13: COMPLETED | Z13: COMPLETED | AA13: COMPLETED | AB13: COMPLETED | AC13: COMPLETED
A14: 6 | B14: 800006 | C14: 21st century Agri supply chain | D14: COMPLETED | E14: 22500 | F14: 22500 | G14: =E14-F14 -> 0 | H14: Yoram | I14: F8: Nation Building Dapps | J14: TRUE | K14: TRUE | L14: TRUE | M14: COMPLETED | S14: COMPLETED | T14: COMPLETED | U14: COMPLETED | V14: COMPLETED | W14: COMPLETED | X14: COMPLETED | Y14: COMPLETED | Z14: COMPLETED | AA14: COMPLETED | AB14: COMPLETED | AC14: COMPLETED
A15: 7 | B15: 800007 | C15: A People's Cadastre in Mozambique ✊ | D15: COMPLETED | E15: 98450 | F15: 98450 | G15: =E15-F15 -> 0 | H15: Peter Van Garderen | I15: F8: Nation Building Dapps | J15: TRUE | K15: TRUE | L15: TRUE | M15: FALSE | N15: TRUE | O15: TRUE | P15: FALSE | Q15: FALSE | R15: FALSE | S15: FALSE | T15: FALSE | U15: FALSE | V15: FALSE | W15: FALSE | X15: FALSE | Y15: FALSE | Z15: FALSE | AA15: FALSE | AB15: FALSE | AC15: FALSE
A16: 8 | B16: 800008 | C16: A Scalable Service For NFT Utility | D16: COMPLETED | E16: 40000 | F16: 40000 | G16: =E16-F16 -> 0 | H16: Abraham Hazbun | I16: F8: Cardano scaling solutions | J16: TRUE | K16: TRUE | L16: TRUE | M16: TRUE | N16: TRUE | O16: FALSE | P16: FALSE | Q16: FALSE | R16: FALSE | S16: FALSE | T16: FALSE | U16: FALSE | V16: COMPLETED | W16: COMPLETED | X16: COMPLETED | Y16: COMPLETED | Z16: COMPLETED | AA16: COMPLETED | AB16: COMPLETED | AC16: COMPLETED
A17: 9 | B17: 800009 | C17: ABC of Governance | D17: COMPLETED | E17: 10135 | F17: 10135 | G17: =E17-F17 -> 0 | H17: Stephen Whitenstall | I17: F8: Miscellaneous Challenge | J17: TRUE | K17: FALSE | L17: TRUE | M17: TRUE | N17: TRUE | O17: FALSE | P17: FALSE | Q17: FALSE | R17: FALSE | S17: TRUE | T17: FALSE | U17: FALSE | V17: FALSE | W17: TRUE | X17: TRUE | Y17: FALSE | Z17: FALSE | AA17: TRUE | AB17: TRUE | AC17: FALSE
A18: 10 | B18: 800010 | C18: ADA Pay Plugin - Wordpress/Laravel | D18: COMPLETED | E18: 35200 | F18: 35200 | G18: =E18-F18 -> 0 | H18: LIDO Nation Foundation | I18: F8: Open Source Development Ecosystem | J18: TRUE | K18: TRUE | L18: TRUE | M18: TRUE | N18: FALSE | O18: TRUE | P18: TRUE | Q18: FALSE | R18: FALSE | S18: FALSE | T18: FALSE | U18: FALSE | V18: FALSE | W18: FALSE | X18: FALSE | Y18: FALSE | Z18: FALSE | AA18: FALSE | AB18: TRUE | AC18: TRUE
A19: 11 | B19: 800011 | C19: ADA Scam Alert - Info & Protection | D19: COMPLETED | E19: 45600 | F19: 45600 | G19: =E19-F19 -> 0 | H19: Otávio (Cardano Feed) | I19: F8: Cardano scaling solutions | J19: TRUE | K19: TRUE | L19: TRUE | M19: TRUE | N19: TRUE | O19: TRUE | P19: FALSE | Q19: TRUE | R19: COMPLETED | S19: COMPLETED | T19: COMPLETED | U19: COMPLETED | V19: COMPLETED | W19: COMPLETED | X19: COMPLETED | Y19: COMPLETED | Z19: COMPLETED | AA19: COMPLETED | AB19: COMPLETED | AC19: COMPLETED
A20: 12 | B20: 800012 | C20: ADA-DESO Templates to Test dApps | D20: COMPLETED | E20: 9250 | F20: 9250 | G20: =E20-F20 -> 0 | H20: Gonzalo Camps | I20: F8: DApps and Integrations | J20: TRUE | K20: TRUE | L20: TRUE | M20: TRUE | N20: TRUE | O20: TRUE | P20: TRUE | Q20: FALSE | R20: TRUE | S20: FALSE | T20: FALSE | U20: TRUE | V20: TRUE | W20: TRUE | X20: COMPLETED | Y20: COMPLETED | Z20: COMPLETED | AA20: COMPLETED | AB20: COMPLETED | AC20: COMPLETED
A21: 13 | B21: 800013 | C21: ADA-DESO Templates to Test Projects | D21: COMPLETED | E21: 19850 | F21: 19850 | G21: =E21-F21 -> 0 | H21: Gonzalo Camps | I21: F8: Cross-Chain Collaboration | J21: TRUE | K21: TRUE | L21: TRUE | M21: TRUE | N21: TRUE | O21: TRUE | P21: TRUE | Q21: FALSE | R21: TRUE | S21: FALSE | T21: FALSE | U21: TRUE | V21: TRUE | W21: TRUE | X21: COMPLETED | Y21: COMPLETED | Z21: COMPLETED | AA21: COMPLETED | AB21: COMPLETED | AC21: COMPLETED
A22: 14 | B22: 800014 | C22: Ada's Place - A Medium Publication | D22: COMPLETED | E22: 33999 | F22: 33999 | G22: =E22-F22 -> 0 | H22: immortaltype | I22: F8: Cardano scaling solutions | J22: TRUE | K22: TRUE | L22: TRUE | M22: COMPLETED | S22: COMPLETED | T22: COMPLETED | U22: COMPLETED | V22: COMPLETED | W22: COMPLETED | X22: COMPLETED | Y22: COMPLETED | Z22: COMPLETED | AA22: COMPLETED | AB22: COMPLETED | AC22: COMPLETED
A23: 15 | B23: 800015 | C23: Adaglass Data Intelligence Platform | D23: COMPLETED | E23: 74000 | F23: 74000 | G23: =E23-F23 -> 0 | H23: despas.damien | I23: F8: Business Solutions (B2B & B2C) | J23: TRUE | K23: TRUE | L23: TRUE | M23: TRUE | N23: TRUE | O23: TRUE | P23: TRUE | Q23: TRUE | R23: TRUE | S23: TRUE | T23: FALSE | U23: FALSE | V23: FALSE | W23: FALSE | X23: FALSE | Y23: FALSE | Z23: FALSE | AA23: FALSE | AB23: FALSE | AC23: FALSE
A24: 16 | B24: 800016 | C24: ADAO Summon: DAO Incubator | D24: COMPLETED | E24: 69420 | F24: 69420 | G24: =E24-F24 -> 0 | H24: Adaminnow | I24: F8: Open Source Development Ecosystem | J24: TRUE | K24: TRUE | L24: TRUE | M24: COMPLETED | S24: COMPLETED | T24: COMPLETED | U24: COMPLETED | V24: COMPLETED | W24: COMPLETED | X24: COMPLETED | Y24: COMPLETED | Z24: COMPLETED | AA24: COMPLETED | AB24: COMPLETED | AC24: COMPLETED
A25: 17 | B25: 800017 | C25: ADAO-Multi-sig Wallet Web Interface | D25: COMPLETED | E25: 10000 | F25: 10000 | G25: =E25-F25 -> 0 | H25: Adaminnow | I25: F8: Open Source Development Ecosystem | J25: TRUE | K25: FALSE | L25: FALSE | M25: FALSE | N25: FALSE | O25: FALSE | P25: FALSE | Q25: FALSE | R25: FALSE | S25: FALSE | T25: FALSE | U25: FALSE | V25: FALSE | W25: FALSE | X25: COMPLETED | Y25: COMPLETED | Z25: COMPLETED | AA25: COMPLETED | AB25: COMPLETED | AC25: COMPLETED
A26: 18 | B26: 800018 | C26: AdaQuest - Concept Phase 2 | D26: COMPLETED | E26: 23000 | F26: 23000 | G26: =E26-F26 -> 0 | H26: Marcin Kugla | I26: F8: Gamers On - Chained | J26: TRUE | K26: TRUE | L26: TRUE | M26: TRUE | N26: COMPLETED | S26: COMPLETED | T26: COMPLETED | U26: COMPLETED | V26: COMPLETED | W26: COMPLETED | X26: COMPLETED | Y26: COMPLETED | Z26: COMPLETED | AA26: COMPLETED | AB26: COMPLETED | AC26: COMPLETED
A27: 19 | B27: 800019 | C27: AdaQuest PROTOTYPE Phase 2 | D27: COMPLETED | E27: 38000 | F27: 38000 | G27: =E27-F27 -> 0 | H27: Marcin Kugla | I27: F8: Gamers On - Chained | J27: TRUE | K27: TRUE | L27: TRUE | M27: TRUE | N27: FALSE | O27: TRUE | P27: TRUE | Q27: FALSE | R27: FALSE | S27: FALSE | T27: FALSE | U27: COMPLETED | V27: COMPLETED | W27: COMPLETED | X27: COMPLETED | Y27: COMPLETED | Z27: COMPLETED | AA27: COMPLETED | AB27: COMPLETED | AC27: COMPLETED
A28: 20 | B28: 800020 | C28: AdaQuest PVE Quests & Stories | D28: COMPLETED | E28: 35000 | F28: 35000 | G28: =E28-F28 -> 0 | H28: Marcin Kugla | I28: F8: Gamers On - Chained | J28: TRUE | K28: TRUE | L28: TRUE | M28: TRUE | N28: FALSE | O28: TRUE | P28: TRUE | Q28: FALSE | R28: FALSE | S28: FALSE | T28: FALSE | U28: FALSE | V28: FALSE | W28: FALSE | X28: FALSE | Y28: FALSE | Z28: COMPLETED | AA28: COMPLETED | AB28: COMPLETED | AC28: COMPLETED
A29: 21 | B29: 800021 | C29: Adatar.me for ATOM | D29: DID NOT FINISH | E29: 8000 | F29: 6000 | G29: =E29-F29 -> 2000 | H29: Matthias Sieber | I29: F8: Cross-Chain Collaboration | J29: TRUE | K29: TRUE | L29: TRUE | M29: FALSE | N29: FALSE | O29: FALSE | P29: FALSE | Q29: FALSE | R29: FALSE | S29: FALSE | T29: FALSE | U29: FALSE | V29: FALSE | W29: FALSE | X29: FALSE | Y29: FALSE | Z29: FALSE | AA29: FALSE | AB29: FALSE | AC29: FALSE
A30: 22 | B30: 800022 | C30: Adatar.me for BTC | D30: DID NOT FINISH | E30: 8000 | F30: 6000 | G30: =E30-F30 -> 2000 | H30: Matthias Sieber | I30: F8: Cross-Chain Collaboration | J30: TRUE | K30: TRUE | L30: TRUE | M30: FALSE | N30: FALSE | O30: FALSE | P30: FALSE | Q30: FALSE | R30: FALSE | S30: FALSE | T30: FALSE | U30: FALSE | V30: FALSE | W30: FALSE | X30: FALSE | Y30: FALSE | Z30: FALSE | AA30: FALSE | AB30: FALSE | AC30: FALSE
A31: 23 | B31: 800023 | C31: Adatar.me for XRP | D31: DID NOT FINISH | E31: 8000 | F31: 6000 | G31: =E31-F31 -> 2000 | H31: Matthias Sieber | I31: F8: Cross-Chain Collaboration | J31: TRUE | K31: TRUE | L31: TRUE | M31: FALSE | N31: FALSE | O31: FALSE | P31: FALSE | Q31: FALSE | R31: FALSE | S31: FALSE | T31: FALSE | U31: FALSE | V31: FALSE | W31: FALSE | X31: FALSE | Y31: FALSE | Z31: FALSE | AA31: FALSE | AB31: FALSE | AC31: FALSE
A32: 24 | B32: 800024 | C32: Adatar.me Website Widget | D32: DID NOT FINISH | E32: 12000 | F32: 9000 | G32: =E32-F32 -> 3000 | H32: Victor Corcino | I32: F8: Open Source Development Ecosystem | J32: TRUE | K32: TRUE | L32: TRUE | M32: FALSE | N32: FALSE | O32: FALSE | P32: FALSE | Q32: FALSE | R32: FALSE | S32: FALSE | T32: FALSE | U32: FALSE | V32: FALSE | W32: FALSE | X32: FALSE | Y32: FALSE | Z32: FALSE | AA32: FALSE | AB32: FALSE | AC32: FALSE
A33: 25 | B33: 800025 | C33: Aedou - Realm of Languages | D33: DID NOT FINISH | E33: 57900 | F33: 46320 | G33: =E33-F33 -> 11580 | H33: Educhainment | I33: F8: Gamers On - Chained | J33: TRUE | K33: TRUE | L33: TRUE | M33: TRUE | N33: TRUE | O33: FALSE | P33: FALSE | Q33: FALSE | R33: FALSE | S33: FALSE | T33: FALSE | U33: FALSE | V33: FALSE | W33: FALSE | X33: FALSE | Y33: FALSE | Z33: FALSE | AA33: FALSE | AB33: FALSE | AC33: FALSE
A34: 26 | B34: 800026 | C34: Aedou DIDs prototype | D34: DID NOT FINISH | E34: 8000 | F34: 4000 | G34: =E34-F34 -> 4000 | H34: Educhainment | I34: F8: Accelerate Decentralized Identity | J34: TRUE | K34: FALSE | L34: FALSE | M34: FALSE | N34: FALSE | O34: FALSE | P34: FALSE | Q34: FALSE | R34: FALSE | S34: FALSE | T34: FALSE | U34: FALSE | V34: FALSE | W34: FALSE | X34: FALSE | Y34: FALSE | Z34: FALSE | AA34: FALSE | AB34: FALSE | AC34: FALSE
A35: 27 | B35: 800027 | C35: Africa Anti-counterfeit Marketplace | D35: PENDING | E35: 69000 | F35: 57500 | G35: =E35-F35 -> 11500 | H35: Andrew Chege | I35: F8: Nation Building Dapps | J35: TRUE | K35: TRUE | L35: TRUE | M35: TRUE | N35: FALSE | O35: FALSE | P35: TRUE | Q35: TRUE | R35: FALSE | S35: FALSE | T35: FALSE | U35: FALSE | V35: FALSE | W35: FALSE | X35: FALSE | Y35: FALSE | Z35: FALSE | AA35: FALSE | AB35: FALSE | AC35: FALSE
A36: 28 | B36: 800028 | C36: After Town Hall by Catalyst Swarm | D36: COMPLETED | E36: 22500 | F36: 22500 | G36: =E36-F36 -> 0 | H36: Felix Weber [SWARM] | I36: F8: New Member Onboarding | J36: TRUE | K36: TRUE | L36: FALSE | M36: FALSE | N36: COMPLETED | S36: COMPLETED | T36: COMPLETED | U36: COMPLETED | V36: COMPLETED | W36: COMPLETED | X36: COMPLETED | Y36: COMPLETED | Z36: COMPLETED | AA36: COMPLETED | AB36: COMPLETED | AC36: COMPLETED
A37: 29 | B37: 800029 | C37: Agora: Plutus governance module | D37: COMPLETED | E37: 100000 | F37: 100000 | G37: =E37-F37 -> 0 | H37: Liqwid Labs | I37: F8: Business Solutions (B2B & B2C) | J37: FALSE | K37: TRUE | L37: TRUE | M37: TRUE | N37: TRUE | O37: TRUE | P37: FALSE | Q37: TRUE | R37: FALSE | S37: FALSE | T37: FALSE | U37: FALSE | V37: FALSE | W37: FALSE | X37: FALSE | Y37: FALSE | Z37: FALSE | AA37: FALSE | AB37: FALSE | AC37: FALSE
A38: 30 | B38: 800030 | C38: AI Mentor matching software | D38: COMPLETED | E38: 30000 | F38: 30000 | G38: =E38-F38 -> 0 | H38: dzhuliana | I38: F8: Business Solutions (B2B & B2C) | J38: TRUE | K38: TRUE | L38: TRUE | M38: TRUE | N38: FALSE | O38: TRUE | P38: COMPLETED | S38: COMPLETED | T38: COMPLETED | U38: COMPLETED | V38: COMPLETED | W38: COMPLETED | X38: COMPLETED | Y38: COMPLETED | Z38: COMPLETED | AA38: COMPLETED | AB38: COMPLETED | AC38: COMPLETED
A39: 31 | B39: 800031 | C39: Anonymity/data control ZKT (part 2) | D39: COMPLETED | E39: 84000 | F39: 84000 | G39: =E39-F39 -> 0 | H39: Michiel Van Roey | I39: F8: DApps and Integrations | J39: TRUE | K39: TRUE | L39: TRUE | M39: TRUE | N39: TRUE | O39: TRUE | P39: TRUE | Q39: TRUE | R39: TRUE | S39: TRUE | T39: TRUE | U39: TRUE | V39: TRUE | W39: TRUE | X39: TRUE | Y39: TRUE | Z39: TRUE | AA39: FALSE | AB39: FALSE | AC39: FALSE
A40: 32 | B40: 800032 | C40: App store for Milkomeda | D40: COMPLETED | E40: 20000 | F40: 20000 | G40: =E40-F40 -> 0 | H40: nicoarqueros | I40: F8: Developer Ecosystem | J40: TRUE | K40: FALSE | L40: FALSE | M40: TRUE | N40: TRUE | O40: TRUE | P40: COMPLETED | S40: COMPLETED | T40: COMPLETED | U40: COMPLETED | V40: COMPLETED | W40: COMPLETED | X40: COMPLETED | Y40: COMPLETED | Z40: COMPLETED | AA40: COMPLETED | AB40: COMPLETED | AC40: COMPLETED
A41: 33 | B41: 800033 | C41: Arizona for Cardano Lobby | D41: DID NOT FINISH | E41: 5000 | F41: 3750 | G41: =E41-F41 -> 1250 | H41: jondepinet | I41: F8: Lobbying for favorable legislation | J41: TRUE | K41: TRUE | L41: FALSE | M41: FALSE | N41: FALSE | O41: FALSE | P41: FALSE | Q41: FALSE | R41: FALSE | S41: FALSE | T41: FALSE | U41: FALSE | V41: FALSE | W41: FALSE | X41: FALSE | Y41: FALSE | Z41: FALSE | AA41: FALSE | AB41: FALSE | AC41: FALSE
A42: 34 | B42: 800034 | C42: Artificial Intelligence/ML API DApp | D42: COMPLETED | E42: 89700 | F42: 89700 | G42: =E42-F42 -> 0 | H42: Frank | I42: F8: DApps and Integrations | J42: TRUE | K42: TRUE | L42: TRUE | M42: TRUE | N42: COMPLETED | S42: COMPLETED | T42: COMPLETED | U42: COMPLETED | V42: COMPLETED | W42: COMPLETED | X42: COMPLETED | Y42: COMPLETED | Z42: COMPLETED | AA42: COMPLETED | AB42: COMPLETED | AC42: COMPLETED
A43: 35 | B43: 800035 | C43: Assembly of State Blockchain PAC's | D43: COMPLETED | E43: 5000 | F43: 5000 | G43: =E43-F43 -> 0 | H43: Robb Bedoya DS9 | I43: F8: Lobbying for favorable legislation | J43: TRUE | K43: TRUE | L43: TRUE | M43: TRUE | N43: TRUE | O43: FALSE | P43: FALSE | Q43: FALSE | R43: FALSE | S43: FALSE | T43: FALSE | U43: FALSE | V43: FALSE | W43: FALSE | X43: FALSE | Y43: FALSE | Z43: FALSE | AA43: FALSE | AB43: FALSE | AC43: FALSE
A44: 36 | B44: 800036 | C44: AtalaPRISM hackathon with devillage | D44: COMPLETED | E44: 100000 | F44: 100000 | G44: =E44-F44 -> 0 | H44: kuni | I44: F8: Accelerate Decentralized Identity | J44: TRUE | K44: TRUE | L44: TRUE | M44: TRUE | N44: TRUE | O44: FALSE | P44: FALSE | Q44: FALSE | R44: TRUE | S44: TRUE | T44: TRUE | U44: FALSE | V44: COMPLETED | W44: COMPLETED | X44: COMPLETED | Y44: COMPLETED | Z44: COMPLETED | AA44: COMPLETED | AB44: COMPLETED | AC44: COMPLETED
A45: 37 | B45: 800037 | C45: Auditing African Proposals, By Wada | D45: COMPLETED | E45: 38000 | F45: 38000 | G45: =E45-F45 -> 0 | H45: Wada | I45: F8: Improve and Grow Auditability | J45: TRUE | K45: TRUE | L45: TRUE | M45: TRUE | N45: TRUE | O45: TRUE | P45: TRUE | Q45: FALSE | R45: TRUE | S45: TRUE | T45: FALSE | U45: TRUE | V45: FALSE | W45: COMPLETED | X45: COMPLETED | Y45: COMPLETED | Z45: COMPLETED | AA45: COMPLETED | AB45: COMPLETED | AC45: COMPLETED
A46: 38 | B46: 800038 | C46: Australian University Cardano Talks | D46: DID NOT FINISH | E46: 19040 | F46: 16320 | G46: =E46-F46 -> 2720 | H46: Emerson | I46: F8: Scale-UP Cardano's Community Hubs | J46: TRUE | K46: TRUE | L46: TRUE | M46: TRUE | N46: TRUE | O46: TRUE | P46: TRUE | Q46: TRUE | R46: TRUE | S46: TRUE | T46: TRUE | U46: TRUE | V46: FALSE | W46: FALSE | X46: FALSE | Y46: FALSE | Z46: FALSE | AA46: FALSE | AB46: FALSE | AC46: FALSE
A47: 39 | B47: 800039 | C47: Automate, Educate, Communicate | D47: COMPLETED | E47: 9750 | F47: 9750 | G47: =E47-F47 -> 0 | H47: Stephen Whitenstall | I47: F8: Open Source Development Ecosystem | J47: TRUE | K47: TRUE | L47: TRUE | M47: TRUE | N47: TRUE | O47: TRUE | P47: TRUE | Q47: FALSE | R47: FALSE | S47: TRUE | T47: TRUE | U47: TRUE | V47: TRUE | W47: COMPLETED | X47: COMPLETED | Y47: COMPLETED | Z47: COMPLETED | AA47: COMPLETED | AB47: COMPLETED | AC47: COMPLETED
A48: 40 | B48: 800040 | C48: Automated mentor-matching tool | D48: COMPLETED | E48: 10000 | F48: 10000 | G48: =E48-F48 -> 0 | H48: dzhuliana | I48: F8: New Member Onboarding | J48: TRUE | K48: TRUE | L48: TRUE | M48: TRUE | N48: FALSE | O48: TRUE | P48: COMPLETED | S48: COMPLETED | T48: COMPLETED | U48: COMPLETED | V48: COMPLETED | W48: COMPLETED | X48: COMPLETED | Y48: COMPLETED | Z48: COMPLETED | AA48: COMPLETED | AB48: COMPLETED | AC48: COMPLETED
A49: 41 | B49: 800041 | C49: Automated Multilingual Tool | D49: COMPLETED | E49: 17600 | F49: 17600 | G49: =E49-F49 -> 0 | H49: kuni | I49: F8: Scale-UP Cardano's Community Hubs | J49: TRUE | K49: TRUE | L49: TRUE | M49: TRUE | N49: TRUE | O49: TRUE | P49: FALSE | Q49: FALSE | R49: FALSE | S49: FALSE | T49: FALSE | U49: FALSE | V49: FALSE | W49: FALSE | X49: COMPLETED | Y49: COMPLETED | Z49: COMPLETED | AA49: COMPLETED | AB49: COMPLETED | AC49: COMPLETED
A50: 42 | B50: 800042 | C50: Avatarada | D50: DID NOT FINISH | E50: 53800 | F50: 43040 | G50: =E50-F50 -> 10760 | H50: Igor [VICE] | I50: F8: Open Standards & Interoperability | J50: TRUE | K50: TRUE | L50: TRUE | M50: TRUE | N50: TRUE | O50: TRUE | P50: FALSE | Q50: FALSE | R50: FALSE | S50: FALSE | T50: FALSE | U50: FALSE | V50: FALSE | W50: FALSE | X50: FALSE | Y50: FALSE | Z50: FALSE | AA50: FALSE | AB50: FALSE | AC50: FALSE
A51: 43 | B51: 800043 | C51: B2B Food Recipes NFT Marketplace | D51: DID NOT FINISH | E51: 5000 | F51: 3333 | G51: =E51-F51 -> 1667 | H51: Karim Sahyoun | I51: F8: Business Solutions (B2B & B2C) | J51: FALSE | K51: TRUE | L51: TRUE | M51: FALSE | N51: FALSE | O51: FALSE | P51: FALSE | Q51: FALSE | R51: FALSE | S51: FALSE | T51: FALSE | U51: FALSE | V51: FALSE | W51: FALSE | X51: FALSE | Y51: FALSE | Z51: FALSE | AA51: FALSE | AB51: FALSE | AC51: FALSE
A52: 44 | B52: 800044 | C52: Batch tx generator for cardano-cli | D52: COMPLETED | E52: 18000 | F52: 18000 | G52: =E52-F52 -> 0 | H52: Reshm | I52: F8: Open Source Development Ecosystem | J52: TRUE | K52: TRUE | L52: COMPLETED | S52: COMPLETED | T52: COMPLETED | U52: COMPLETED | V52: COMPLETED | W52: COMPLETED | X52: COMPLETED | Y52: COMPLETED | Z52: COMPLETED | AA52: COMPLETED | AB52: COMPLETED | AC52: COMPLETED
A53: 45 | B53: 800045 | C53: Beyond Create Teaming Agreements | D53: COMPLETED | E53: 64000 | F53: 64000 | G53: =E53-F53 -> 0 | H53: lenkabul | I53: F8: Developer Ecosystem | J53: TRUE | K53: TRUE | L53: TRUE | M53: TRUE | N53: TRUE | O53: TRUE | P53: FALSE | Q53: TRUE | R53: FALSE | S53: FALSE | T53: FALSE | U53: FALSE | V53: FALSE | W53: FALSE | X53: FALSE | Y53: FALSE | Z53: FALSE | AA53: FALSE | AB53: FALSE | AC53: FALSE
A54: 46 | B54: 800046 | C54: Blockchain and Cardano Library | D54: COMPLETED | E54: 11500 | F54: 11500 | G54: =E54-F54 -> 0 | H54: VCoinCheck | I54: F8: Grow East Asia, Grow Cardano | J54: TRUE | K54: TRUE | L54: TRUE | M54: TRUE | N54: TRUE | O54: COMPLETED | S54: COMPLETED | T54: COMPLETED | U54: COMPLETED | V54: COMPLETED | W54: COMPLETED | X54: COMPLETED | Y54: COMPLETED | Z54: COMPLETED | AA54: COMPLETED | AB54: COMPLETED | AC54: COMPLETED
A55: 47 | B55: 800047 | C55: Blockchain Class by adatruth.com | D55: COMPLETED | E55: 12000 | F55: 12000 | G55: =E55-F55 -> 0 | H55: petr.smelik | I55: F8: Film + Media (FAM) creatives unite! | J55: TRUE | K55: TRUE | L55: TRUE | M55: TRUE | N55: TRUE | O55: TRUE | P55: FALSE | Q55: FALSE | R55: COMPLETED | S55: COMPLETED | T55: COMPLETED | U55: COMPLETED | V55: COMPLETED | W55: COMPLETED | X55: COMPLETED | Y55: COMPLETED | Z55: COMPLETED | AA55: COMPLETED | AB55: COMPLETED | AC55: COMPLETED
A56: 48 | B56: 800048 | C56: Blockchain Learning Center + Coffee | D56: COMPLETED | E56: 33800 | F56: 33800 | G56: =E56-F56 -> 0 | H56: baxter30 | I56: F8: Scale-UP Cardano's Community Hubs | J56: TRUE | K56: TRUE | L56: TRUE | M56: TRUE | N56: TRUE | O56: TRUE | P56: COMPLETED | S56: COMPLETED | T56: COMPLETED | U56: COMPLETED | V56: COMPLETED | W56: COMPLETED | X56: COMPLETED | Y56: COMPLETED | Z56: COMPLETED | AA56: COMPLETED | AB56: COMPLETED | AC56: COMPLETED
A57: 49 | B57: 800049 | C57: Bonfire - Scheduling dApp 🔥 | D57: COMPLETED | E57: 15000 | F57: 15000 | G57: =E57-F57 -> 0 | H57: Piotr | I57: F8: Business Solutions (B2B & B2C) | J57: TRUE | K57: TRUE | L57: TRUE | M57: TRUE | N57: TRUE | O57: FALSE | P57: TRUE | Q57: FALSE | R57: FALSE | S57: TRUE | T57: TRUE | U57: TRUE | V57: TRUE | W57: TRUE | X57: TRUE | Y57: TRUE | Z57: FALSE | AA57: TRUE | AB57: COMPLETED | AC57: COMPLETED
A58: 50 | B58: 800050 | C58: Bridge liquidity for top protocols | D58: COMPLETED | E58: 90000 | F58: 90000 | G58: =E58-F58 -> 0 | H58: nicoarqueros | I58: F8: The Great Migration (from Ethereum) | J58: FALSE | K58: FALSE | L58: FALSE | M58: FALSE | N58: FALSE | O58: FALSE | P58: FALSE | Q58: TRUE | R58: FALSE | S58: FALSE | T58: FALSE | U58: FALSE | V58: FALSE | W58: FALSE | X58: FALSE | Y58: FALSE | Z58: FALSE | AA58: FALSE | AB58: FALSE | AC58: COMPLETED
A59: 51 | B59: 800051 | C59: Bringing E.A Investors to Cardano | D59: COMPLETED | E59: 8640 | F59: 8640 | G59: =E59-F59 -> 0 | H59: Lucas Macchiavelli | I59: F8: Grow East Asia, Grow Cardano | J59: TRUE | K59: TRUE | L59: TRUE | M59: TRUE | N59: TRUE | O59: COMPLETED | S59: COMPLETED | T59: COMPLETED | U59: COMPLETED | V59: COMPLETED | W59: COMPLETED | X59: COMPLETED | Y59: COMPLETED | Z59: COMPLETED | AA59: COMPLETED | AB59: COMPLETED | AC59: COMPLETED
A60: 52 | B60: 800052 | C60: Broaden open source wallet options | D60: COMPLETED | E60: 3850 | F60: 3850 | G60: =E60-F60 -> 0 | H60: abezawodni | I60: F8: Open Source Development Ecosystem | J60: TRUE | K60: TRUE | L60: TRUE | M60: TRUE | N60: FALSE | O60: FALSE | P60: FALSE | Q60: FALSE | R60: FALSE | S60: FALSE | T60: FALSE | U60: FALSE | V60: FALSE | W60: FALSE | X60: FALSE | Y60: FALSE | Z60: FALSE | AA60: FALSE | AB60: FALSE | AC60: FALSE
A61: 53 | B61: 800053 | C61: BWORKs - Pay As Done Works Platform | D61: COMPLETED | E61: 66000 | F61: 66000 | G61: =E61-F61 -> 0 | H61: Duc TIGER | I61: F8: Business Solutions (B2B & B2C) | J61: TRUE | K61: TRUE | L61: TRUE | M61: TRUE | N61: TRUE | O61: TRUE | P61: TRUE | Q61: FALSE | R61: FALSE | S61: FALSE | T61: TRUE | U61: TRUE | V61: FALSE | W61: FALSE | X61: FALSE | Y61: FALSE | Z61: FALSE | AA61: FALSE | AB61: FALSE | AC61: FALSE
A62: 54 | B62: 800054 | C62: BWORKs - Right Dev in Right Work | D62: COMPLETED | E62: 54780 | F62: 54780 | G62: =E62-F62 -> 0 | H62: Thang Tran - Saigon Bitmaster | I62: F8: Developer Ecosystem | J62: TRUE | K62: TRUE | L62: TRUE | M62: TRUE | N62: FALSE | O62: TRUE | P62: TRUE | Q62: TRUE | R62: TRUE | S62: TRUE | T62: TRUE | U62: TRUE | V62: FALSE | W62: FALSE | X62: FALSE | Y62: COMPLETED | Z62: COMPLETED | AA62: COMPLETED | AB62: COMPLETED | AC62: COMPLETED
A63: 55 | B63: 800055 | C63: BWORKs - Smart contract HR platform | D63: COMPLETED | E63: 71000 | F63: 71000 | G63: =E63-F63 -> 0 | H63: Thang Tran - Saigon Bitmaster | I63: F8: DApps and Integrations | J63: TRUE | K63: TRUE | L63: TRUE | M63: TRUE | N63: FALSE | O63: TRUE | P63: TRUE | Q63: TRUE | R63: TRUE | S63: TRUE | T63: TRUE | U63: TRUE | V63: FALSE | W63: FALSE | X63: FALSE | Y63: COMPLETED | Z63: COMPLETED | AA63: COMPLETED | AB63: COMPLETED | AC63: COMPLETED
A64: 56 | B64: 800056 | C64: C4C Community Hub Operations | D64: COMPLETED | E64: 12050 | F64: 12050 | G64: =E64-F64 -> 0 | H64: cardano4climate | I64: F8: Scale-UP Cardano's Community Hubs | J64: TRUE | K64: TRUE | L64: TRUE | M64: TRUE | N64: TRUE | O64: COMPLETED | S64: COMPLETED | T64: COMPLETED | U64: COMPLETED | V64: COMPLETED | W64: COMPLETED | X64: COMPLETED | Y64: COMPLETED | Z64: COMPLETED | AA64: COMPLETED | AB64: COMPLETED | AC64: COMPLETED
A65: 57 | B65: 800057 | C65: C4S - Cardano for Seniors Hubs | D65: COMPLETED | E65: 25000 | F65: 25000 | G65: =E65-F65 -> 0 | H65: Headelf | I65: F8: Scale-UP Cardano's Community Hubs | J65: TRUE | K65: TRUE | L65: TRUE | M65: TRUE | N65: TRUE | O65: FALSE | P65: FALSE | Q65: FALSE | R65: COMPLETED | S65: COMPLETED | T65: COMPLETED | U65: COMPLETED | V65: COMPLETED | W65: COMPLETED | X65: COMPLETED | Y65: COMPLETED | Z65: COMPLETED | AA65: COMPLETED | AB65: COMPLETED | AC65: COMPLETED
A66: 58 | B66: 800058 | C66: CA Academy Certification | D66: COMPLETED | E66: 8000 | F66: 8000 | G66: =E66-F66 -> 0 | H66: Natnael Demelash | I66: F8: Community Advisor Improvements | J66: TRUE | K66: TRUE | L66: TRUE | M66: TRUE | N66: FALSE | O66: FALSE | P66: FALSE | Q66: FALSE | R66: FALSE | S66: FALSE | T66: FALSE | U66: FALSE | V66: FALSE | W66: FALSE | X66: FALSE | Y66: FALSE | Z66: FALSE | AA66: FALSE | AB66: FALSE | AC66: FALSE
A67: 59 | B67: 800059 | C67: CA Guidelines Joint Drafting | D67: DID NOT FINISH | E67: 7640 | F67: 6791 | G67: =E67-F67 -> 849 | H67: Aharon Porath | I67: F8: Community Advisor Improvements | J67: TRUE | K67: TRUE | L67: TRUE | M67: TRUE | N67: TRUE | O67: TRUE | P67: FALSE | Q67: TRUE | R67: FALSE | S67: FALSE | T67: FALSE | U67: FALSE | V67: FALSE | W67: FALSE | X67: TRUE | Y67: FALSE | Z67: FALSE | AA67: FALSE | AB67: FALSE | AC67: FALSE
A68: 60 | B68: 800060 | C68: CA-tool Dev & Maintenance - AIM | D68: COMPLETED | E68: 7500 | F68: 7500 | G68: =E68-F68 -> 0 | H68: Philip Khoo | I68: F8: Community Advisor Improvements | J68: TRUE | K68: FALSE | L68: FALSE | M68: FALSE | N68: FALSE | O68: TRUE | P68: FALSE | Q68: FALSE | R68: FALSE | S68: FALSE | T68: FALSE | U68: FALSE | V68: FALSE | W68: FALSE | X68: FALSE | Y68: FALSE | Z68: FALSE | AA68: FALSE | AB68: COMPLETED | AC68: COMPLETED
A69: 61 | B69: 800061 | C69: CA/VCA Treasury for Rapid Funding | D69: COMPLETED | E69: 30000 | F69: 30000 | G69: =E69-F69 -> 0 | H69: nadiahopkins | I69: F8: Community Advisor Improvements | J69: TRUE | K69: TRUE | L69: TRUE | M69: TRUE | N69: TRUE | O69: TRUE | P69: TRUE | Q69: FALSE | R69: FALSE | S69: FALSE | T69: FALSE | U69: FALSE | V69: FALSE | W69: FALSE | X69: FALSE | Y69: FALSE | Z69: FALSE | AA69: FALSE | AB69: FALSE | AC69: FALSE
A70: 62 | B70: 800062 | C70: Carbon ERC-20 Converter to Cardano | D70: COMPLETED | E70: 27000 | F70: 27000 | G70: =E70-F70 -> 0 | H70: June Akra | I70: F8: The Great Migration (from Ethereum) | J70: TRUE | K70: TRUE | L70: TRUE | M70: TRUE | N70: TRUE | O70: TRUE | P70: FALSE | Q70: FALSE | R70: FALSE | S70: FALSE | T70: FALSE | U70: FALSE | V70: FALSE | W70: FALSE | X70: FALSE | Y70: FALSE | Z70: FALSE | AA70: COMPLETED | AB70: COMPLETED | AC70: COMPLETED
A71: 63 | B71: 800063 | C71: Carbon Marketplace and Exchange | D71: COMPLETED | E71: 64100 | F71: 64100 | G71: =E71-F71 -> 0 | H71: BlockCarbon | I71: F8: DApps and Integrations | J71: TRUE | K71: TRUE | L71: TRUE | M71: TRUE | N71: TRUE | O71: TRUE | P71: FALSE | Q71: FALSE | R71: FALSE | S71: FALSE | T71: FALSE | U71: FALSE | V71: FALSE | W71: FALSE | X71: FALSE | Y71: FALSE | Z71: FALSE | AA71: FALSE | AB71: FALSE | AC71: FALSE
A72: 64 | B72: 800064 | C72: Cardano and Smart City Awareness | D72: COMPLETED | E72: 1249 | F72: 1249 | G72: =E72-F72 -> 0 | H72: fanna | I72: F8: Grow Africa, Grow Cardano | J72: FALSE | K72: TRUE | L72: TRUE | M72: COMPLETED | S72: COMPLETED | T72: COMPLETED | U72: COMPLETED | V72: COMPLETED | W72: COMPLETED | X72: COMPLETED | Y72: COMPLETED | Z72: COMPLETED | AA72: COMPLETED | AB72: COMPLETED | AC72: COMPLETED
A73: 65 | B73: 800065 | C73: Cardano Annual Market Report | D73: COMPLETED | E73: 10000 | F73: 10000 | G73: =E73-F73 -> 0 | H73: tranthanhtung37 | I73: F8: Film + Media (FAM) creatives unite! | J73: TRUE | K73: TRUE | L73: TRUE | M73: TRUE | N73: COMPLETED | S73: COMPLETED | T73: COMPLETED | U73: COMPLETED | V73: COMPLETED | W73: COMPLETED | X73: COMPLETED | Y73: COMPLETED | Z73: COMPLETED | AA73: COMPLETED | AB73: COMPLETED | AC73: COMPLETED
A74: 66 | B74: 800066 | C74: Cardano Beam - GPS based Assets | D74: COMPLETED | E74: 30200 | F74: 30200 | G74: =E74-F74 -> 0 | H74: dynamicstrategiesio | I74: F8: DApps and Integrations | J74: TRUE | K74: TRUE | L74: TRUE | M74: TRUE | N74: TRUE | O74: TRUE | P74: COMPLETED | S74: COMPLETED | T74: COMPLETED | U74: COMPLETED | V74: COMPLETED | W74: COMPLETED | X74: COMPLETED | Y74: COMPLETED | Z74: COMPLETED | AA74: COMPLETED | AB74: COMPLETED | AC74: COMPLETED
A75: 67 | B75: 800067 | C75: Cardano Center Poland stage 2 - SPO | D75: COMPLETED | E75: 5280 | F75: 5280 | G75: =E75-F75 -> 0 | H75: Kornel | I75: F8: Scale-UP Cardano's Community Hubs | J75: TRUE | K75: TRUE | L75: TRUE | M75: COMPLETED | S75: COMPLETED | T75: COMPLETED | U75: COMPLETED | V75: COMPLETED | W75: COMPLETED | X75: COMPLETED | Y75: COMPLETED | Z75: COMPLETED | AA75: COMPLETED | AB75: COMPLETED | AC75: COMPLETED
A76: 68 | B76: 800068 | C76: Cardano coffee - Regional languages | D76: DID NOT FINISH | E76: 29750 | F76: 25500 | G76: =E76-F76 -> 4250 | H76: Sarod Sasidharan | I76: F8: Grow India, Grow Cardano | J76: TRUE | K76: TRUE | L76: TRUE | M76: TRUE | N76: TRUE | O76: TRUE | P76: FALSE | Q76: FALSE | R76: FALSE | S76: FALSE | T76: FALSE | U76: FALSE | V76: FALSE | W76: FALSE | X76: FALSE | Y76: FALSE | Z76: FALSE | AA76: FALSE | AB76: FALSE | AC76: FALSE
A77: 69 | B77: 800069 | C77: Cardano Coffee lounge in Vietnam | D77: COMPLETED | E77: 24800 | F77: 24800 | G77: =E77-F77 -> 0 | H77: nvhieu | I77: F8: Scale-UP Cardano's Community Hubs | J77: TRUE | K77: TRUE | L77: TRUE | M77: TRUE | N77: TRUE | O77: TRUE | P77: COMPLETED | S77: COMPLETED | T77: COMPLETED | U77: COMPLETED | V77: COMPLETED | W77: COMPLETED | X77: COMPLETED | Y77: COMPLETED | Z77: COMPLETED | AA77: COMPLETED | AB77: COMPLETED | AC77: COMPLETED
A78: 70 | B78: 800070 | C78: Cardano Community in Geneva | D78: COMPLETED | E78: 25000 | F78: 25000 | G78: =E78-F78 -> 0 | H78: Accelerate2030 | I78: F8: Scale-UP Cardano's Community Hubs | J78: TRUE | K78: TRUE | L78: TRUE | M78: FALSE | N78: TRUE | O78: TRUE | P78: COMPLETED | S78: COMPLETED | T78: COMPLETED | U78: COMPLETED | V78: COMPLETED | W78: COMPLETED | X78: COMPLETED | Y78: COMPLETED | Z78: COMPLETED | AA78: COMPLETED | AB78: COMPLETED | AC78: COMPLETED
A79: 71 | B79: 800071 | C79: Cardano Community Podcasts & YT | D79: COMPLETED | E79: 6000 | F79: 6000 | G79: =E79-F79 -> 0 | H79: Kornel | I79: F8: Film + Media (FAM) creatives unite! | J79: TRUE | K79: TRUE | L79: TRUE | M79: TRUE | N79: TRUE | O79: TRUE | P79: FALSE | Q79: FALSE | R79: FALSE | S79: FALSE | T79: FALSE | U79: COMPLETED | V79: COMPLETED | W79: COMPLETED | X79: COMPLETED | Y79: COMPLETED | Z79: COMPLETED | AA79: COMPLETED | AB79: COMPLETED | AC79: COMPLETED
A80: 72 | B80: 800072 | C80: Cardano development library in C++ | D80: COMPLETED | E80: 10000 | F80: 10000 | G80: =E80-F80 -> 0 | H80: viperstakepool | I80: F8: Open Source Development Ecosystem | J80: TRUE | K80: FALSE | L80: TRUE | M80: TRUE | N80: TRUE | O80: TRUE | P80: COMPLETED | S80: COMPLETED | T80: COMPLETED | U80: COMPLETED | V80: COMPLETED | W80: COMPLETED | X80: COMPLETED | Y80: COMPLETED | Z80: COMPLETED | AA80: COMPLETED | AB80: COMPLETED | AC80: COMPLETED
A81: 73 | B81: 800073 | C81: Cardano for African impact ventures | D81: COMPLETED | E81: 20000 | F81: 20000 | G81: =E81-F81 -> 0 | H81: Accelerate2030 | I81: F8: Grow Africa, Grow Cardano | J81: TRUE | K81: TRUE | L81: TRUE | M81: FALSE | N81: TRUE | O81: TRUE | P81: COMPLETED | S81: COMPLETED | T81: COMPLETED | U81: COMPLETED | V81: COMPLETED | W81: COMPLETED | X81: COMPLETED | Y81: COMPLETED | Z81: COMPLETED | AA81: COMPLETED | AB81: COMPLETED | AC81: COMPLETED
A82: 74 | B82: 800074 | C82: Cardano Forest In Vietnam | D82: COMPLETED | E82: 24150 | F82: 24150 | G82: =E82-F82 -> 0 | H82: Quoc ADAUP | I82: F8: Grow East Asia, Grow Cardano | J82: TRUE | K82: TRUE | L82: TRUE | M82: TRUE | N82: TRUE | O82: TRUE | P82: FALSE | Q82: FALSE | R82: COMPLETED | S82: COMPLETED | T82: COMPLETED | U82: COMPLETED | V82: COMPLETED | W82: COMPLETED | X82: COMPLETED | Y82: COMPLETED | Z82: COMPLETED | AA82: COMPLETED | AB82: COMPLETED | AC82: COMPLETED
A83: 75 | B83: 800075 | C83: CARDANO FRENCH COMMUNITY IN DRC | D83: COMPLETED | E83: 9000 | F83: 9000 | G83: =E83-F83 -> 0 | H83: uptodatedevelopers | I83: F8: Grow Africa, Grow Cardano | J83: TRUE | K83: TRUE | L83: TRUE | M83: TRUE | N83: TRUE | O83: COMPLETED | S83: COMPLETED | T83: COMPLETED | U83: COMPLETED | V83: COMPLETED | W83: COMPLETED | X83: COMPLETED | Y83: COMPLETED | Z83: COMPLETED | AA83: COMPLETED | AB83: COMPLETED | AC83: COMPLETED
A84: 76 | B84: 800076 | C84: Cardano Hackathon in Argentina | D84: COMPLETED | E84: 21100 | F84: 21100 | G84: =E84-F84 -> 0 | H84: Jose Iadicicco | I84: F8: Developer Ecosystem | J84: FALSE | K84: TRUE | L84: TRUE | M84: TRUE | N84: FALSE | O84: COMPLETED | S84: COMPLETED | T84: COMPLETED | U84: COMPLETED | V84: COMPLETED | W84: COMPLETED | X84: COMPLETED | Y84: COMPLETED | Z84: COMPLETED | AA84: COMPLETED | AB84: COMPLETED | AC84: COMPLETED
A85: 77 | B85: 800077 | C85: Cardano Hub TAIWAN | D85: COMPLETED | E85: 9780 | F85: 9780 | G85: =E85-F85 -> 0 | H85: sabrina | I85: F8: Scale-UP Cardano's Community Hubs | J85: TRUE | K85: TRUE | L85: TRUE | M85: TRUE | N85: TRUE | O85: TRUE | P85: TRUE | Q85: TRUE | R85: TRUE | S85: TRUE | T85: TRUE | U85: FALSE | V85: FALSE | W85: FALSE | X85: FALSE | Y85: COMPLETED | Z85: COMPLETED | AA85: COMPLETED | AB85: COMPLETED | AC85: COMPLETED
A86: 78 | B86: 800078 | C86: Cardano Hubs Directory | D86: COMPLETED | E86: 28000 | F86: 28000 | G86: =E86-F86 -> 0 | H86: Josh F | I86: F8: Scale-UP Cardano's Community Hubs | J86: TRUE | K86: TRUE | L86: TRUE | M86: TRUE | N86: TRUE | O86: TRUE | P86: TRUE | Q86: FALSE | R86: FALSE | S86: FALSE | T86: FALSE | U86: FALSE | V86: FALSE | W86: FALSE | X86: FALSE | Y86: FALSE | Z86: FALSE | AA86: FALSE | AB86: COMPLETED | AC86: COMPLETED
A87: 79 | B87: 800079 | C87: Cardano impact project directory | D87: COMPLETED | E87: 8500 | F87: 8500 | G87: =E87-F87 -> 0 | H87: Raz | I87: F8: Cross-Chain Collaboration | J87: FALSE | K87: TRUE | L87: FALSE | M87: TRUE | N87: TRUE | O87: TRUE | P87: TRUE | Q87: TRUE | R87: TRUE | S87: FALSE | T87: TRUE | U87: TRUE | V87: FALSE | W87: FALSE | X87: FALSE | Y87: FALSE | Z87: FALSE | AA87: FALSE | AB87: FALSE | AC87: COMPLETED
A88: 80 | B88: 800080 | C88: Cardano in Gujarati | D88: DID NOT FINISH | E88: 7100 | F88: 4733 | G88: =E88-F88 -> 2367 | H88: Dimitri Fernando | I88: F8: Grow India, Grow Cardano | J88: TRUE | K88: TRUE | L88: TRUE | M88: FALSE | N88: FALSE | O88: FALSE | P88: FALSE | Q88: FALSE | R88: FALSE | S88: FALSE | T88: FALSE | U88: FALSE | V88: FALSE | W88: FALSE | X88: FALSE | Y88: FALSE | Z88: FALSE | AA88: FALSE | AB88: FALSE | AC88: FALSE
A89: 81 | B89: 800081 | C89: Cardano in Hindi | D89: DID NOT FINISH | E89: 7100 | F89: 4733 | G89: =E89-F89 -> 2367 | H89: Dimitri Fernando | I89: F8: Grow India, Grow Cardano | J89: TRUE | K89: TRUE | L89: TRUE | M89: FALSE | N89: FALSE | O89: FALSE | P89: FALSE | Q89: FALSE | R89: FALSE | S89: FALSE | T89: FALSE | U89: FALSE | V89: FALSE | W89: FALSE | X89: FALSE | Y89: FALSE | Z89: FALSE | AA89: FALSE | AB89: FALSE | AC89: FALSE
A90: 82 | B90: 800082 | C90: Cardano in Thai | D90: DID NOT FINISH | E90: 7100 | F90: 4057 | G90: =E90-F90 -> 3043 | H90: Dimitri Fernando | I90: F8: Grow East Asia, Grow Cardano | J90: TRUE | K90: TRUE | L90: TRUE | M90: FALSE | N90: FALSE | O90: FALSE | P90: FALSE | Q90: FALSE | R90: FALSE | S90: FALSE | T90: FALSE | U90: FALSE | V90: FALSE | W90: FALSE | X90: FALSE | Y90: FALSE | Z90: FALSE | AA90: FALSE | AB90: FALSE | AC90: FALSE
A91: 83 | B91: 800083 | C91: Cardano IPFS chronicles 2022 | D91: COMPLETED | E91: 26400 | F91: 26400 | G91: =E91-F91 -> 0 | H91: Five Binaries | I91: F8: Developer Ecosystem | J91: TRUE | K91: TRUE | L91: TRUE | M91: TRUE | N91: TRUE | O91: TRUE | P91: FALSE | Q91: FALSE | R91: FALSE | S91: FALSE | T91: FALSE | U91: FALSE | V91: FALSE | W91: FALSE | X91: FALSE | Y91: FALSE | Z91: FALSE | AA91: FALSE | AB91: FALSE | AC91: FALSE
A92: 84 | B92: 800084 | C92: Cardano learning needs assessment | D92: COMPLETED | E92: 980 | F92: 980 | G92: =E92-F92 -> 0 | H92: Michael A. Cenkner, MEd | I92: F8: New Member Onboarding | J92: TRUE | K92: TRUE | L92: TRUE | M92: FALSE | N92: FALSE | O92: FALSE | P92: FALSE | Q92: FALSE | R92: COMPLETED | S92: COMPLETED | T92: COMPLETED | U92: COMPLETED | V92: COMPLETED | W92: COMPLETED | X92: COMPLETED | Y92: COMPLETED | Z92: COMPLETED | AA92: COMPLETED | AB92: COMPLETED | AC92: COMPLETED
A93: 85 | B93: 800085 | C93: Cardano PR Initiative Japan | D93: COMPLETED | E93: 36000 | F93: 36000 | G93: =E93-F93 -> 0 | H93: FTanaka | I93: F8: Miscellaneous Challenge | J93: TRUE | K93: TRUE | L93: TRUE | M93: TRUE | N93: FALSE | O93: FALSE | P93: FALSE | Q93: FALSE | R93: FALSE | S93: FALSE | T93: FALSE | U93: FALSE | V93: FALSE | W93: FALSE | X93: FALSE | Y93: FALSE | Z93: FALSE | AA93: FALSE | AB93: FALSE | AC93: FALSE
A94: 86 | B94: 800086 | C94: Cardano Recycling DApp | D94: COMPLETED | E94: 44586 | F94: 44586 | G94: =E94-F94 -> 0 | H94: Nana Safo | I94: F8: Business Solutions (B2B & B2C) | J94: TRUE | K94: TRUE | L94: TRUE | M94: TRUE | N94: TRUE | O94: FALSE | P94: FALSE | Q94: FALSE | R94: FALSE | S94: FALSE | T94: FALSE | U94: FALSE | V94: FALSE | W94: FALSE | X94: FALSE | Y94: FALSE | Z94: FALSE | AA94: FALSE | AB94: FALSE | AC94: FALSE
A95: 87 | B95: 800087 | C95: Cardano Rust SDK Babbage | D95: COMPLETED | E95: 30000 | F95: 30000 | G95: =E95-F95 -> 0 | H95: nicoarqueros | I95: F8: Open Source Development Ecosystem | J95: FALSE | K95: FALSE | L95: TRUE | M95: TRUE | N95: FALSE | O95: FALSE | P95: FALSE | Q95: FALSE | R95: COMPLETED | S95: COMPLETED | T95: COMPLETED | U95: COMPLETED | V95: COMPLETED | W95: COMPLETED | X95: COMPLETED | Y95: COMPLETED | Z95: COMPLETED | AA95: COMPLETED | AB95: COMPLETED | AC95: COMPLETED
A96: 88 | B96: 800088 | C96: Cardano SSI standards contributors | D96: COMPLETED | E96: 8400 | F96: 8400 | G96: =E96-F96 -> 0 | H96: RootsID | I96: F8: Self-Sovereign Identity | J96: TRUE | K96: TRUE | L96: TRUE | M96: COMPLETED | S96: COMPLETED | T96: COMPLETED | U96: COMPLETED | V96: COMPLETED | W96: COMPLETED | X96: COMPLETED | Y96: COMPLETED | Z96: COMPLETED | AA96: COMPLETED | AB96: COMPLETED | AC96: COMPLETED
A97: 89 | B97: 800089 | C97: Cardano Tools & Software for ARM | D97: COMPLETED | E97: 30000 | F97: 30000 | G97: =E97-F97 -> 0 | H97: wael ivie | I97: F8: Open Source Development Ecosystem | J97: TRUE | K97: TRUE | L97: TRUE | M97: TRUE | N97: TRUE | O97: TRUE | P97: TRUE | Q97: FALSE | R97: COMPLETED | S97: COMPLETED | T97: COMPLETED | U97: COMPLETED | V97: COMPLETED | W97: COMPLETED | X97: COMPLETED | Y97: COMPLETED | Z97: COMPLETED | AA97: COMPLETED | AB97: COMPLETED | AC97: COMPLETED
A98: 90 | B98: 800090 | C98: Cardano White Board videos (Telugu) | D98: DID NOT FINISH | E98: 6988 | F98: 5435 | G98: =E98-F98 -> 1553 | H98: gulla0.harsha | I98: F8: Grow India, Grow Cardano | J98: TRUE | K98: TRUE | L98: TRUE | M98: TRUE | N98: FALSE | O98: TRUE | P98: TRUE | Q98: FALSE | R98: FALSE | S98: FALSE | T98: FALSE | U98: FALSE | V98: FALSE | W98: FALSE | X98: FALSE | Y98: FALSE | Z98: FALSE | AA98: FALSE | AB98: FALSE | AC98: FALSE
A99: 91 | B99: 800091 | C99: Cardano-Tools Python Library | D99: COMPLETED | E99: 10000 | F99: 10000 | G99: =E99-F99 -> 0 | H99: viperstakepool | I99: F8: Open Source Development Ecosystem | J99: TRUE | K99: TRUE | L99: TRUE | M99: TRUE | N99: TRUE | O99: TRUE | P99: COMPLETED | S99: COMPLETED | T99: COMPLETED | U99: COMPLETED | V99: COMPLETED | W99: COMPLETED | X99: COMPLETED | Y99: COMPLETED | Z99: COMPLETED | AA99: COMPLETED | AB99: COMPLETED | AC99: COMPLETED
A100: 92 | B100: 800092 | C100: Cardanobi.io | D100: COMPLETED | E100: 49032 | F100: 49032 | G100: =E100-F100 -> 0 | H100: Thomas Langlois | I100: F8: Open Source Development Ecosystem | J100: TRUE | K100: TRUE | L100: TRUE | M100: TRUE | N100: TRUE | O100: TRUE | P100: TRUE | Q100: FALSE | R100: TRUE | S100: TRUE | T100: FALSE | U100: TRUE | V100: FALSE | W100: FALSE | X100: FALSE | Y100: COMPLETED | Z100: COMPLETED | AA100: COMPLETED | AB100: COMPLETED | AC100: COMPLETED
A101: 93 | B101: 800093 | C101: CardanoCommunityHubs.com Worldwide | D101: COMPLETED | E101: 19500 | F101: 19500 | G101: =E101-F101 -> 0 | H101: Carl Henry Global | I101: F8: Scale-UP Cardano's Community Hubs | J101: TRUE | K101: TRUE | L101: TRUE | M101: TRUE | N101: COMPLETED | S101: COMPLETED | T101: COMPLETED | U101: COMPLETED | V101: COMPLETED | W101: COMPLETED | X101: COMPLETED | Y101: COMPLETED | Z101: COMPLETED | AA101: COMPLETED | AB101: COMPLETED | AC101: COMPLETED
A102: 94 | B102: 800094 | C102: CardanoFeel (Cardano -> Real World) | D102: COMPLETED | E102: 10000 | F102: 10000 | G102: =E102-F102 -> 0 | H102: David Bayon | I102: F8: Miscellaneous Challenge | J102: TRUE | K102: TRUE | L102: TRUE | M102: FALSE | N102: COMPLETED | S102: COMPLETED | T102: COMPLETED | U102: COMPLETED | V102: COMPLETED | W102: COMPLETED | X102: COMPLETED | Y102: COMPLETED | Z102: COMPLETED | AA102: COMPLETED | AB102: COMPLETED | AC102: COMPLETED
...

Sheet Fund7 Reporting
A1: THIS DOCUMENT WILL BE DEPRECATED SOON If you need support please submit a ticket via zendesk.
C4: FUND7 | E4: Funding ($) | I4: fast
A5: # | B5: ID | C5: Project Name | D5: Project Status | E5: Requested | F5: Distributed to date | G5: Remaining | H5: Primary Proposer - Guarantor | I5: Challenge | J5: Progress Report | K5: Progress Report | L5: Progress Report | M5: Progress Report | N5: Progress Report | O5: Progress Report | P5: Progress Report | Q5: Progress Report | R5: Progress Report | S5: Progress Report | T5: Progress Report | U5: Progress Report | V5: Progress Report | W5: Progress Report | X5: Progress Report | Y5: Progress Report | Z5: Progress Report | AA5: Progress Report | AB5: Progress Report | AC5: Progress Report | AD5: Progress Report | AE5: Progress Report
E6: =SUM(E9:E277) -> 6399832 | F6: =SUM(F9:F277) -> 5965576 | G6: =SUM(G9:G277) -> 434256 | J6: March '22 | K6: April '22 | L6: May '22 | M6: June '22 | N6: July '22 | O6: August '22 | P6: September '22 | Q6: October '22 | R6: November '22 | S6: December '22 | T6: January '23 | U6: February '23 | V6: March '23 | W6: April '23 | X6: May '23 | Y6: June '23 | Z6: July '23 | AA6: August '23 | AB6: September '23 | AC6: October '23 | AD6: November '23 | AE6: December '23
C7: Reporting % | J7: =J8/($C$8 - (COUNTIF(J9:J277, "COMPLETED")+COUNTIF(J9:J277, ""))) -> 0.90188679 | K7: =K8/($C$8 - (COUNTIF(K9:K277, "COMPLETED")+COUNTIF(K9:K277, ""))) -> 0.9034749 | L7: =L8/($C$8 - (COUNTIF(L9:L277, "COMPLETED")+COUNTIF(L9:L277, ""))) -> 0.82995951 | M7: =M8/($C$8 - (COUNTIF(M9:M277, "COMPLETED")+COUNTIF(M9:M277, ""))) -> 0.74418605 | N7: =N8/($C$8 - (COUNTIF(N9:N277, "COMPLETED")+COUNTIF(N9:N277, ""))) -> 0.56565657 | O7: =O8/($C$8 - (COUNTIF(O9:O277, "COMPLETED")+COUNTIF(O9:O277, ""))) -> 0.46031746 | P7: =P8/($C$8 - (COUNTIF(P9:P277, "COMPLETED")+COUNTIF(P9:P277, ""))) -> 0.43452381 | Q7: =Q8/($C$8 - (COUNTIF(Q9:Q277, "COMPLETED")+COUNTIF(Q9:Q277, ""))) -> 0.43030303 | ... AE7: =AE8/($C$8 - (COUNTIF(AE9:AE277, "COMPLETED")+COUNTIF(AE9:AE277, ""))) -> 0.026666667
C8: =Counta(C9:C277) -> 269 | J8: =COUNTIF(J9:J277, TRUE) -> 239 | K8: =COUNTIF(K9:K277, TRUE) -> 234 | L8: =COUNTIF(L9:L277, TRUE) -> 205 | M8: =COUNTIF(M9:M277, TRUE) -> 160 | N8: =COUNTIF(N9:N277, TRUE) -> 112 | O8: =COUNTIF(O9:O277, TRUE) -> 87 | P8: =COUNTIF(P9:P277, TRUE) -> 73 | Q8: =COUNTIF(Q9:Q277, TRUE) -> 71 | ... AE8: =COUNTIF(AE9:AE277, TRUE) -> 2
A9: 1 | B9: 700001 | C9: @chain-lib Cardano API Plugins | D9: DID NOT FINISH | E9: 5214 | F9: 3911 | G9: =E9-F9 -> 1303 | H9: wValthar | I9: F7: Open Source Developer Ecosystem | J9: TRUE | K9: TRUE | L9: TRUE | M9: FALSE | N9: FALSE | O9: FALSE | P9: FALSE | Q9: FALSE | R9: FALSE | S9: FALSE | T9: FALSE | U9: FALSE | V9: FALSE | W9: FALSE | X9: FALSE | Y9: FALSE | Z9: FALSE | AA9: FALSE | AB9: FALSE | AC9: FALSE | AD9: FALSE | AE9: FALSE
A10: 2 | B10: 700002 | C10: @chain-lib Documentation Website | D10: DID NOT FINISH | E10: 4211 | F10: 3158 | G10: =E10-F10 -> 1053 | H10: wValthar | I10: F7: Open Source Developer Ecosystem | J10: TRUE | K10: TRUE | L10: TRUE | M10: FALSE | N10: FALSE | O10: FALSE | P10: FALSE | Q10: FALSE | R10: FALSE | S10: FALSE | T10: FALSE | U10: FALSE | V10: FALSE | W10: FALSE | X10: FALSE | Y10: FALSE | Z10: FALSE | AA10: FALSE | AB10: FALSE | AC10: FALSE | AD10: FALSE | AE10: FALSE
A11: 3 | B11: 700003 | C11: ₳GOV: Agreements Building Platform | D11: COMPLETED | E11: 68800 | F11: 68800 | G11: =E11-F11 -> 0 | H11: Aharon Porath | I11: F7: DAOs ❤ Cardano | J11: TRUE | K11: TRUE | L11: TRUE | M11: TRUE | N11: FALSE | O11: TRUE | P11: TRUE | Q11: TRUE | R11: TRUE | S11: FALSE | T11: COMPLETED | U11: COMPLETED | V11: COMPLETED | W11: COMPLETED | X11: COMPLETED | Y11: COMPLETED | Z11: COMPLETED | AA11: COMPLETED | AB11: COMPLETED | AC11: COMPLETED | AD11: COMPLETED | AE11: COMPLETED
A12: 4 | B12: 700004 | C12: 1st universal E-learning connector | D12: COMPLETED | E12: 9999 | F12: 9999 | G12: =E12-F12 -> 0 | H12: altimario | I12: F7: Mini/Low-Budget Dapps & Integrations | J12: TRUE | K12: TRUE | L12: FALSE | M12: FALSE | N12: FALSE | O12: FALSE | P12: FALSE | Q12: FALSE | R12: FALSE | S12: TRUE | T12: COMPLETED | U12: COMPLETED | V12: COMPLETED | W12: COMPLETED | X12: COMPLETED | Y12: COMPLETED | Z12: COMPLETED | AA12: COMPLETED | AB12: COMPLETED | AC12: COMPLETED | AD12: COMPLETED | AE12: COMPLETED
A13: 5 | B13: 700005 | C13: 2MIN REVIEW Integrated Platform | D13: COMPLETED | E13: 12298 | F13: 12298 | G13: =E13-F13 -> 0 | H13: Two Min | I13: F7: Improve and Grow Auditability | J13: TRUE | K13: TRUE | L13: FALSE | M13: FALSE | N13: FALSE | O13: FALSE | P13: FALSE | Q13: FALSE | R13: FALSE | S13: FALSE | T13: FALSE | U13: FALSE | V13: FALSE | W13: FALSE | X13: FALSE | Y13: FALSE | Z13: FALSE | AA13: FALSE | AB13: FALSE | AC13: COMPLETED | AD13: COMPLETED | AE13: COMPLETED
A14: 6 | B14: 700006 | C14: 3D Design and Print NFT Spacecoins | D14: COMPLETED | E14: 10000 | F14: 10000 | G14: =E14-F14 -> 0 | H14: gradyw | I14: F7: Mini/Low-Budget Dapps & Integrations | J14: TRUE | K14: FALSE | L14: FALSE | M14: TRUE | N14: FALSE | O14: FALSE | P14: FALSE | Q14: FALSE | R14: FALSE | S14: FALSE | T14: FALSE | U14: FALSE | V14: FALSE | W14: FALSE | X14: FALSE | Y14: FALSE | Z14: FALSE | AA14: FALSE | AB14: FALSE | AC14: FALSE | AD14: FALSE | AE14: FALSE
A15: 7 | B15: 700007 | C15: A Community Vesting Dapp | D15: COMPLETED | E15: 10000 | F15: 10000 | G15: =E15-F15 -> 0 | H15: quinn | I15: F7: Mini/Low-Budget Dapps & Integrations | J15: TRUE | K15: TRUE | L15: COMPLETED | U15: COMPLETED | V15: COMPLETED | W15: COMPLETED | X15: COMPLETED | Y15: COMPLETED | Z15: COMPLETED | AA15: COMPLETED | AB15: COMPLETED | AC15: COMPLETED | AD15: COMPLETED | AE15: COMPLETED
A16: 8 | B16: 700008 | C16: A portal to audit and release funds | D16: DID NOT FINISH | E16: 9000 | F16: 0 | G16: =E16-F16 -> 9000 | H16: Ministry of good ideas | I16: F7: Improve and Grow Auditability | J16: FALSE | K16: FALSE | L16: FALSE | M16: FALSE | N16: FALSE | O16: FALSE | P16: FALSE | Q16: FALSE | R16: FALSE | S16: FALSE | T16: FALSE | U16: FALSE | V16: FALSE | W16: FALSE | X16: FALSE | Y16: FALSE | Z16: FALSE | AA16: FALSE | AB16: FALSE | AC16: FALSE | AD16: FALSE | AE16: FALSE
A17: 9 | B17: 700009 | C17: Accelerating Enterprise Adoption | D17: COMPLETED | E17: 75000 | F17: 75000 | G17: =E17-F17 -> 0 | H17: Joget | I17: F7: Nation Building Dapps | J17: TRUE | K17: TRUE | L17: TRUE | M17: TRUE | N17: TRUE | O17: COMPLETED | U17: COMPLETED | V17: COMPLETED | W17: COMPLETED | X17: COMPLETED | Y17: COMPLETED | Z17: COMPLETED | AA17: COMPLETED | AB17: COMPLETED | AC17: COMPLETED | AD17: COMPLETED | AE17: COMPLETED
A18: 10 | B18: 700010 | C18: Acceleration Program in Africa | D18: COMPLETED | E18: 85500 | F18: 85500 | G18: =E18-F18 -> 0 | H18: Seedstars | I18: F7: Catalyst Accelerator & Mentors | J18: TRUE | K18: TRUE | L18: TRUE | M18: TRUE | N18: TRUE | O18: TRUE | P18: TRUE | Q18: TRUE | R18: TRUE | S18: TRUE | T18: COMPLETED | U18: COMPLETED | V18: COMPLETED | W18: COMPLETED | X18: COMPLETED | Y18: COMPLETED | Z18: COMPLETED | AA18: COMPLETED | AB18: COMPLETED | AC18: COMPLETED | AD18: COMPLETED | AE18: COMPLETED
A19: 11 | B19: 700011 | C19: Accelerator in Emerging Markets | D19: COMPLETED | E19: 85000 | F19: 85000 | G19: =E19-F19 -> 0 | H19: Seedstars | I19: F7: Catalyst Accelerator & Mentors | J19: TRUE | K19: TRUE | L19: TRUE | M19: TRUE | N19: FALSE | O19: TRUE | P19: TRUE | Q19: TRUE | R19: TRUE | S19: TRUE | T19: COMPLETED | U19: COMPLETED | V19: COMPLETED | W19: COMPLETED | X19: COMPLETED | Y19: COMPLETED | Z19: COMPLETED | AA19: COMPLETED | AB19: COMPLETED | AC19: COMPLETED | AD19: COMPLETED | AE19: COMPLETED
A20: 12 | B20: 700012 | C20: Ada Donation Widget | D20: DID NOT FINISH | E20: 10000 | F20: 7500 | G20: =E20-F20 -> 2500 | H20: volibra | I20: F7: Mini/Low-Budget Dapps & Integrations | J20: TRUE | K20: TRUE | L20: TRUE | M20: TRUE | N20: FALSE | O20: FALSE | P20: FALSE | Q20: FALSE | R20: FALSE | S20: FALSE | T20: FALSE | U20: FALSE | V20: FALSE | W20: FALSE | X20: FALSE | Y20: FALSE | Z20: FALSE | AA20: FALSE | AB20: FALSE | AC20: FALSE | AD20: FALSE | AE20: FALSE
A21: 13 | B21: 700013 | C21: ADA Handle Wallet Authentication | D21: COMPLETED | E21: 45000 | F21: 45000 | G21: =E21-F21 -> 0 | H21: CONR₳D | I21: F7: DApps & Integrations | J21: FALSE | K21: TRUE | L21: FALSE | M21: FALSE | N21: FALSE | O21: FALSE | P21: COMPLETED | U21: COMPLETED | V21: COMPLETED | W21: COMPLETED | X21: COMPLETED | Y21: COMPLETED | Z21: COMPLETED | AA21: COMPLETED | AB21: COMPLETED | AC21: COMPLETED | AD21: COMPLETED | AE21: COMPLETED
A22: 14 | B22: 700014 | C22: Ada payment link generator | D22: DID NOT FINISH | E22: 10000 | F22: 7500 | G22: =E22-F22 -> 2500 | H22: volibra | I22: F7: Mini/Low-Budget Dapps & Integrations | J22: TRUE | K22: TRUE | L22: TRUE | M22: TRUE | N22: FALSE | O22: FALSE | P22: FALSE | Q22: FALSE | R22: FALSE | S22: FALSE | T22: FALSE | U22: FALSE | V22: FALSE | W22: FALSE | X22: FALSE | Y22: FALSE | Z22: FALSE | AA22: FALSE | AB22: FALSE | AC22: FALSE | AD22: FALSE | AE22: FALSE
A23: 15 | B23: 700015 | C23: ADA Payments for Joomla 3 & 4 | D23: COMPLETED | F23: 0 | G23: =E23-F23 -> 0 | H23: Carl Henry Global | I23: F7: Catalyst Natives COTI: Pay with ADA Plug-in | J23: TRUE | K23: TRUE | L23: COMPLETED | U23: COMPLETED | V23: COMPLETED | W23: COMPLETED | X23: COMPLETED | Y23: COMPLETED | Z23: COMPLETED | AA23: COMPLETED | AB23: COMPLETED | AC23: COMPLETED | AD23: COMPLETED | AE23: COMPLETED
A24: 16 | B24: 700016 | C24: ADAPlus - Pool Boost | D24: DID NOT FINISH | E24: 38100 | F24: 33867 | G24: =E24-F24 -> 4233 | H24: Igor [VICE] | I24: F7: Global Sustainable Indep. SPO's | J24: TRUE | K24: TRUE | L24: TRUE | M24: TRUE | N24: TRUE | O24: TRUE | P24: TRUE | Q24: TRUE | R24: TRUE | S24: FALSE | T24: FALSE | U24: FALSE | V24: FALSE | W24: FALSE | X24: FALSE | Y24: FALSE | Z24: FALSE | AA24: FALSE | AB24: FALSE | AC24: FALSE | AD24: FALSE | AE24: FALSE
A25: 17 | B25: 700017 | C25: After Town Hall by Catalyst Swarm | D25: COMPLETED | E25: 25000 | F25: 25000 | G25: =E25-F25 -> 0 | H25: Felix Weber | I25: F7: Community Events | J25: TRUE | K25: FALSE | L25: FALSE | M25: COMPLETED | U25: COMPLETED | V25: COMPLETED | W25: COMPLETED | X25: COMPLETED | Y25: COMPLETED | Z25: COMPLETED | AA25: COMPLETED | AB25: COMPLETED | AC25: COMPLETED | AD25: COMPLETED | AE25: COMPLETED
A26: 18 | B26: 700018 | C26: AI Resolution of Smart Contracts | D26: DID NOT FINISH | E26: 16000 | F26: 6000 | G26: =E26-F26 -> 10000 | H26: Ryan Sweeney | I26: F7: A.I. & SingularityNet a $5T market | J26: TRUE | K26: TRUE | L26: TRUE | M26: FALSE | N26: FALSE | O26: FALSE | P26: FALSE | Q26: FALSE | R26: FALSE | S26: FALSE | T26: FALSE | U26: FALSE | V26: FALSE | W26: FALSE | X26: FALSE | Y26: FALSE | Z26: FALSE | AA26: FALSE | AB26: FALSE | AC26: FALSE | AD26: FALSE | AE26: FALSE
A27: 19 | B27: 700019 | C27: ALDEA NFT - Community Marketplace | D27: COMPLETED | E27: 26850 | F27: 26850 | G27: =E27-F27 -> 0 | H27: Matias Falcone | I27: F7: Grow Latin America, Grow Cardano | J27: TRUE | K27: TRUE | L27: TRUE | M27: TRUE | N27: TRUE | O27: TRUE | P27: TRUE | Q27: TRUE | R27: FALSE | S27: FALSE | T27: FALSE | U27: FALSE | V27: FALSE | W27: FALSE | X27: FALSE | Y27: COMPLETED | Z27: COMPLETED | AA27: COMPLETED | AB27: COMPLETED | AC27: COMPLETED | AD27: COMPLETED | AE27: COMPLETED
A28: 20 | B28: 700020 | C28: An AI Domain Specific Language | D28: COMPLETED | E28: 79950 | F28: 79950 | G28: =E28-F28 -> 0 | H28: Matt Ikle | I28: F7: A.I. & SingularityNet a $5T market | J28: TRUE | K28: TRUE | L28: TRUE | M28: TRUE | N28: TRUE | O28: TRUE | P28: FALSE | Q28: COMPLETED | U28: COMPLETED | V28: COMPLETED | W28: COMPLETED | X28: COMPLETED | Y28: COMPLETED | Z28: COMPLETED | AA28: COMPLETED | AB28: COMPLETED | AC28: COMPLETED | AD28: COMPLETED | AE28: COMPLETED
A29: 21 | B29: 700021 | C29: Anonymity & data control online ZKT | D29: COMPLETED | E29: 25050 | F29: 25050 | G29: =E29-F29 -> 0 | H29: Michiel Van Roey | I29: F7: DApps & Integrations | J29: TRUE | K29: TRUE | L29: TRUE | M29: TRUE | N29: TRUE | O29: TRUE | P29: TRUE | Q29: TRUE | R29: TRUE | S29: TRUE | T29: TRUE | U29: TRUE | V29: TRUE | W29: TRUE | X29: TRUE | Y29: TRUE | Z29: TRUE | AA29: TRUE | AB29: TRUE | AC29: FALSE | AD29: FALSE | AE29: FALSE
A30: 22 | B30: 700022 | C30: Atala Japanese Translation ＆ CNFT | D30: COMPLETED | E30: 50000 | F30: 50000 | G30: =E30-F30 -> 0 | H30: kuni | I30: F7: Accelerate Decentralized Identity | J30: TRUE | K30: FALSE | L30: TRUE | M30: TRUE | N30: TRUE | O30: TRUE | P30: TRUE | Q30: FALSE | R30: FALSE | S30: FALSE | T30: TRUE | U30: TRUE | V30: TRUE | W30: COMPLETED | X30: COMPLETED | Y30: COMPLETED | Z30: COMPLETED | AA30: COMPLETED | AB30: COMPLETED | AC30: COMPLETED | AD30: COMPLETED | AE30: COMPLETED
A31: 23 | B31: 700023 | C31: AVOUM on Cardano | D31: COMPLETED | E31: 26500 | F31: 26500 | G31: =E31-F31 -> 0 | H31: Alexander Smart | I31: F7: Seeding Cardano's Grassroots DeFi | J31: TRUE | K31: FALSE | L31: FALSE | M31: FALSE | N31: FALSE | O31: FALSE | P31: FALSE | Q31: FALSE | R31: FALSE | S31: FALSE | T31: COMPLETED | U31: COMPLETED | V31: COMPLETED | W31: COMPLETED | X31: COMPLETED | Y31: COMPLETED | Z31: COMPLETED | AA31: COMPLETED | AB31: COMPLETED | AC31: COMPLETED | AD31: COMPLETED | AE31: COMPLETED
A32: 24 | B32: 700024 | C32: Basic Plutus Voting dApp | D32: COMPLETED | E32: 15000 | F32: 15000 | G32: =E32-F32 -> 0 | H32: dcSpark | I32: F7: DAOs ❤ Cardano | J32: FALSE | K32: TRUE | L32: TRUE | M32: COMPLETED | U32: COMPLETED | V32: COMPLETED | W32: COMPLETED | X32: COMPLETED | Y32: COMPLETED | Z32: COMPLETED | AA32: COMPLETED | AB32: COMPLETED | AC32: COMPLETED | AD32: COMPLETED | AE32: COMPLETED
A33: 25 | B33: 700025 | C33: Beyond ISOs: SPO-driven Funding | D33: DID NOT FINISH | E33: 35300 | F33: 30257 | G33: =E33-F33 -> 5043 | H33: gargiulo.gianni | I33: F7: New SPO Business Opportunities | J33: TRUE | K33: TRUE | L33: TRUE | M33: TRUE | N33: FALSE | O33: TRUE | P33: FALSE | Q33: FALSE | R33: FALSE | S33: FALSE | T33: FALSE | U33: FALSE | V33: FALSE | W33: FALSE | X33: FALSE | Y33: FALSE | Z33: FALSE | AA33: FALSE | AB33: FALSE | AC33: FALSE | AD33: FALSE | AE33: FALSE
A34: 26 | B34: 700026 | C34: Bridge Builders - Governance Events | D34: COMPLETED | E34: 18000 | F34: 18000 | G34: =E34-F34 -> 0 | H34: Felix Weber | I34: F7: Community Events | J34: TRUE | K34: TRUE | L34: FALSE | M34: FALSE | N34: FALSE | O34: FALSE | P34: FALSE | Q34: FALSE | R34: FALSE | S34: FALSE | T34: FALSE | U34: FALSE | V34: FALSE | W34: FALSE | X34: FALSE | Y34: FALSE | Z34: FALSE | AA34: FALSE | AB34: FALSE | AC34: FALSE | AD34: FALSE | AE34: COMPLETED
A35: 27 | B35: 700027 | C35: Bridge Builders Mentorship Program | D35: COMPLETED | E35: 60000 | F35: 60000 | G35: =E35-F35 -> 0 | H35: Felix Weber | I35: F7: Catalyst Accelerator & Mentors | J35: TRUE | K35: TRUE | L35: FALSE | M35: FALSE | N35: COMPLETED | U35: COMPLETED | V35: COMPLETED | W35: COMPLETED | X35: COMPLETED | Y35: COMPLETED | Z35: COMPLETED | AA35: COMPLETED | AB35: COMPLETED | AC35: COMPLETED | AD35: COMPLETED | AE35: COMPLETED
A36: 28 | B36: 700028 | C36: Browser tool- How to use DeFi dApps | D36: COMPLETED | E36: 49800 | F36: 49800 | G36: =E36-F36 -> 0 | H36: Ben Mesnik | I36: F7: Seeding Cardano's Grassroots DeFi | J36: TRUE | K36: TRUE | L36: TRUE | M36: TRUE | N36: TRUE | O36: TRUE | P36: TRUE | Q36: TRUE | R36: TRUE | S36: TRUE | T36: TRUE | U36: FALSE | V36: FALSE | W36: COMPLETED | X36: COMPLETED | Y36: COMPLETED | Z36: COMPLETED | AA36: COMPLETED | AB36: COMPLETED | AC36: COMPLETED | AD36: COMPLETED | AE36: COMPLETED
A37: 29 | B37: 700029 | C37: Build out 14 Digital Language Hubs | D37: DID NOT FINISH | E37: 17500 | F37: 11667 | G37: =E37-F37 -> 5833 | H37: Mike D | I37: F7: Scale-UP Cardano's Community Hubs | J37: TRUE | K37: TRUE | L37: TRUE | M37: FALSE | N37: TRUE | O37: FALSE | P37: FALSE | Q37: FALSE | R37: FALSE | S37: FALSE | T37: FALSE | U37: FALSE | V37: FALSE | W37: FALSE | X37: FALSE | Y37: FALSE | Z37: FALSE | AA37: FALSE | AB37: FALSE | AC37: FALSE | AD37: FALSE | AE37: FALSE
A38: 30 | B38: 700030 | C38: Carbon as DeFi Asset | BlockCarbon | D38: COMPLETED | E38: 30000 | F38: 30000 | G38: =E38-F38 -> 0 | H38: Thomas Wedler | I38: F7: Boosting Cardano's DeFi | J38: TRUE | K38: TRUE | L38: TRUE | M38: TRUE | N38: FALSE | O38: FALSE | P38: FALSE | Q38: FALSE | R38: FALSE | S38: TRUE | T38: FALSE | U38: FALSE | V38: FALSE | W38: FALSE | X38: COMPLETED | Y38: COMPLETED | Z38: COMPLETED | AA38: COMPLETED | AB38: COMPLETED | AC38: COMPLETED | AD38: COMPLETED | AE38: COMPLETED
A39: 31 | B39: 700031 | C39: CardaBot: telegram bot with tipping | D39: COMPLETED | E39: 10000 | F39: 10000 | G39: =E39-F39 -> 0 | H39: Lincon Vidal | I39: F7: Mini/Low-Budget Dapps & Integrations | J39: TRUE | K39: TRUE | L39: TRUE | M39: TRUE | N39: TRUE | O39: TRUE | P39: FALSE | Q39: COMPLETED | U39: COMPLETED | V39: COMPLETED | W39: COMPLETED | X39: COMPLETED | Y39: COMPLETED | Z39: COMPLETED | AA39: COMPLETED | AB39: COMPLETED | AC39: COMPLETED | AD39: COMPLETED | AE39: COMPLETED
A40: 32 | B40: 700032 | C40: Cardano After Dark - Hold'em poker | D40: COMPLETED | E40: 40000 | F40: 40000 | G40: =E40-F40 -> 0 | H40: card.afterdark | I40: F7: Gamers On-Chained | J40: TRUE | K40: TRUE | L40: TRUE | M40: TRUE | N40: TRUE | O40: TRUE | P40: FALSE | Q40: FALSE | R40: FALSE | S40: FALSE | T40: FALSE | U40: FALSE | V40: FALSE | W40: FALSE | X40: FALSE | Y40: FALSE | Z40: FALSE | AA40: FALSE | AB40: FALSE | AC40: FALSE | AD40: FALSE | AE40: FALSE
A41: 33 | B41: 700033 | C41: Cardano Ambassadors & Latin America | D41: COMPLETED | E41: 35500 | F41: 35500 | G41: =E41-F41 -> 0 | H41: Felix Weber | I41: F7: Grow Latin America, Grow Cardano | J41: TRUE | K41: FALSE | L41: TRUE | M41: FALSE | N41: FALSE | O41: FALSE | P41: COMPLETED | U41: COMPLETED | V41: COMPLETED | W41: COMPLETED | X41: COMPLETED | Y41: COMPLETED | Z41: COMPLETED | AA41: COMPLETED | AB41: COMPLETED | AC41: COMPLETED | AD41: COMPLETED | AE41: COMPLETED
A42: 34 | B42: 700034 | C42: Cardano Ambassadors Catalyst Guild | D42: COMPLETED | E42: 10000 | F42: 10000 | G42: =E42-F42 -> 0 | H42: Felix Weber | I42: F7: Miscellaneous Challenge | J42: TRUE | K42: FALSE | L42: FALSE | M42: TRUE | N42: FALSE | O42: FALSE | P42: COMPLETED | U42: COMPLETED | V42: COMPLETED | W42: COMPLETED | X42: COMPLETED | Y42: COMPLETED | Z42: COMPLETED | AA42: COMPLETED | AB42: COMPLETED | AC42: COMPLETED | AD42: COMPLETED | AE42: COMPLETED
A43: 35 | B43: 700035 | C43: Cardano Blockchain Lab in Kenya | D43: COMPLETED | E43: 38255 | F43: 38255 | G43: =E43-F43 -> 0 | H43: Darlington Wleh | I43: F7: Scale-UP Cardano's Community Hubs | J43: TRUE | K43: TRUE | L43: TRUE | M43: TRUE | N43: TRUE | O43: TRUE | P43: TRUE | Q43: TRUE | R43: TRUE | S43: TRUE | T43: COMPLETED | U43: COMPLETED | V43: COMPLETED | W43: COMPLETED | X43: COMPLETED | Y43: COMPLETED | Z43: COMPLETED | AA43: COMPLETED | AB43: COMPLETED | AC43: COMPLETED | AD43: COMPLETED | AE43: COMPLETED
A44: 36 | B44: 700036 | C44: Cardano Builders' Hub India | D44: COMPLETED | E44: 25000 | F44: 25000 | G44: =E44-F44 -> 0 | H44: Reshm | I44: F7: Scale-UP Cardano's Community Hubs | J44: TRUE | K44: TRUE | L44: TRUE | M44: TRUE | N44: TRUE | O44: TRUE | P44: FALSE | Q44: FALSE | R44: COMPLETED | U44: COMPLETED | V44: COMPLETED | W44: COMPLETED | X44: COMPLETED | Y44: COMPLETED | Z44: COMPLETED | AA44: COMPLETED | AB44: COMPLETED | AC44: COMPLETED | AD44: COMPLETED | AE44: COMPLETED
A45: 37 | B45: 700037 | C45: Cardano Catalyst TV | D45: COMPLETED | E45: 3900 | F45: 3900 | G45: =E45-F45 -> 0 | H45: Mie Tran | I45: F7: Multilingual resources | J45: TRUE | K45: TRUE | L45: FALSE | M45: FALSE | N45: COMPLETED | U45: COMPLETED | V45: COMPLETED | W45: COMPLETED | X45: COMPLETED | Y45: COMPLETED | Z45: COMPLETED | AA45: COMPLETED | AB45: COMPLETED | AC45: COMPLETED | AD45: COMPLETED | AE45: COMPLETED
A46: 38 | B46: 700038 | C46: Cardano Center Poland web & socials | D46: COMPLETED | E46: 8000 | F46: 8000 | G46: =E46-F46 -> 0 | H46: Kornel | I46: F7: Multilingual resources | J46: TRUE | K46: TRUE | L46: TRUE | M46: TRUE | N46: TRUE | O46: TRUE | P46: COMPLETED | U46: COMPLETED | V46: COMPLETED | W46: COMPLETED | X46: COMPLETED | Y46: COMPLETED | Z46: COMPLETED | AA46: COMPLETED | AB46: COMPLETED | AC46: COMPLETED | AD46: COMPLETED | AE46: COMPLETED
A47: 39 | B47: 700039 | C47: Cardano for STEM Brazilian students | D47: COMPLETED | E47: 7500 | F47: 7500 | G47: =E47-F47 -> 0 | H47: Gilvânia Vilela | I47: F7: Grow Latin America, Grow Cardano | J47: TRUE | K47: TRUE | L47: COMPLETED | U47: COMPLETED | V47: COMPLETED | W47: COMPLETED | X47: COMPLETED | Y47: COMPLETED | Z47: COMPLETED | AA47: COMPLETED | AB47: COMPLETED | AC47: COMPLETED | AD47: COMPLETED | AE47: COMPLETED
A48: 40 | B48: 700040 | C48: Cardano games assets for Unity | D48: COMPLETED | E48: 57000 | F48: 57000 | G48: =E48-F48 -> 0 | H48: Five Binaries | I48: F7: Gamers On-Chained | J48: TRUE | K48: TRUE | L48: TRUE | M48: TRUE | N48: TRUE | O48: COMPLETED | U48: COMPLETED | V48: COMPLETED | W48: COMPLETED | X48: COMPLETED | Y48: COMPLETED | Z48: COMPLETED | AA48: COMPLETED | AB48: COMPLETED | AC48: COMPLETED | AD48: COMPLETED | AE48: COMPLETED
A49: 41 | B49: 700041 | C49: Cardano Hub Indonesia - Workshops | D49: COMPLETED | E49: 10777 | F49: 10777 | G49: =E49-F49 -> 0 | H49: Andreas Sosilo | I49: F7: Scale-UP Cardano's Community Hubs | J49: TRUE | K49: TRUE | L49: TRUE | M49: TRUE | N49: TRUE | O49: TRUE | P49: TRUE | Q49: TRUE | R49: TRUE | S49: TRUE | T49: TRUE | U49: FALSE | V49: FALSE | W49: FALSE | X49: FALSE | Y49: FALSE | Z49: FALSE | AA49: FALSE | AB49: FALSE | AC49: FALSE | AD49: TRUE | AE49: TRUE
A50: 42 | B50: 700042 | C50: Cardano in Spanish | D50: COMPLETED | E50: 6000 | F50: 6000 | G50: =E50-F50 -> 0 | H50: Seba (Spanish Translator) | I50: F7: Multilingual resources | J50: TRUE | K50: TRUE | L50: TRUE | M50: TRUE | N50: TRUE | O50: TRUE | P50: COMPLETED | U50: COMPLETED | V50: COMPLETED | W50: COMPLETED | X50: COMPLETED | Y50: COMPLETED | Z50: COMPLETED | AA50: COMPLETED | AB50: COMPLETED | AC50: COMPLETED | AD50: COMPLETED | AE50: COMPLETED
A51: 43 | B51: 700043 | C51: Cardano Interop NOW | D51: DID NOT FINISH | E51: 28000 | F51: 4667 | G51: =E51-F51 -> 23333 | H51: Chris Raczkowski | I51: F7: Accelerate Decentralized Identity | J51: FALSE | K51: FALSE | L51: FALSE | M51: FALSE | N51: FALSE | O51: FALSE | P51: FALSE | Q51: FALSE | R51: FALSE | S51: FALSE | T51: FALSE | U51: FALSE | V51: FALSE | W51: FALSE | X51: FALSE | Y51: FALSE | Z51: FALSE | AA51: FALSE | AB51: FALSE | AC51: FALSE | AD51: FALSE | AE51: FALSE
A52: 44 | B52: 700044 | C52: Cardano Mobile Hubs | D52: COMPLETED | E52: 30000 | F52: 30000 | G52: =E52-F52 -> 0 | H52: Josh F | I52: F7: Scale-UP Cardano's Community Hubs | J52: TRUE | K52: TRUE | L52: TRUE | M52: TRUE | N52: TRUE | O52: TRUE | P52: TRUE | Q52: TRUE | R52: TRUE | S52: FALSE | T52: FALSE | U52: FALSE | V52: FALSE | W52: FALSE | X52: FALSE | Y52: FALSE | Z52: FALSE | AA52: FALSE | AB52: FALSE | AC52: FALSE | AD52: FALSE | AE52: FALSE
A53: 45 | B53: 700045 | C53: Cardano Multi-DEX SDK | D53: COMPLETED | E53: 21900 | F53: 21900 | G53: =E53-F53 -> 0 | H53: Indigo Labs | I53: F7: Boosting Cardano's DeFi | J53: TRUE | K53: TRUE | L53: TRUE | M53: TRUE | N53: FALSE | O53: TRUE | P53: TRUE | Q53: TRUE | R53: FALSE | S53: FALSE | T53: FALSE | U53: FALSE | V53: FALSE | W53: FALSE | X53: FALSE | Y53: COMPLETED | Z53: COMPLETED | AA53: COMPLETED | AB53: COMPLETED | AC53: COMPLETED | AD53: COMPLETED | AE53: COMPLETED
A54: 46 | B54: 700046 | C54: Cardano NFT Art Festival | D54: COMPLETED | E54: 10000 | F54: 10000 | G54: =E54-F54 -> 0 | H54: Timothy Vang | I54: F7: Connecting Japan/日本 Community | J54: TRUE | K54: TRUE | L54: FALSE | M54: COMPLETED | U54: COMPLETED | V54: COMPLETED | W54: COMPLETED | X54: COMPLETED | Y54: COMPLETED | Z54: COMPLETED | AA54: COMPLETED | AB54: COMPLETED | AC54: COMPLETED | AD54: COMPLETED | AE54: COMPLETED
A55: 47 | B55: 700047 | C55: Cardano Omnibus - UTXO Management | D55: COMPLETED | E55: 40000 | F55: 40000 | G55: =E55-F55 -> 0 | H55: dcSpark | I55: F7: Open Source Developer Ecosystem | J55: FALSE | K55: TRUE | L55: TRUE | M55: FALSE | N55: FALSE | O55: FALSE | P55: FALSE | Q55: FALSE | R55: FALSE | S55: FALSE | T55: COMPLETED | U55: COMPLETED | V55: COMPLETED | W55: COMPLETED | X55: COMPLETED | Y55: COMPLETED | Z55: COMPLETED | AA55: COMPLETED | AB55: COMPLETED | AC55: COMPLETED | AD55: COMPLETED | AE55: COMPLETED
A56: 48 | B56: 700048 | C56: CARDANO SCAMWATCH TASK FORCE | D56: DID NOT FINISH | E56: 3627 | F56: 0 | G56: =E56-F56 -> 3627 | H56: sergio.sp | I56: F7: Disarm cyber disinformation attacks | J56: FALSE | K56: FALSE | L56: FALSE | M56: FALSE | N56: FALSE | O56: FALSE | P56: FALSE | Q56: FALSE | R56: FALSE | S56: FALSE | T56: FALSE | U56: FALSE | V56: FALSE | W56: FALSE | X56: FALSE | Y56: FALSE | Z56: FALSE | AA56: FALSE | AB56: FALSE | AC56: FALSE | AD56: FALSE | AE56: FALSE
A57: 49 | B57: 700049 | C57: Cardano Subnet/VM Avalanche Bridge | D57: COMPLETED | E57: 9600 | F57: 9600 | G57: =E57-F57 -> 0 | H57: NFT-DAO (the whole team) | I57: F7: Boosting Cardano's DeFi | J57: TRUE | K57: TRUE | L57: TRUE | M57: TRUE | N57: TRUE | O57: TRUE | P57: COMPLETED | U57: COMPLETED | V57: COMPLETED | W57: COMPLETED | X57: COMPLETED | Y57: COMPLETED | Z57: COMPLETED | AA57: COMPLETED | AB57: COMPLETED | AC57: COMPLETED | AD57: COMPLETED | AE57: COMPLETED
A58: 50 | B58: 700050 | C58: Cardano Technical hub in Vietnamese | D58: COMPLETED | E58: 23960 | F58: 23960 | G58: =E58-F58 -> 0 | H58: tienna | I58: F7: Scale-UP Cardano's Community Hubs | J58: TRUE | K58: TRUE | L58: TRUE | M58: TRUE | N58: TRUE | O58: COMPLETED | U58: COMPLETED | V58: COMPLETED | W58: COMPLETED | X58: COMPLETED | Y58: COMPLETED | Z58: COMPLETED | AA58: COMPLETED | AB58: COMPLETED | AC58: COMPLETED | AD58: COMPLETED | AE58: COMPLETED
A59: 51 | B59: 700051 | C59: Cardano Text Resources in Chinese | D59: COMPLETED | E59: 5572 | F59: 5572 | G59: =E59-F59 -> 0 | H59: Bullish Dumpling | I59: F7: Multilingual resources | J59: TRUE | K59: TRUE | L59: TRUE | M59: FALSE | N59: FALSE | O59: FALSE | P59: FALSE | Q59: FALSE | R59: FALSE | S59: FALSE | T59: FALSE | U59: FALSE | V59: FALSE | W59: FALSE | X59: FALSE | Y59: FALSE | Z59: COMPLETED | AA59: COMPLETED | AB59: COMPLETED | AC59: COMPLETED | AD59: COMPLETED | AE59: COMPLETED
A60: 52 | B60: 700052 | C60: Cardano Totem: Onboarding the World | D60: COMPLETED | E60: 40500 | F60: 40500 | G60: =E60-F60 -> 0 | H60: Adriano Fiorenza | I60: F7: Grow Latin America, Grow Cardano | J60: TRUE | K60: TRUE | L60: TRUE | M60: TRUE | N60: TRUE | O60: TRUE | P60: COMPLETED | U60: COMPLETED | V60: COMPLETED | W60: COMPLETED | X60: COMPLETED | Y60: COMPLETED | Z60: COMPLETED | AA60: COMPLETED | AB60: COMPLETED | AC60: COMPLETED | AD60: COMPLETED | AE60: COMPLETED
A61: 53 | B61: 700053 | C61: Cardano Worldwide Community Hubs | D61: COMPLETED | E61: 9636 | F61: 9636 | G61: =E61-F61 -> 0 | H61: Carl Henry Global | I61: F7: Scale-UP Cardano's Community Hubs | J61: TRUE | K61: COMPLETED | U61: COMPLETED | V61: COMPLETED | W61: COMPLETED | X61: COMPLETED | Y61: COMPLETED | Z61: COMPLETED | AA61: COMPLETED | AB61: COMPLETED | AC61: COMPLETED | AD61: COMPLETED | AE61: COMPLETED
A62: 54 | B62: 700054 | C62: Cardano4Climate Community Events | D62: COMPLETED | E62: 4181 | F62: 4181 | G62: =E62-F62 -> 0 | H62: cardano4climate | I62: F7: Community Events | J62: TRUE | K62: TRUE | L62: TRUE | M62: FALSE | N62: FALSE | O62: FALSE | P62: COMPLETED | U62: COMPLETED | V62: COMPLETED | W62: COMPLETED | X62: COMPLETED | Y62: COMPLETED | Z62: COMPLETED | AA62: COMPLETED | AB62: COMPLETED | AC62: COMPLETED | AD62: COMPLETED | AE62: COMPLETED
A63: 55 | B63: 700055 | C63: Cardano4Climate Community Hub | D63: COMPLETED | E63: 6765 | F63: 6765 | G63: =E63-F63 -> 0 | H63: cardano4climate | I63: F7: Scale-UP Cardano's Community Hubs | J63: TRUE | K63: TRUE | L63: TRUE | M63: FALSE | N63: FALSE | O63: FALSE | P63: COMPLETED | U63: COMPLETED | V63: COMPLETED | W63: COMPLETED | X63: COMPLETED | Y63: COMPLETED | Z63: COMPLETED | AA63: COMPLETED | AB63: COMPLETED | AC63: COMPLETED | AD63: COMPLETED | AE63: COMPLETED
A64: 56 | B64: 700056 | C64: CardanoRio 2022: Hybrid event | D64: COMPLETED | E64: 17501 | F64: 17501 | G64: =E64-F64 -> 0 | H64: Lincon Vidal | I64: F7: Grow Latin America, Grow Cardano | J64: TRUE | K64: TRUE | L64: TRUE | M64: TRUE | N64: TRUE | O64: TRUE | P64: TRUE | Q64: FALSE | R64: FALSE | S64: COMPLETED | U64: COMPLETED | V64: COMPLETED | W64: COMPLETED | X64: COMPLETED | Y64: COMPLETED | Z64: COMPLETED | AA64: COMPLETED | AB64: COMPLETED | AC64: COMPLETED | AD64: COMPLETED | AE64: COMPLETED
A65: 57 | B65: 700057 | C65: Case Study: Yomi.ai & Ada Pay | D65: PENDING | F65: 0 | G65: =E65-F65 -> 0 | H65: Matthias Sieber | I65: F7: Catalyst Natives COTI: Pay with ADA Plug-in | J65: TRUE | K65: TRUE | L65: TRUE | M65: TRUE | N65: TRUE | O65: FALSE | P65: FALSE | Q65: FALSE | R65: FALSE | S65: FALSE | T65: FALSE | U65: FALSE | V65: FALSE | W65: FALSE | X65: FALSE | Y65: FALSE | Z65: FALSE | AA65: FALSE | AB65: FALSE | AC65: FALSE | AD65: FALSE | AE65: FALSE
A66: 58 | B66: 700058 | C66: Catalyst Audit Circle | D66: COMPLETED | E66: 12700 | F66: 12700 | G66: =E66-F66 -> 0 | H66: Stephen Whitenstall | I66: F7: Improve and Grow Auditability | J66: TRUE | K66: TRUE | L66: TRUE | M66: FALSE | N66: FALSE | O66: FALSE | P66: FALSE | Q66: FALSE | R66: FALSE | S66: FALSE | T66: FALSE | U66: COMPLETED | V66: COMPLETED | W66: COMPLETED | X66: COMPLETED | Y66: COMPLETED | Z66: COMPLETED | AA66: COMPLETED | AB66: COMPLETED | AC66: COMPLETED | AD66: COMPLETED | AE66: COMPLETED
